Workbook

Sheet README
A1: GNMA Project Loan Prepayment Model
A3: PURPOSE
A4: This workbook predicts monthly SMM (Single Monthly Mortality) and annualized CPR (Conditional Prepayment Rate) for individual GNMA multifamily project loans, then aggregates loans up to the GNR REMIC deal level so deals can be compared and the drivers of speed differences can be isolated.
A6: HOW TO USE
A7: 1. Open the Loan_Input sheet.
A8: 2. Replace the demo data (rows 2 and below) with your own loan-level data. At minimum you need: deal_id, loan_rate, upb, dates (origination, maturity, lockout end, prepay end), prepay penalty period, FHA program code, affordable status, modified/non-level/mature flags, period (YYYYMM). All formulas to the right derive features and predict CPR automatically.
A9: 3. Yellow cells are user input. Green cells are derived/computed. Orange cells are per-component attribution.
A10: 4. The Deal_Summary sheet aggregates loans by deal_id with weighted averages. The Deal_Comparison sheet displays the underlying drivers of CPR differences across deals side-by-side.
A11: 5. To override a model coefficient (e.g. for a stress scenario), edit the corresponding cell on Parameters.
A13: MODEL ARCHITECTURE
A14: Trained on 932,014 loan-month observations from 201812 through 202406 (8,881 voluntary prepay events). Held-out test: 308,876 observations from 202407 through 202603.
A16: Functional form: logistic regression on engineered piecewise-linear splines. log( SMM/(1-SMM) ) = intercept + Σ contributions. Each contribution maps cleanly to an Excel formula and to a CPR attribution.
... A50: Blue cells = parameter / coefficient

Sheet Parameters
A1: Parameter | B1: Value | C1: Description
A2: INTERCEPT | B2: -6.5830653 | C2: Logistic intercept; baseline log-odds when all features = 0.
A3: OPTIONAL_CPR_SCALAR | B3: 1 | C3: Multiplier on final predicted SMM. Use 1.0 for the unbiased model; use <1 to dampen if you believe the regime is more out-of-money than training; >1 for stress.
A5: Component | B5: Feature | C5: Coefficient | D5: Description
A6: REFI | B6: refi_lin | C6: 0.0043203709 | D6: Linear slope of refi incentive in bps
A7: REFI | B7: refi_k-150 | C7: 0.0022721146 | D7: Hinge: extra slope past −150 bps incentive
A8: REFI | B8: refi_k-50 | C8: 0.0017670998 | D8: Hinge: extra slope past −50 bps incentive
A9: REFI | B9: refi_k0 | C9: 0.00091223458 | D9: Hinge: extra slope past 0 bps (at-money)
A10: REFI | B10: refi_k50 | C10: -0.0015626207 | D10: Hinge: extra slope past +50 bps incentive
A11: REFI | B11: refi_k100 | C11: -0.0034164295 | D11: Hinge: extra slope past +100 bps incentive
A12: REFI | B12: refi_k150 | C12: -0.0023538754 | D12: Hinge: extra slope past +150 bps incentive
A13: REFI | B13: refi_k250 | C13: -0.00097698167 | D13: Hinge: extra slope past +250 bps incentive
A14: AGE | B14: age_lin | C14: 0.0059010869 | D14: Linear slope of loan age (months)
A15: AGE | B15: age_k12 | C15: 0.005360449 | D15: Hinge: extra slope past 12 months age
A16: AGE | B16: age_k36 | C16: 0.00056806319 | D16: Hinge: extra slope past 36 months age
A17: AGE | B17: age_k60 | C17: -0.0029967448 | D17: Hinge: extra slope past 60 months age
... A59: POOL | B59: is_rx_pool | C59: -0.47853494 | D59: Pool type = RX (Mark-to-Market)

Sheet PLC_Rates
A1: period | B1: PLC_rate_bps
A2: 201812 | B2: 354
A3: 201901 | B3: 352
A4: 201902 | B4: 355
A5: 201903 | B5: 328
A6: 201904 | B6: 319
A7: 201905 | B7: 279
A8: 201906 | B8: 276
A9: 201907 | B9: 264
A10: 201908 | B10: 228
A11: 201909 | B11: 245
A12: 201910 | B12: 242
A13: 201911 | B13: 262
... A89: 202603 | B89: 490.5

Sheet Vintage_Rates
A1: vintage_year | B1: median_loan_rate_pct | C1: n_loans
A2: 1990 | B2: 4.52 | C2: 1
A3: 1991 | B3: 3.785 | C3: 2
A4: 1992 | B4: 3.78 | C4: 4
A5: 1994 | B5: 3.58 | C5: 7
A6: 1995 | B6: 4.22 | C6: 9
A7: 1996 | B7: 3.6975 | C7: 4
A8: 1997 | B8: 3.53 | C8: 10
A9: 1998 | B9: 5.85 | C9: 19
A10: 1999 | B10: 6 | C10: 28
A11: 2000 | B11: 6 | C11: 13
A12: 2001 | B12: 7.5 | C12: 66
A13: 2002 | B13: 6.75 | C13: 139
... A37: 2026 | B37: 5.5 | C37: 106

Sheet FHA_Lookup
A1: search_substring | B1: fha_category | C1: loan_purpose
A2: 538 | B2: 538 | C2: 538
A3: 232 | B3: 232 | C3: NC
A4: 223(F) | B4: 223f | C4: RP
A5: 223F | B5: 223f | C5: RP
A6: 223(A) | B6: 223a7 | C6: RP
A7: 223A | B7: 223a7 | C7: RP
A8: 221(D) | B8: 221d4 | C8: NC
A9: 221D | B9: 221d4 | C9: NC
A10: 220 | B10: 220 | C10: NC
A11: 241 | B11: 241 | C11: NC

Sheet Loan_Input
A1: LOAN INPUTS — replace with your data | AA1: DERIVED FEATURES — auto-computed | BF1: LOG-ODDS CONTRIBUTIONS — by component | BS1: PREDICTED CPR & ATTRIBUTION
A2: deal_id | B2: pool_cusip | C2: pool_type | D2: issuer_name | E2: loan_id | F2: period | G2: loan_rate_pct | H2: upb | I2: loan_term_months | J2: origination_date | K2: loan_maturity_date | L2: lockout_end_date | M2: prepay_end_date | N2: prepay_premium_period_yrs | O2: fha_program_code | P2: affordable_status | Q2: modified_ind | R2: non_level_ind | S2: mature_loan_flag | T2: property_state | U2: num_units | V2: plc_rate_bps_input | W2: loan_age_months_input | X2: vintage_year_input | Y2: sato_bps_input | Z2: prepay_penalty_points_input | AA2: loan_age_months | AB2: months_to_maturity | AC2: months_post_lockout | AD2: in_lockout | AE2: in_prepay_penalty | AF2: past_all_restrictions | AG2: vintage_year | AH2: vintage_median_rate | AI2: sato_bps | AJ2: plc_rate_bps | AK2: prepay_penalty_points | AL2: gross_refi_incentive_bps | AM2: refi_incentive_bps | AN2: upb_millions | AO2: fha_category | AP2: loan_purpose | AQ2: is_nc | AR2: aff_aff | AS2: aff_baf | AT2: aff_mkt | AU2: fha_221d4 | AV2: fha_223a7 | AW2: fha_232 | AX2: fha_538 | AY2: fha_241 | AZ2: fha_220 | BA2: fha_other | BB2: is_lm_pool | BC2: is_pn_pool | BD2: is_ls_pool | BE2: is_rx_pool | BF2: REFI_logodds | BG2: AGE_logodds | BH2: PEN_logodds | BI2: SATO_logodds | BJ2: SIZE_logodds | BK2: M2M_logodds | BL2: MPL_logodds | BM2: INTERACT_logodds | BN2: PHASE_logodds | BO2: FHA_logodds | BP2: PURPOSE_logodds | BQ2: AFF_logodds | BR2: POOL_logodds | BS2: intercept_logodds | BT2: total_logodds | BU2: predicted_SMM | BV2: predicted_CPR_pct | BW2: baseline_CPR_pct | BX2: CPR_attr_REFI | BY2: CPR_attr_AGE | BZ2: CPR_attr_PEN | CA2: CPR_attr_SATO | CB2: CPR_attr_SIZE | CC2: CPR_attr_M2M | CD2: CPR_attr_MPL | CE2: CPR_attr_INTERACT | CF2: CPR_attr_PHASE | CG2: CPR_attr_FHA | CH2: CPR_attr_PURPOSE | CI2: CPR_attr_AFF | CJ2: CPR_attr_POOL
A3: GNR_2024_NEW | B3: 3618M3XD2 | C3: PN | D3: VIUM CAPITAL MORTGAGE, LLC. | E3: 3618M3XD2_000000006422141 | F3: 202603 | G3: 5.69 | H3: 24499232 | I3: 420 | J3: 20251201 | K3: 20610101 | M3: 20360201 | N3: 10 | O3: 232/223(F) | T3: LA | U3: 63 | V3: 490.5 | W3: 3 | X3: 2025 | Y3: -13 | Z3: 10 | AA3: =IF(ISNUMBER(W3),W3,IFERROR(MAX(0,(VALUE(LEFT(F3,4))-VALUE(LEFT(TEXT(J3,"00000000"),4)))*12+(VALUE(MID(F3,5,2))-VALUE(MID(TEXT(J3,"00000000"),5,2)))),"")) | AB3: =IFERROR((VALUE(LEFT(TEXT(K3,"00000000"),4))-VALUE(LEFT(F3,4)))*12+(VALUE(MID(TEXT(K3,"00000000"),5,2))-VALUE(MID(F3,5,2))),"") | AC3: =IF(OR(L3="",NOT(ISNUMBER(L3))),0,MAX(0,MIN(60,(VALUE(LEFT(F3,4))-VALUE(LEFT(TEXT(L3,"00000000"),4)))*12+(VALUE(MID(F3,5,2))-VALUE(MID(TEXT(L3,"00000000"),5,2)))))) | AD3: =IF(OR(L3="",NOT(ISNUMBER(L3))),0,IF(VALUE(F3)<VALUE(LEFT(TEXT(L3,"00000000"),6)),1,0)) | AE3: =IF(OR(M3="",NOT(ISNUMBER(M3))),0,IF(VALUE(F3)<VALUE(LEFT(TEXT(M3,"00000000"),6)),1,0)) | AF3: =IF(AND(AD3=0,AE3=0),1,0) | AG3: =IF(ISNUMBER(X3),X3,IFERROR(VALUE(LEFT(TEXT(J3,"00000000"),4)),"")) | AH3: =IFERROR(XLOOKUP(AG3,Vintage_Rates!$A$2:$A$1000,Vintage_Rates!$B$2:$B$1000,""),"") | AI3: =IF(ISNUMBER(Y3),Y3,IFERROR((G3-AH3)*100,"")) | AJ3: =IF(ISNUMBER(V3),V3,IFERROR(XLOOKUP(VALUE(F3),PLC_Rates!$A$2:$A$1000,PLC_Rates!$B$2:$B$1000,""),"")) | AK3: =IF(ISNUMBER(Z3),Z3,IF(AE3=0,0,MAX(0,MIN(10,((VALUE(LEFT(TEXT(M3,"00000000"),4))-VALUE(LEFT(F3,4)))*12+(VALUE(MID(TEXT(M3,"00000000"),5,2))-VALUE(MID(F3,5,2))))/12)))) | AL3: =IFERROR(G3*100-AJ3,"") | AM3: =IFERROR(G3*100-(AJ3+(1+AK3)*12.5),"") | AN3: =IFERROR(MIN(H3/1000000,100),"") | AO3: =IFERROR(INDEX(FHA_Lookup!$B$2:$B$11,MATCH(TRUE,ISNUMBER(SEARCH(FHA_Lookup!$A$2:$A$11,UPPER(SUBSTITUTE(O3," ","")))),0)),"OTHER") | AP3: =IFERROR(INDEX(FHA_Lookup!$C$2:$C$11,MATCH(TRUE,ISNUMBER(SEARCH(FHA_Lookup!$A$2:$A$11,UPPER(SUBSTITUTE(O3," ","")))),0)),"OTHER") | AQ3: =IF(AP3="NC",1,0) | AR3: =IF(UPPER(TRIM(P3))="AFF",1,0) | AS3: =IF(UPPER(TRIM(P3))="BAF",1,0) | AT3: =IF(UPPER(TRIM(P3))="MKT",1,0) | AU3: =IF(AO3="221d4",1,0) | AV3: =IF(AO3="223a7",1,0) | AW3: =IF(AO3="232",1,0) | AX3: =IF(AO3="538",1,0) | AY3: =IF(AO3="241",1,0) | AZ3: =IF(AO3="220",1,0) | BA3: =IF(AO3="OTHER",1,0) | BB3: =IF(UPPER(TRIM(C3))="LM",1,0) | BC3: =IF(UPPER(TRIM(C3))="PN",1,0) | BD3: =IF(UPPER(TRIM(C3))="LS",1,0) | BE3: =IF(UPPER(TRIM(C3))="RX",1,0) | BF3: =IFERROR((Parameters!$C$6*AM3+Parameters!$C$7*MAX(AM3-(-150),0)+Parameters!$C$8*MAX(AM3-(-50),0)+Parameters!$C$9*MAX(AM3-(0),0)+Parameters!$C$10*MAX(AM3-(50),0)+Parameters!$C$11*MAX(AM3-(100),0)+Parameters!$C$12*MAX(AM3-(150),0)+Parameters!$C$13*MAX(AM3-(250),0)),0) | BG3: =IFERROR((Parameters!$C$14*AA3+Parameters!$C$15*MAX(AA3-(12),0)+Parameters!$C$16*MAX(AA3-(36),0)+Parameters!$C$17*MAX(AA3-(60),0)+Parameters!$C$18*MAX(AA3-(84),0)+Parameters!$C$19*MAX(AA3-(120),0)+Parameters!$C$20*MAX(AA3-(180),0)),0) | BH3: =IFERROR((Parameters!$C$21*AK3+Parameters!$C$22*MAX(AK3-(0),0)+Parameters!$C$23*MAX(AK3-(2),0)+Parameters!$C$24*MAX(AK3-(5),0)+Parameters!$C$25*MAX(AK3-(8),0)),0) | BI3: =IFERROR((Parameters!$C$26*AI3+Parameters!$C$27*MAX(AI3-(-100),0)+Parameters!$C$28*MAX(AI3-(-25),0)+Parameters!$C$29*MAX(AI3-(25),0)+Parameters!$C$30*MAX(AI3-(100),0)),0) | BJ3: =IFERROR((Parameters!$C$31*AN3+Parameters!$C$32*MAX(AN3-(2),0)+Parameters!$C$33*MAX(AN3-(10),0)+Parameters!$C$34*MAX(AN3-(25),0)),0) | BK3: =IFERROR((Parameters!$C$35*AB3+Parameters!$C$36*MAX(AB3-(12),0)+Parameters!$C$37*MAX(AB3-(24),0)+Parameters!$C$38*MAX(AB3-(60),0)),0) | BL3: =IFERROR((Parameters!$C$39*AC3+Parameters!$C$40*MAX(AC3-(6),0)+Parameters!$C$41*MAX(AC3-(12),0)+Parameters!$C$42*MAX(AC3-(24),0)),0) | BM3: =IFERROR(Parameters!$C$43*(MAX(AM3,0)*MIN(MAX(AK3,0),10))/100,0) | BN3: =Parameters!$C$44*AE3 | BO3: =Parameters!$C$45*AU3 + Parameters!$C$46*AV3 + Parameters!$C$47*AW3 + Parameters!$C$48*AX3 + Parameters!$C$49*AY3 + Parameters!$C$50*AZ3 + Parameters!$C$51*BA3 | BP3: =Parameters!$C$52*AQ3 | BQ3: =Parameters!$C$53*AR3+Parameters!$C$54*AS3+Parameters!$C$55*AT3 | BR3: =Parameters!$C$56*BB3+Parameters!$C$57*BC3+Parameters!$C$58*BD3+Parameters!$C$59*BE3 | BS3: =Parameters!$B$2 | BT3: =BS3+BF3 + BG3 + BH3 + BI3 + BJ3 + BK3 + BL3 + BM3 + BN3 + BO3 + BP3 + BQ3 + BR3 | BU3: =IF(AD3=1,0,1/(1+EXP(-BT3))*Parameters!$B$3) | BV3: =(1-(1-BU3)^12)*100 | BW3: =IF(AD3=1,0,(1-(1-1/(1+EXP(-Parameters!$B$2)))^12)*100) | BX3: =IF(AD3=1,0,BV3-(1-(1-(1/(1+EXP(-(BT3-BF3)))*Parameters!$B$3))^12)*100) | BY3: =IF(AD3=1,0,BV3-(1-(1-(1/(1+EXP(-(BT3-BG3)))*Parameters!$B$3))^12)*100) | BZ3: =IF(AD3=1,0,BV3-(1-(1-(1/(1+EXP(-(BT3-BH3)))*Parameters!$B$3))^12)*100) | CA3: =IF(AD3=1,0,BV3-(1-(1-(1/(1+EXP(-(BT3-BI3)))*Parameters!$B$3))^12)*100) | CB3: =IF(AD3=1,0,BV3-(1-(1-(1/(1+EXP(-(BT3-BJ3)))*Parameters!$B$3))^12)*100) | CC3: =IF(AD3=1,0,BV3-(1-(1-(1/(1+EXP(-(BT3-BK3)))*Parameters!$B$3))^12)*100) | CD3: =IF(AD3=1,0,BV3-(1-(1-(1/(1+EXP(-(BT3-BL3)))*Parameters!$B$3))^12)*100) | CE3: =IF(AD3=1,0,BV3-(1-(1-(1/(1+EXP(-(BT3-BM3)))*Parameters!$B$3))^12)*100) | CF3: =IF(AD3=1,0,BV3-(1-(1-(1/(1+EXP(-(BT3-BN3)))*Parameters!$B$3))^12)*100) | CG3: =IF(AD3=1,0,BV3-(1-(1-(1/(1+EXP(-(BT3-BO3)))*Parameters!$B$3))^12)*100) | CH3: =IF(AD3=1,0,BV3-(1-(1-(1/(1+EXP(-(BT3-BP3)))*Parameters!$B$3))^12)*100) | CI3: =IF(AD3=1,0,BV3-(1-(1-(1/(1+EXP(-(BT3-BQ3)))*Parameters!$B$3))^12)*100) | CJ3: =IF(AD3=1,0,BV3-(1-(1-(1/(1+EXP(-(BT3-BR3)))*Parameters!$B$3))^12)*100)
A4: GNR_2024_NEW | B4: 3618K96G4 | C4: PN | D4: GREYSTONE FUNDING COMPANY LLC | E4: 3618K96G4_000000011622044 | F4: 202603 | G4: 5.89 | H4: 12467559 | I4: 420 | J4: 20250401 | K4: 20600501 | M4: 20350601 | N4: 10 | O4: 232/223(F) | T4: NM | U4: 32 | V4: 490.5 | W4: 11 | X4: 2025 | Y4: 7 | Z4: 10 | AA4: =IF(ISNUMBER(W4),W4,IFERROR(MAX(0,(VALUE(LEFT(F4,4))-VALUE(LEFT(TEXT(J4,"00000000"),4)))*12+(VALUE(MID(F4,5,2))-VALUE(MID(TEXT(J4,"00000000"),5,2)))),"")) | AB4: =IFERROR((VALUE(LEFT(TEXT(K4,"00000000"),4))-VALUE(LEFT(F4,4)))*12+(VALUE(MID(TEXT(K4,"00000000"),5,2))-VALUE(MID(F4,5,2))),"") | AC4: =IF(OR(L4="",NOT(ISNUMBER(L4))),0,MAX(0,MIN(60,(VALUE(LEFT(F4,4))-VALUE(LEFT(TEXT(L4,"00000000"),4)))*12+(VALUE(MID(F4,5,2))-VALUE(MID(TEXT(L4,"00000000"),5,2)))))) | AD4: =IF(OR(L4="",NOT(ISNUMBER(L4))),0,IF(VALUE(F4)<VALUE(LEFT(TEXT(L4,"00000000"),6)),1,0)) | AE4: =IF(OR(M4="",NOT(ISNUMBER(M4))),0,IF(VALUE(F4)<VALUE(LEFT(TEXT(M4,"00000000"),6)),1,0)) | AF4: =IF(AND(AD4=0,AE4=0),1,0) | AG4: =IF(ISNUMBER(X4),X4,IFERROR(VALUE(LEFT(TEXT(J4,"00000000"),4)),"")) | AH4: =IFERROR(XLOOKUP(AG4,Vintage_Rates!$A$2:$A$1000,Vintage_Rates!$B$2:$B$1000,""),"") | AI4: =IF(ISNUMBER(Y4),Y4,IFERROR((G4-AH4)*100,"")) | AJ4: =IF(ISNUMBER(V4),V4,IFERROR(XLOOKUP(VALUE(F4),PLC_Rates!$A$2:$A$1000,PLC_Rates!$B$2:$B$1000,""),"")) | AK4: =IF(ISNUMBER(Z4),Z4,IF(AE4=0,0,MAX(0,MIN(10,((VALUE(LEFT(TEXT(M4,"00000000"),4))-VALUE(LEFT(F4,4)))*12+(VALUE(MID(TEXT(M4,"00000000"),5,2))-VALUE(MID(F4,5,2))))/12)))) | AL4: =IFERROR(G4*100-AJ4,"") | AM4: =IFERROR(G4*100-(AJ4+(1+AK4)*12.5),"") | AN4: =IFERROR(MIN(H4/1000000,100),"") | AO4: =IFERROR(INDEX(FHA_Lookup!$B$2:$B$11,MATCH(TRUE,ISNUMBER(SEARCH(FHA_Lookup!$A$2:$A$11,UPPER(SUBSTITUTE(O4," ","")))),0)),"OTHER") | AP4: =IFERROR(INDEX(FHA_Lookup!$C$2:$C$11,MATCH(TRUE,ISNUMBER(SEARCH(FHA_Lookup!$A$2:$A$11,UPPER(SUBSTITUTE(O4," ","")))),0)),"OTHER") | AQ4: =IF(AP4="NC",1,0) | AR4: =IF(UPPER(TRIM(P4))="AFF",1,0) | AS4: =IF(UPPER(TRIM(P4))="BAF",1,0) | AT4: =IF(UPPER(TRIM(P4))="MKT",1,0) | AU4: =IF(AO4="221d4",1,0) | AV4: =IF(AO4="223a7",1,0) | AW4: =IF(AO4="232",1,0) | AX4: =IF(AO4="538",1,0) | AY4: =IF(AO4="241",1,0) | AZ4: =IF(AO4="220",1,0) | BA4: =IF(AO4="OTHER",1,0) | BB4: =IF(UPPER(TRIM(C4))="LM",1,0) | BC4: =IF(UPPER(TRIM(C4))="PN",1,0) | BD4: =IF(UPPER(TRIM(C4))="LS",1,0) | BE4: =IF(UPPER(TRIM(C4))="RX",1,0) | BF4: =IFERROR((Parameters!$C$6*AM4+Parameters!$C$7*MAX(AM4-(-150),0)+Parameters!$C$8*MAX(AM4-(-50),0)+Parameters!$C$9*MAX(AM4-(0),0)+Parameters!$C$10*MAX(AM4-(50),0)+Parameters!$C$11*MAX(AM4-(100),0)+Parameters!$C$12*MAX(AM4-(150),0)+Parameters!$C$13*MAX(AM4-(250),0)),0) | BG4: =IFERROR((Parameters!$C$14*AA4+Parameters!$C$15*MAX(AA4-(12),0)+Parameters!$C$16*MAX(AA4-(36),0)+Parameters!$C$17*MAX(AA4-(60),0)+Parameters!$C$18*MAX(AA4-(84),0)+Parameters!$C$19*MAX(AA4-(120),0)+Parameters!$C$20*MAX(AA4-(180),0)),0) | BH4: =IFERROR((Parameters!$C$21*AK4+Parameters!$C$22*MAX(AK4-(0),0)+Parameters!$C$23*MAX(AK4-(2),0)+Parameters!$C$24*MAX(AK4-(5),0)+Parameters!$C$25*MAX(AK4-(8),0)),0) | BI4: =IFERROR((Parameters!$C$26*AI4+Parameters!$C$27*MAX(AI4-(-100),0)+Parameters!$C$28*MAX(AI4-(-25),0)+Parameters!$C$29*MAX(AI4-(25),0)+Parameters!$C$30*MAX(AI4-(100),0)),0) | BJ4: =IFERROR((Parameters!$C$31*AN4+Parameters!$C$32*MAX(AN4-(2),0)+Parameters!$C$33*MAX(AN4-(10),0)+Parameters!$C$34*MAX(AN4-(25),0)),0) | BK4: =IFERROR((Parameters!$C$35*AB4+Parameters!$C$36*MAX(AB4-(12),0)+Parameters!$C$37*MAX(AB4-(24),0)+Parameters!$C$38*MAX(AB4-(60),0)),0) | BL4: =IFERROR((Parameters!$C$39*AC4+Parameters!$C$40*MAX(AC4-(6),0)+Parameters!$C$41*MAX(AC4-(12),0)+Parameters!$C$42*MAX(AC4-(24),0)),0) | BM4: =IFERROR(Parameters!$C$43*(MAX(AM4,0)*MIN(MAX(AK4,0),10))/100,0) | BN4: =Parameters!$C$44*AE4 | BO4: =Parameters!$C$45*AU4 + Parameters!$C$46*AV4 + Parameters!$C$47*AW4 + Parameters!$C$48*AX4 + Parameters!$C$49*AY4 + Parameters!$C$50*AZ4 + Parameters!$C$51*BA4 | BP4: =Parameters!$C$52*AQ4 | BQ4: =Parameters!$C$53*AR4+Parameters!$C$54*AS4+Parameters!$C$55*AT4 | BR4: =Parameters!$C$56*BB4+Parameters!$C$57*BC4+Parameters!$C$58*BD4+Parameters!$C$59*BE4 | BS4: =Parameters!$B$2 | BT4: =BS4+BF4 + BG4 + BH4 + BI4 + BJ4 + BK4 + BL4 + BM4 + BN4 + BO4 + BP4 + BQ4 + BR4 | BU4: =IF(AD4=1,0,1/(1+EXP(-BT4))*Parameters!$B$3) | BV4: =(1-(1-BU4)^12)*100 | BW4: =IF(AD4=1,0,(1-(1-1/(1+EXP(-Parameters!$B$2)))^12)*100) | BX4: =IF(AD4=1,0,BV4-(1-(1-(1/(1+EXP(-(BT4-BF4)))*Parameters!$B$3))^12)*100) | BY4: =IF(AD4=1,0,BV4-(1-(1-(1/(1+EXP(-(BT4-BG4)))*Parameters!$B$3))^12)*100) | BZ4: =IF(AD4=1,0,BV4-(1-(1-(1/(1+EXP(-(BT4-BH4)))*Parameters!$B$3))^12)*100) | CA4: =IF(AD4=1,0,BV4-(1-(1-(1/(1+EXP(-(BT4-BI4)))*Parameters!$B$3))^12)*100) | CB4: =IF(AD4=1,0,BV4-(1-(1-(1/(1+EXP(-(BT4-BJ4)))*Parameters!$B$3))^12)*100) | CC4: =IF(AD4=1,0,BV4-(1-(1-(1/(1+EXP(-(BT4-BK4)))*Parameters!$B$3))^12)*100) | CD4: =IF(AD4=1,0,BV4-(1-(1-(1/(1+EXP(-(BT4-BL4)))*Parameters!$B$3))^12)*100) | CE4: =IF(AD4=1,0,BV4-(1-(1-(1/(1+EXP(-(BT4-BM4)))*Parameters!$B$3))^12)*100) | CF4: =IF(AD4=1,0,BV4-(1-(1-(1/(1+EXP(-(BT4-BN4)))*Parameters!$B$3))^12)*100) | CG4: =IF(AD4=1,0,BV4-(1-(1-(1/(1+EXP(-(BT4-BO4)))*Parameters!$B$3))^12)*100) | CH4: =IF(AD4=1,0,BV4-(1-(1-(1/(1+EXP(-(BT4-BP4)))*Parameters!$B$3))^12)*100) | CI4: =IF(AD4=1,0,BV4-(1-(1-(1/(1+EXP(-(BT4-BQ4)))*Parameters!$B$3))^12)*100) | CJ4: =IF(AD4=1,0,BV4-(1-(1-(1/(1+EXP(-(BT4-BR4)))*Parameters!$B$3))^12)*100)
A5: GNR_2024_NEW | B5: 3618FH2S0 | C5: PN | D5: NEWPOINT REAL ESTATE CAPITAL LLC | E5: 3618FH2S0_000000001711297 | F5: 202603 | G5: 5.98 | H5: 3566192.3 | I5: 420 | J5: 20240221 | K5: 20590301 | M5: 20340401 | N5: 10 | O5: 207/223(F) | P5: MKT | T5: CT | U5: 25 | V5: 490.5 | W5: 25 | X5: 2024 | Y5: 20 | Z5: 9 | AA5: =IF(ISNUMBER(W5),W5,IFERROR(MAX(0,(VALUE(LEFT(F5,4))-VALUE(LEFT(TEXT(J5,"00000000"),4)))*12+(VALUE(MID(F5,5,2))-VALUE(MID(TEXT(J5,"00000000"),5,2)))),"")) | AB5: =IFERROR((VALUE(LEFT(TEXT(K5,"00000000"),4))-VALUE(LEFT(F5,4)))*12+(VALUE(MID(TEXT(K5,"00000000"),5,2))-VALUE(MID(F5,5,2))),"") | AC5: =IF(OR(L5="",NOT(ISNUMBER(L5))),0,MAX(0,MIN(60,(VALUE(LEFT(F5,4))-VALUE(LEFT(TEXT(L5,"00000000"),4)))*12+(VALUE(MID(F5,5,2))-VALUE(MID(TEXT(L5,"00000000"),5,2)))))) | AD5: =IF(OR(L5="",NOT(ISNUMBER(L5))),0,IF(VALUE(F5)<VALUE(LEFT(TEXT(L5,"00000000"),6)),1,0)) | AE5: =IF(OR(M5="",NOT(ISNUMBER(M5))),0,IF(VALUE(F5)<VALUE(LEFT(TEXT(M5,"00000000"),6)),1,0)) | AF5: =IF(AND(AD5=0,AE5=0),1,0) | AG5: =IF(ISNUMBER(X5),X5,IFERROR(VALUE(LEFT(TEXT(J5,"00000000"),4)),"")) | AH5: =IFERROR(XLOOKUP(AG5,Vintage_Rates!$A$2:$A$1000,Vintage_Rates!$B$2:$B$1000,""),"") | AI5: =IF(ISNUMBER(Y5),Y5,IFERROR((G5-AH5)*100,"")) | AJ5: =IF(ISNUMBER(V5),V5,IFERROR(XLOOKUP(VALUE(F5),PLC_Rates!$A$2:$A$1000,PLC_Rates!$B$2:$B$1000,""),"")) | AK5: =IF(ISNUMBER(Z5),Z5,IF(AE5=0,0,MAX(0,MIN(10,((VALUE(LEFT(TEXT(M5,"00000000"),4))-VALUE(LEFT(F5,4)))*12+(VALUE(MID(TEXT(M5,"00000000"),5,2))-VALUE(MID(F5,5,2))))/12)))) | AL5: =IFERROR(G5*100-AJ5,"") | AM5: =IFERROR(G5*100-(AJ5+(1+AK5)*12.5),"") | AN5: =IFERROR(MIN(H5/1000000,100),"") | AO5: =IFERROR(INDEX(FHA_Lookup!$B$2:$B$11,MATCH(TRUE,ISNUMBER(SEARCH(FHA_Lookup!$A$2:$A$11,UPPER(SUBSTITUTE(O5," ","")))),0)),"OTHER") | AP5: =IFERROR(INDEX(FHA_Lookup!$C$2:$C$11,MATCH(TRUE,ISNUMBER(SEARCH(FHA_Lookup!$A$2:$A$11,UPPER(SUBSTITUTE(O5," ","")))),0)),"OTHER") | AQ5: =IF(AP5="NC",1,0) | AR5: =IF(UPPER(TRIM(P5))="AFF",1,0) | AS5: =IF(UPPER(TRIM(P5))="BAF",1,0) | AT5: =IF(UPPER(TRIM(P5))="MKT",1,0) | AU5: =IF(AO5="221d4",1,0) | AV5: =IF(AO5="223a7",1,0) | AW5: =IF(AO5="232",1,0) | AX5: =IF(AO5="538",1,0) | AY5: =IF(AO5="241",1,0) | AZ5: =IF(AO5="220",1,0) | BA5: =IF(AO5="OTHER",1,0) | BB5: =IF(UPPER(TRIM(C5))="LM",1,0) | BC5: =IF(UPPER(TRIM(C5))="PN",1,0) | BD5: =IF(UPPER(TRIM(C5))="LS",1,0) | BE5: =IF(UPPER(TRIM(C5))="RX",1,0) | BF5: =IFERROR((Parameters!$C$6*AM5+Parameters!$C$7*MAX(AM5-(-150),0)+Parameters!$C$8*MAX(AM5-(-50),0)+Parameters!$C$9*MAX(AM5-(0),0)+Parameters!$C$10*MAX(AM5-(50),0)+Parameters!$C$11*MAX(AM5-(100),0)+Parameters!$C$12*MAX(AM5-(150),0)+Parameters!$C$13*MAX(AM5-(250),0)),0) | BG5: =IFERROR((Parameters!$C$14*AA5+Parameters!$C$15*MAX(AA5-(12),0)+Parameters!$C$16*MAX(AA5-(36),0)+Parameters!$C$17*MAX(AA5-(60),0)+Parameters!$C$18*MAX(AA5-(84),0)+Parameters!$C$19*MAX(AA5-(120),0)+Parameters!$C$20*MAX(AA5-(180),0)),0) | BH5: =IFERROR((Parameters!$C$21*AK5+Parameters!$C$22*MAX(AK5-(0),0)+Parameters!$C$23*MAX(AK5-(2),0)+Parameters!$C$24*MAX(AK5-(5),0)+Parameters!$C$25*MAX(AK5-(8),0)),0) | BI5: =IFERROR((Parameters!$C$26*AI5+Parameters!$C$27*MAX(AI5-(-100),0)+Parameters!$C$28*MAX(AI5-(-25),0)+Parameters!$C$29*MAX(AI5-(25),0)+Parameters!$C$30*MAX(AI5-(100),0)),0) | BJ5: =IFERROR((Parameters!$C$31*AN5+Parameters!$C$32*MAX(AN5-(2),0)+Parameters!$C$33*MAX(AN5-(10),0)+Parameters!$C$34*MAX(AN5-(25),0)),0) | BK5: =IFERROR((Parameters!$C$35*AB5+Parameters!$C$36*MAX(AB5-(12),0)+Parameters!$C$37*MAX(AB5-(24),0)+Parameters!$C$38*MAX(AB5-(60),0)),0) | BL5: =IFERROR((Parameters!$C$39*AC5+Parameters!$C$40*MAX(AC5-(6),0)+Parameters!$C$41*MAX(AC5-(12),0)+Parameters!$C$42*MAX(AC5-(24),0)),0) | BM5: =IFERROR(Parameters!$C$43*(MAX(AM5,0)*MIN(MAX(AK5,0),10))/100,0) | BN5: =Parameters!$C$44*AE5 | BO5: =Parameters!$C$45*AU5 + Parameters!$C$46*AV5 + Parameters!$C$47*AW5 + Parameters!$C$48*AX5 + Parameters!$C$49*AY5 + Parameters!$C$50*AZ5 + Parameters!$C$51*BA5 | BP5: =Parameters!$C$52*AQ5 | BQ5: =Parameters!$C$53*AR5+Parameters!$C$54*AS5+Parameters!$C$55*AT5 | BR5: =Parameters!$C$56*BB5+Parameters!$C$57*BC5+Parameters!$C$58*BD5+Parameters!$C$59*BE5 | BS5: =Parameters!$B$2 | BT5: =BS5+BF5 + BG5 + BH5 + BI5 + BJ5 + BK5 + BL5 + BM5 + BN5 + BO5 + BP5 + BQ5 + BR5 | BU5: =IF(AD5=1,0,1/(1+EXP(-BT5))*Parameters!$B$3) | BV5: =(1-(1-BU5)^12)*100 | BW5: =IF(AD5=1,0,(1-(1-1/(1+EXP(-Parameters!$B$2)))^12)*100) | BX5: =IF(AD5=1,0,BV5-(1-(1-(1/(1+EXP(-(BT5-BF5)))*Parameters!$B$3))^12)*100) | BY5: =IF(AD5=1,0,BV5-(1-(1-(1/(1+EXP(-(BT5-BG5)))*Parameters!$B$3))^12)*100) | BZ5: =IF(AD5=1,0,BV5-(1-(1-(1/(1+EXP(-(BT5-BH5)))*Parameters!$B$3))^12)*100) | CA5: =IF(AD5=1,0,BV5-(1-(1-(1/(1+EXP(-(BT5-BI5)))*Parameters!$B$3))^12)*100) | CB5: =IF(AD5=1,0,BV5-(1-(1-(1/(1+EXP(-(BT5-BJ5)))*Parameters!$B$3))^12)*100) | CC5: =IF(AD5=1,0,BV5-(1-(1-(1/(1+EXP(-(BT5-BK5)))*Parameters!$B$3))^12)*100) | CD5: =IF(AD5=1,0,BV5-(1-(1-(1/(1+EXP(-(BT5-BL5)))*Parameters!$B$3))^12)*100) | CE5: =IF(AD5=1,0,BV5-(1-(1-(1/(1+EXP(-(BT5-BM5)))*Parameters!$B$3))^12)*100) | CF5: =IF(AD5=1,0,BV5-(1-(1-(1/(1+EXP(-(BT5-BN5)))*Parameters!$B$3))^12)*100) | CG5: =IF(AD5=1,0,BV5-(1-(1-(1/(1+EXP(-(BT5-BO5)))*Parameters!$B$3))^12)*100) | CH5: =IF(AD5=1,0,BV5-(1-(1-(1/(1+EXP(-(BT5-BP5)))*Parameters!$B$3))^12)*100) | CI5: =IF(AD5=1,0,BV5-(1-(1-(1/(1+EXP(-(BT5-BQ5)))*Parameters!$B$3))^12)*100) | CJ5: =IF(AD5=1,0,BV5-(1-(1-(1/(1+EXP(-(BT5-BR5)))*Parameters!$B$3))^12)*100)
A6: GNR_2024_NEW | B6: 3617XHQ56 | C6: PN | D6: COLUMBIANATIONAL REAL ESTATE FINANCE, LL | E6: 3617XHQ56_000000003411314 | F6: 202603 | G6: 5.73 | H6: 4785391.6 | I6: 420 | J6: 20250501 | K6: 20600601 | M6: 20350701 | N6: 10 | O6: 207/223(F) | T6: PA | U6: 42 | V6: 490.5 | W6: 10 | X6: 2025 | Y6: -9 | Z6: 10 | AA6: =IF(ISNUMBER(W6),W6,IFERROR(MAX(0,(VALUE(LEFT(F6,4))-VALUE(LEFT(TEXT(J6,"00000000"),4)))*12+(VALUE(MID(F6,5,2))-VALUE(MID(TEXT(J6,"00000000"),5,2)))),"")) | AB6: =IFERROR((VALUE(LEFT(TEXT(K6,"00000000"),4))-VALUE(LEFT(F6,4)))*12+(VALUE(MID(TEXT(K6,"00000000"),5,2))-VALUE(MID(F6,5,2))),"") | AC6: =IF(OR(L6="",NOT(ISNUMBER(L6))),0,MAX(0,MIN(60,(VALUE(LEFT(F6,4))-VALUE(LEFT(TEXT(L6,"00000000"),4)))*12+(VALUE(MID(F6,5,2))-VALUE(MID(TEXT(L6,"00000000"),5,2)))))) | AD6: =IF(OR(L6="",NOT(ISNUMBER(L6))),0,IF(VALUE(F6)<VALUE(LEFT(TEXT(L6,"00000000"),6)),1,0)) | AE6: =IF(OR(M6="",NOT(ISNUMBER(M6))),0,IF(VALUE(F6)<VALUE(LEFT(TEXT(M6,"00000000"),6)),1,0)) | AF6: =IF(AND(AD6=0,AE6=0),1,0) | AG6: =IF(ISNUMBER(X6),X6,IFERROR(VALUE(LEFT(TEXT(J6,"00000000"),4)),"")) | AH6: =IFERROR(XLOOKUP(AG6,Vintage_Rates!$A$2:$A$1000,Vintage_Rates!$B$2:$B$1000,""),"") | AI6: =IF(ISNUMBER(Y6),Y6,IFERROR((G6-AH6)*100,"")) | AJ6: =IF(ISNUMBER(V6),V6,IFERROR(XLOOKUP(VALUE(F6),PLC_Rates!$A$2:$A$1000,PLC_Rates!$B$2:$B$1000,""),"")) | AK6: =IF(ISNUMBER(Z6),Z6,IF(AE6=0,0,MAX(0,MIN(10,((VALUE(LEFT(TEXT(M6,"00000000"),4))-VALUE(LEFT(F6,4)))*12+(VALUE(MID(TEXT(M6,"00000000"),5,2))-VALUE(MID(F6,5,2))))/12)))) | AL6: =IFERROR(G6*100-AJ6,"") | AM6: =IFERROR(G6*100-(AJ6+(1+AK6)*12.5),"") | AN6: =IFERROR(MIN(H6/1000000,100),"") | AO6: =IFERROR(INDEX(FHA_Lookup!$B$2:$B$11,MATCH(TRUE,ISNUMBER(SEARCH(FHA_Lookup!$A$2:$A$11,UPPER(SUBSTITUTE(O6," ","")))),0)),"OTHER") | AP6: =IFERROR(INDEX(FHA_Lookup!$C$2:$C$11,MATCH(TRUE,ISNUMBER(SEARCH(FHA_Lookup!$A$2:$A$11,UPPER(SUBSTITUTE(O6," ","")))),0)),"OTHER") | AQ6: =IF(AP6="NC",1,0) | AR6: =IF(UPPER(TRIM(P6))="AFF",1,0) | AS6: =IF(UPPER(TRIM(P6))="BAF",1,0) | AT6: =IF(UPPER(TRIM(P6))="MKT",1,0) | AU6: =IF(AO6="221d4",1,0) | AV6: =IF(AO6="223a7",1,0) | AW6: =IF(AO6="232",1,0) | AX6: =IF(AO6="538",1,0) | AY6: =IF(AO6="241",1,0) | AZ6: =IF(AO6="220",1,0) | BA6: =IF(AO6="OTHER",1,0) | BB6: =IF(UPPER(TRIM(C6))="LM",1,0) | BC6: =IF(UPPER(TRIM(C6))="PN",1,0) | BD6: =IF(UPPER(TRIM(C6))="LS",1,0) | BE6: =IF(UPPER(TRIM(C6))="RX",1,0) | BF6: =IFERROR((Parameters!$C$6*AM6+Parameters!$C$7*MAX(AM6-(-150),0)+Parameters!$C$8*MAX(AM6-(-50),0)+Parameters!$C$9*MAX(AM6-(0),0)+Parameters!$C$10*MAX(AM6-(50),0)+Parameters!$C$11*MAX(AM6-(100),0)+Parameters!$C$12*MAX(AM6-(150),0)+Parameters!$C$13*MAX(AM6-(250),0)),0) | BG6: =IFERROR((Parameters!$C$14*AA6+Parameters!$C$15*MAX(AA6-(12),0)+Parameters!$C$16*MAX(AA6-(36),0)+Parameters!$C$17*MAX(AA6-(60),0)+Parameters!$C$18*MAX(AA6-(84),0)+Parameters!$C$19*MAX(AA6-(120),0)+Parameters!$C$20*MAX(AA6-(180),0)),0) | BH6: =IFERROR((Parameters!$C$21*AK6+Parameters!$C$22*MAX(AK6-(0),0)+Parameters!$C$23*MAX(AK6-(2),0)+Parameters!$C$24*MAX(AK6-(5),0)+Parameters!$C$25*MAX(AK6-(8),0)),0) | BI6: =IFERROR((Parameters!$C$26*AI6+Parameters!$C$27*MAX(AI6-(-100),0)+Parameters!$C$28*MAX(AI6-(-25),0)+Parameters!$C$29*MAX(AI6-(25),0)+Parameters!$C$30*MAX(AI6-(100),0)),0) | BJ6: =IFERROR((Parameters!$C$31*AN6+Parameters!$C$32*MAX(AN6-(2),0)+Parameters!$C$33*MAX(AN6-(10),0)+Parameters!$C$34*MAX(AN6-(25),0)),0) | BK6: =IFERROR((Parameters!$C$35*AB6+Parameters!$C$36*MAX(AB6-(12),0)+Parameters!$C$37*MAX(AB6-(24),0)+Parameters!$C$38*MAX(AB6-(60),0)),0) | BL6: =IFERROR((Parameters!$C$39*AC6+Parameters!$C$40*MAX(AC6-(6),0)+Parameters!$C$41*MAX(AC6-(12),0)+Parameters!$C$42*MAX(AC6-(24),0)),0) | BM6: =IFERROR(Parameters!$C$43*(MAX(AM6,0)*MIN(MAX(AK6,0),10))/100,0) | BN6: =Parameters!$C$44*AE6 | BO6: =Parameters!$C$45*AU6 + Parameters!$C$46*AV6 + Parameters!$C$47*AW6 + Parameters!$C$48*AX6 + Parameters!$C$49*AY6 + Parameters!$C$50*AZ6 + Parameters!$C$51*BA6 | BP6: =Parameters!$C$52*AQ6 | BQ6: =Parameters!$C$53*AR6+Parameters!$C$54*AS6+Parameters!$C$55*AT6 | BR6: =Parameters!$C$56*BB6+Parameters!$C$57*BC6+Parameters!$C$58*BD6+Parameters!$C$59*BE6 | BS6: =Parameters!$B$2 | BT6: =BS6+BF6 + BG6 + BH6 + BI6 + BJ6 + BK6 + BL6 + BM6 + BN6 + BO6 + BP6 + BQ6 + BR6 | BU6: =IF(AD6=1,0,1/(1+EXP(-BT6))*Parameters!$B$3) | BV6: =(1-(1-BU6)^12)*100 | BW6: =IF(AD6=1,0,(1-(1-1/(1+EXP(-Parameters!$B$2)))^12)*100) | BX6: =IF(AD6=1,0,BV6-(1-(1-(1/(1+EXP(-(BT6-BF6)))*Parameters!$B$3))^12)*100) | BY6: =IF(AD6=1,0,BV6-(1-(1-(1/(1+EXP(-(BT6-BG6)))*Parameters!$B$3))^12)*100) | BZ6: =IF(AD6=1,0,BV6-(1-(1-(1/(1+EXP(-(BT6-BH6)))*Parameters!$B$3))^12)*100) | CA6: =IF(AD6=1,0,BV6-(1-(1-(1/(1+EXP(-(BT6-BI6)))*Parameters!$B$3))^12)*100) | CB6: =IF(AD6=1,0,BV6-(1-(1-(1/(1+EXP(-(BT6-BJ6)))*Parameters!$B$3))^12)*100) | CC6: =IF(AD6=1,0,BV6-(1-(1-(1/(1+EXP(-(BT6-BK6)))*Parameters!$B$3))^12)*100) | CD6: =IF(AD6=1,0,BV6-(1-(1-(1/(1+EXP(-(BT6-BL6)))*Parameters!$B$3))^12)*100) | CE6: =IF(AD6=1,0,BV6-(1-(1-(1/(1+EXP(-(BT6-BM6)))*Parameters!$B$3))^12)*100) | CF6: =IF(AD6=1,0,BV6-(1-(1-(1/(1+EXP(-(BT6-BN6)))*Parameters!$B$3))^12)*100) | CG6: =IF(AD6=1,0,BV6-(1-(1-(1/(1+EXP(-(BT6-BO6)))*Parameters!$B$3))^12)*100) | CH6: =IF(AD6=1,0,BV6-(1-(1-(1/(1+EXP(-(BT6-BP6)))*Parameters!$B$3))^12)*100) | CI6: =IF(AD6=1,0,BV6-(1-(1-(1/(1+EXP(-(BT6-BQ6)))*Parameters!$B$3))^12)*100) | CJ6: =IF(AD6=1,0,BV6-(1-(1-(1/(1+EXP(-(BT6-BR6)))*Parameters!$B$3))^12)*100)
A7: GNR_2024_NEW | B7: 3618L6QB8 | C7: PN | D7: KEYBANK NATIONAL ASSOCIATION | E7: 3618L6QB8_000000005322284 | F7: 202603 | G7: 5.4 | H7: 21113919 | I7: 420 | J7: 20250901 | K7: 20601001 | M7: 20351031 | N7: 10 | O7: 232/223(F) | T7: NC | U7: 40 | V7: 490.5 | W7: 6 | X7: 2025 | Y7: -42 | Z7: 10 | AA7: =IF(ISNUMBER(W7),W7,IFERROR(MAX(0,(VALUE(LEFT(F7,4))-VALUE(LEFT(TEXT(J7,"00000000"),4)))*12+(VALUE(MID(F7,5,2))-VALUE(MID(TEXT(J7,"00000000"),5,2)))),"")) | AB7: =IFERROR((VALUE(LEFT(TEXT(K7,"00000000"),4))-VALUE(LEFT(F7,4)))*12+(VALUE(MID(TEXT(K7,"00000000"),5,2))-VALUE(MID(F7,5,2))),"") | AC7: =IF(OR(L7="",NOT(ISNUMBER(L7))),0,MAX(0,MIN(60,(VALUE(LEFT(F7,4))-VALUE(LEFT(TEXT(L7,"00000000"),4)))*12+(VALUE(MID(F7,5,2))-VALUE(MID(TEXT(L7,"00000000"),5,2)))))) | AD7: =IF(OR(L7="",NOT(ISNUMBER(L7))),0,IF(VALUE(F7)<VALUE(LEFT(TEXT(L7,"00000000"),6)),1,0)) | AE7: =IF(OR(M7="",NOT(ISNUMBER(M7))),0,IF(VALUE(F7)<VALUE(LEFT(TEXT(M7,"00000000"),6)),1,0)) | AF7: =IF(AND(AD7=0,AE7=0),1,0) | AG7: =IF(ISNUMBER(X7),X7,IFERROR(VALUE(LEFT(TEXT(J7,"00000000"),4)),"")) | AH7: =IFERROR(XLOOKUP(AG7,Vintage_Rates!$A$2:$A$1000,Vintage_Rates!$B$2:$B$1000,""),"") | AI7: =IF(ISNUMBER(Y7),Y7,IFERROR((G7-AH7)*100,"")) | AJ7: =IF(ISNUMBER(V7),V7,IFERROR(XLOOKUP(VALUE(F7),PLC_Rates!$A$2:$A$1000,PLC_Rates!$B$2:$B$1000,""),"")) | AK7: =IF(ISNUMBER(Z7),Z7,IF(AE7=0,0,MAX(0,MIN(10,((VALUE(LEFT(TEXT(M7,"00000000"),4))-VALUE(LEFT(F7,4)))*12+(VALUE(MID(TEXT(M7,"00000000"),5,2))-VALUE(MID(F7,5,2))))/12)))) | AL7: =IFERROR(G7*100-AJ7,"") | AM7: =IFERROR(G7*100-(AJ7+(1+AK7)*12.5),"") | AN7: =IFERROR(MIN(H7/1000000,100),"") | AO7: =IFERROR(INDEX(FHA_Lookup!$B$2:$B$11,MATCH(TRUE,ISNUMBER(SEARCH(FHA_Lookup!$A$2:$A$11,UPPER(SUBSTITUTE(O7," ","")))),0)),"OTHER") | AP7: =IFERROR(INDEX(FHA_Lookup!$C$2:$C$11,MATCH(TRUE,ISNUMBER(SEARCH(FHA_Lookup!$A$2:$A$11,UPPER(SUBSTITUTE(O7," ","")))),0)),"OTHER") | AQ7: =IF(AP7="NC",1,0) | AR7: =IF(UPPER(TRIM(P7))="AFF",1,0) | AS7: =IF(UPPER(TRIM(P7))="BAF",1,0) | AT7: =IF(UPPER(TRIM(P7))="MKT",1,0) | AU7: =IF(AO7="221d4",1,0) | AV7: =IF(AO7="223a7",1,0) | AW7: =IF(AO7="232",1,0) | AX7: =IF(AO7="538",1,0) | AY7: =IF(AO7="241",1,0) | AZ7: =IF(AO7="220",1,0) | BA7: =IF(AO7="OTHER",1,0) | BB7: =IF(UPPER(TRIM(C7))="LM",1,0) | BC7: =IF(UPPER(TRIM(C7))="PN",1,0) | BD7: =IF(UPPER(TRIM(C7))="LS",1,0) | BE7: =IF(UPPER(TRIM(C7))="RX",1,0) | BF7: =IFERROR((Parameters!$C$6*AM7+Parameters!$C$7*MAX(AM7-(-150),0)+Parameters!$C$8*MAX(AM7-(-50),0)+Parameters!$C$9*MAX(AM7-(0),0)+Parameters!$C$10*MAX(AM7-(50),0)+Parameters!$C$11*MAX(AM7-(100),0)+Parameters!$C$12*MAX(AM7-(150),0)+Parameters!$C$13*MAX(AM7-(250),0)),0) | BG7: =IFERROR((Parameters!$C$14*AA7+Parameters!$C$15*MAX(AA7-(12),0)+Parameters!$C$16*MAX(AA7-(36),0)+Parameters!$C$17*MAX(AA7-(60),0)+Parameters!$C$18*MAX(AA7-(84),0)+Parameters!$C$19*MAX(AA7-(120),0)+Parameters!$C$20*MAX(AA7-(180),0)),0) | BH7: =IFERROR((Parameters!$C$21*AK7+Parameters!$C$22*MAX(AK7-(0),0)+Parameters!$C$23*MAX(AK7-(2),0)+Parameters!$C$24*MAX(AK7-(5),0)+Parameters!$C$25*MAX(AK7-(8),0)),0) | BI7: =IFERROR((Parameters!$C$26*AI7+Parameters!$C$27*MAX(AI7-(-100),0)+Parameters!$C$28*MAX(AI7-(-25),0)+Parameters!$C$29*MAX(AI7-(25),0)+Parameters!$C$30*MAX(AI7-(100),0)),0) | BJ7: =IFERROR((Parameters!$C$31*AN7+Parameters!$C$32*MAX(AN7-(2),0)+Parameters!$C$33*MAX(AN7-(10),0)+Parameters!$C$34*MAX(AN7-(25),0)),0) | BK7: =IFERROR((Parameters!$C$35*AB7+Parameters!$C$36*MAX(AB7-(12),0)+Parameters!$C$37*MAX(AB7-(24),0)+Parameters!$C$38*MAX(AB7-(60),0)),0) | BL7: =IFERROR((Parameters!$C$39*AC7+Parameters!$C$40*MAX(AC7-(6),0)+Parameters!$C$41*MAX(AC7-(12),0)+Parameters!$C$42*MAX(AC7-(24),0)),0) | BM7: =IFERROR(Parameters!$C$43*(MAX(AM7,0)*MIN(MAX(AK7,0),10))/100,0) | BN7: =Parameters!$C$44*AE7 | BO7: =Parameters!$C$45*AU7 + Parameters!$C$46*AV7 + Parameters!$C$47*AW7 + Parameters!$C$48*AX7 + Parameters!$C$49*AY7 + Parameters!$C$50*AZ7 + Parameters!$C$51*BA7 | BP7: =Parameters!$C$52*AQ7 | BQ7: =Parameters!$C$53*AR7+Parameters!$C$54*AS7+Parameters!$C$55*AT7 | BR7: =Parameters!$C$56*BB7+Parameters!$C$57*BC7+Parameters!$C$58*BD7+Parameters!$C$59*BE7 | BS7: =Parameters!$B$2 | BT7: =BS7+BF7 + BG7 + BH7 + BI7 + BJ7 + BK7 + BL7 + BM7 + BN7 + BO7 + BP7 + BQ7 + BR7 | BU7: =IF(AD7=1,0,1/(1+EXP(-BT7))*Parameters!$B$3) | BV7: =(1-(1-BU7)^12)*100 | BW7: =IF(AD7=1,0,(1-(1-1/(1+EXP(-Parameters!$B$2)))^12)*100) | BX7: =IF(AD7=1,0,BV7-(1-(1-(1/(1+EXP(-(BT7-BF7)))*Parameters!$B$3))^12)*100) | BY7: =IF(AD7=1,0,BV7-(1-(1-(1/(1+EXP(-(BT7-BG7)))*Parameters!$B$3))^12)*100) | BZ7: =IF(AD7=1,0,BV7-(1-(1-(1/(1+EXP(-(BT7-BH7)))*Parameters!$B$3))^12)*100) | CA7: =IF(AD7=1,0,BV7-(1-(1-(1/(1+EXP(-(BT7-BI7)))*Parameters!$B$3))^12)*100) | CB7: =IF(AD7=1,0,BV7-(1-(1-(1/(1+EXP(-(BT7-BJ7)))*Parameters!$B$3))^12)*100) | CC7: =IF(AD7=1,0,BV7-(1-(1-(1/(1+EXP(-(BT7-BK7)))*Parameters!$B$3))^12)*100) | CD7: =IF(AD7=1,0,BV7-(1-(1-(1/(1+EXP(-(BT7-BL7)))*Parameters!$B$3))^12)*100) | CE7: =IF(AD7=1,0,BV7-(1-(1-(1/(1+EXP(-(BT7-BM7)))*Parameters!$B$3))^12)*100) | CF7: =IF(AD7=1,0,BV7-(1-(1-(1/(1+EXP(-(BT7-BN7)))*Parameters!$B$3))^12)*100) | CG7: =IF(AD7=1,0,BV7-(1-(1-(1/(1+EXP(-(BT7-BO7)))*Parameters!$B$3))^12)*100) | CH7: =IF(AD7=1,0,BV7-(1-(1-(1/(1+EXP(-(BT7-BP7)))*Parameters!$B$3))^12)*100) | CI7: =IF(AD7=1,0,BV7-(1-(1-(1/(1+EXP(-(BT7-BQ7)))*Parameters!$B$3))^12)*100) | CJ7: =IF(AD7=1,0,BV7-(1-(1-(1/(1+EXP(-(BT7-BR7)))*Parameters!$B$3))^12)*100)
A8: GNR_2024_NEW | B8: 3618HGKV3 | C8: PN | D8: WELLS FARGO BANK, N.A. | E8: 3618HGKV3_000000010111361 | F8: 202603 | G8: 5.92 | H8: 20435174 | I8: 420 | J8: 20250701 | K8: 20600801 | L8: 20250901 | M8: 20350901 | N8: 10 | O8: 207/223(f) | T8: CO | U8: 120 | V8: 490.5 | W8: 8 | X8: 2025 | Y8: 10 | Z8: 10 | AA8: =IF(ISNUMBER(W8),W8,IFERROR(MAX(0,(VALUE(LEFT(F8,4))-VALUE(LEFT(TEXT(J8,"00000000"),4)))*12+(VALUE(MID(F8,5,2))-VALUE(MID(TEXT(J8,"00000000"),5,2)))),"")) | AB8: =IFERROR((VALUE(LEFT(TEXT(K8,"00000000"),4))-VALUE(LEFT(F8,4)))*12+(VALUE(MID(TEXT(K8,"00000000"),5,2))-VALUE(MID(F8,5,2))),"") | AC8: =IF(OR(L8="",NOT(ISNUMBER(L8))),0,MAX(0,MIN(60,(VALUE(LEFT(F8,4))-VALUE(LEFT(TEXT(L8,"00000000"),4)))*12+(VALUE(MID(F8,5,2))-VALUE(MID(TEXT(L8,"00000000"),5,2)))))) | AD8: =IF(OR(L8="",NOT(ISNUMBER(L8))),0,IF(VALUE(F8)<VALUE(LEFT(TEXT(L8,"00000000"),6)),1,0)) | AE8: =IF(OR(M8="",NOT(ISNUMBER(M8))),0,IF(VALUE(F8)<VALUE(LEFT(TEXT(M8,"00000000"),6)),1,0)) | AF8: =IF(AND(AD8=0,AE8=0),1,0) | AG8: =IF(ISNUMBER(X8),X8,IFERROR(VALUE(LEFT(TEXT(J8,"00000000"),4)),"")) | AH8: =IFERROR(XLOOKUP(AG8,Vintage_Rates!$A$2:$A$1000,Vintage_Rates!$B$2:$B$1000,""),"") | AI8: =IF(ISNUMBER(Y8),Y8,IFERROR((G8-AH8)*100,"")) | AJ8: =IF(ISNUMBER(V8),V8,IFERROR(XLOOKUP(VALUE(F8),PLC_Rates!$A$2:$A$1000,PLC_Rates!$B$2:$B$1000,""),"")) | AK8: =IF(ISNUMBER(Z8),Z8,IF(AE8=0,0,MAX(0,MIN(10,((VALUE(LEFT(TEXT(M8,"00000000"),4))-VALUE(LEFT(F8,4)))*12+(VALUE(MID(TEXT(M8,"00000000"),5,2))-VALUE(MID(F8,5,2))))/12)))) | AL8: =IFERROR(G8*100-AJ8,"") | AM8: =IFERROR(G8*100-(AJ8+(1+AK8)*12.5),"") | AN8: =IFERROR(MIN(H8/1000000,100),"") | AO8: =IFERROR(INDEX(FHA_Lookup!$B$2:$B$11,MATCH(TRUE,ISNUMBER(SEARCH(FHA_Lookup!$A$2:$A$11,UPPER(SUBSTITUTE(O8," ","")))),0)),"OTHER") | AP8: =IFERROR(INDEX(FHA_Lookup!$C$2:$C$11,MATCH(TRUE,ISNUMBER(SEARCH(FHA_Lookup!$A$2:$A$11,UPPER(SUBSTITUTE(O8," ","")))),0)),"OTHER") | AQ8: =IF(AP8="NC",1,0) | AR8: =IF(UPPER(TRIM(P8))="AFF",1,0) | AS8: =IF(UPPER(TRIM(P8))="BAF",1,0) | AT8: =IF(UPPER(TRIM(P8))="MKT",1,0) | AU8: =IF(AO8="221d4",1,0) | AV8: =IF(AO8="223a7",1,0) | AW8: =IF(AO8="232",1,0) | AX8: =IF(AO8="538",1,0) | AY8: =IF(AO8="241",1,0) | AZ8: =IF(AO8="220",1,0) | BA8: =IF(AO8="OTHER",1,0) | BB8: =IF(UPPER(TRIM(C8))="LM",1,0) | BC8: =IF(UPPER(TRIM(C8))="PN",1,0) | BD8: =IF(UPPER(TRIM(C8))="LS",1,0) | BE8: =IF(UPPER(TRIM(C8))="RX",1,0) | BF8: =IFERROR((Parameters!$C$6*AM8+Parameters!$C$7*MAX(AM8-(-150),0)+Parameters!$C$8*MAX(AM8-(-50),0)+Parameters!$C$9*MAX(AM8-(0),0)+Parameters!$C$10*MAX(AM8-(50),0)+Parameters!$C$11*MAX(AM8-(100),0)+Parameters!$C$12*MAX(AM8-(150),0)+Parameters!$C$13*MAX(AM8-(250),0)),0) | BG8: =IFERROR((Parameters!$C$14*AA8+Parameters!$C$15*MAX(AA8-(12),0)+Parameters!$C$16*MAX(AA8-(36),0)+Parameters!$C$17*MAX(AA8-(60),0)+Parameters!$C$18*MAX(AA8-(84),0)+Parameters!$C$19*MAX(AA8-(120),0)+Parameters!$C$20*MAX(AA8-(180),0)),0) | BH8: =IFERROR((Parameters!$C$21*AK8+Parameters!$C$22*MAX(AK8-(0),0)+Parameters!$C$23*MAX(AK8-(2),0)+Parameters!$C$24*MAX(AK8-(5),0)+Parameters!$C$25*MAX(AK8-(8),0)),0) | BI8: =IFERROR((Parameters!$C$26*AI8+Parameters!$C$27*MAX(AI8-(-100),0)+Parameters!$C$28*MAX(AI8-(-25),0)+Parameters!$C$29*MAX(AI8-(25),0)+Parameters!$C$30*MAX(AI8-(100),0)),0) | BJ8: =IFERROR((Parameters!$C$31*AN8+Parameters!$C$32*MAX(AN8-(2),0)+Parameters!$C$33*MAX(AN8-(10),0)+Parameters!$C$34*MAX(AN8-(25),0)),0) | BK8: =IFERROR((Parameters!$C$35*AB8+Parameters!$C$36*MAX(AB8-(12),0)+Parameters!$C$37*MAX(AB8-(24),0)+Parameters!$C$38*MAX(AB8-(60),0)),0) | BL8: =IFERROR((Parameters!$C$39*AC8+Parameters!$C$40*MAX(AC8-(6),0)+Parameters!$C$41*MAX(AC8-(12),0)+Parameters!$C$42*MAX(AC8-(24),0)),0) | BM8: =IFERROR(Parameters!$C$43*(MAX(AM8,0)*MIN(MAX(AK8,0),10))/100,0) | BN8: =Parameters!$C$44*AE8 | BO8: =Parameters!$C$45*AU8 + Parameters!$C$46*AV8 + Parameters!$C$47*AW8 + Parameters!$C$48*AX8 + Parameters!$C$49*AY8 + Parameters!$C$50*AZ8 + Parameters!$C$51*BA8 | BP8: =Parameters!$C$52*AQ8 | BQ8: =Parameters!$C$53*AR8+Parameters!$C$54*AS8+Parameters!$C$55*AT8 | BR8: =Parameters!$C$56*BB8+Parameters!$C$57*BC8+Parameters!$C$58*BD8+Parameters!$C$59*BE8 | BS8: =Parameters!$B$2 | BT8: =BS8+BF8 + BG8 + BH8 + BI8 + BJ8 + BK8 + BL8 + BM8 + BN8 + BO8 + BP8 + BQ8 + BR8 | BU8: =IF(AD8=1,0,1/(1+EXP(-BT8))*Parameters!$B$3) | BV8: =(1-(1-BU8)^12)*100 | BW8: =IF(AD8=1,0,(1-(1-1/(1+EXP(-Parameters!$B$2)))^12)*100) | BX8: =IF(AD8=1,0,BV8-(1-(1-(1/(1+EXP(-(BT8-BF8)))*Parameters!$B$3))^12)*100) | BY8: =IF(AD8=1,0,BV8-(1-(1-(1/(1+EXP(-(BT8-BG8)))*Parameters!$B$3))^12)*100) | BZ8: =IF(AD8=1,0,BV8-(1-(1-(1/(1+EXP(-(BT8-BH8)))*Parameters!$B$3))^12)*100) | CA8: =IF(AD8=1,0,BV8-(1-(1-(1/(1+EXP(-(BT8-BI8)))*Parameters!$B$3))^12)*100) | CB8: =IF(AD8=1,0,BV8-(1-(1-(1/(1+EXP(-(BT8-BJ8)))*Parameters!$B$3))^12)*100) | CC8: =IF(AD8=1,0,BV8-(1-(1-(1/(1+EXP(-(BT8-BK8)))*Parameters!$B$3))^12)*100) | CD8: =IF(AD8=1,0,BV8-(1-(1-(1/(1+EXP(-(BT8-BL8)))*Parameters!$B$3))^12)*100) | CE8: =IF(AD8=1,0,BV8-(1-(1-(1/(1+EXP(-(BT8-BM8)))*Parameters!$B$3))^12)*100) | CF8: =IF(AD8=1,0,BV8-(1-(1-(1/(1+EXP(-(BT8-BN8)))*Parameters!$B$3))^12)*100) | CG8: =IF(AD8=1,0,BV8-(1-(1-(1/(1+EXP(-(BT8-BO8)))*Parameters!$B$3))^12)*100) | CH8: =IF(AD8=1,0,BV8-(1-(1-(1/(1+EXP(-(BT8-BP8)))*Parameters!$B$3))^12)*100) | CI8: =IF(AD8=1,0,BV8-(1-(1-(1/(1+EXP(-(BT8-BQ8)))*Parameters!$B$3))^12)*100) | CJ8: =IF(AD8=1,0,BV8-(1-(1-(1/(1+EXP(-(BT8-BR8)))*Parameters!$B$3))^12)*100)
A9: GNR_2024_NEW | B9: 3618GTXQ3 | C9: PN | D9: BERKADIA COMMERCIAL MORTGAGE, LLC | E9: 3618GTXQ3_000000006311195 | F9: 202603 | G9: 5.07 | H9: 21410853 | I9: 420 | J9: 20240625 | K9: 20590901 | M9: 20341001 | N9: 10 | O9: 207/223(F) | P9: MKT | T9: FL | U9: 124 | V9: 490.5 | W9: 21 | X9: 2024 | Y9: -71 | Z9: 10 | AA9: =IF(ISNUMBER(W9),W9,IFERROR(MAX(0,(VALUE(LEFT(F9,4))-VALUE(LEFT(TEXT(J9,"00000000"),4)))*12+(VALUE(MID(F9,5,2))-VALUE(MID(TEXT(J9,"00000000"),5,2)))),"")) | AB9: =IFERROR((VALUE(LEFT(TEXT(K9,"00000000"),4))-VALUE(LEFT(F9,4)))*12+(VALUE(MID(TEXT(K9,"00000000"),5,2))-VALUE(MID(F9,5,2))),"") | AC9: =IF(OR(L9="",NOT(ISNUMBER(L9))),0,MAX(0,MIN(60,(VALUE(LEFT(F9,4))-VALUE(LEFT(TEXT(L9,"00000000"),4)))*12+(VALUE(MID(F9,5,2))-VALUE(MID(TEXT(L9,"00000000"),5,2)))))) | AD9: =IF(OR(L9="",NOT(ISNUMBER(L9))),0,IF(VALUE(F9)<VALUE(LEFT(TEXT(L9,"00000000"),6)),1,0)) | AE9: =IF(OR(M9="",NOT(ISNUMBER(M9))),0,IF(VALUE(F9)<VALUE(LEFT(TEXT(M9,"00000000"),6)),1,0)) | AF9: =IF(AND(AD9=0,AE9=0),1,0) | AG9: =IF(ISNUMBER(X9),X9,IFERROR(VALUE(LEFT(TEXT(J9,"00000000"),4)),"")) | AH9: =IFERROR(XLOOKUP(AG9,Vintage_Rates!$A$2:$A$1000,Vintage_Rates!$B$2:$B$1000,""),"") | AI9: =IF(ISNUMBER(Y9),Y9,IFERROR((G9-AH9)*100,"")) | AJ9: =IF(ISNUMBER(V9),V9,IFERROR(XLOOKUP(VALUE(F9),PLC_Rates!$A$2:$A$1000,PLC_Rates!$B$2:$B$1000,""),"")) | AK9: =IF(ISNUMBER(Z9),Z9,IF(AE9=0,0,MAX(0,MIN(10,((VALUE(LEFT(TEXT(M9,"00000000"),4))-VALUE(LEFT(F9,4)))*12+(VALUE(MID(TEXT(M9,"00000000"),5,2))-VALUE(MID(F9,5,2))))/12)))) | AL9: =IFERROR(G9*100-AJ9,"") | AM9: =IFERROR(G9*100-(AJ9+(1+AK9)*12.5),"") | AN9: =IFERROR(MIN(H9/1000000,100),"") | AO9: =IFERROR(INDEX(FHA_Lookup!$B$2:$B$11,MATCH(TRUE,ISNUMBER(SEARCH(FHA_Lookup!$A$2:$A$11,UPPER(SUBSTITUTE(O9," ","")))),0)),"OTHER") | AP9: =IFERROR(INDEX(FHA_Lookup!$C$2:$C$11,MATCH(TRUE,ISNUMBER(SEARCH(FHA_Lookup!$A$2:$A$11,UPPER(SUBSTITUTE(O9," ","")))),0)),"OTHER") | AQ9: =IF(AP9="NC",1,0) | AR9: =IF(UPPER(TRIM(P9))="AFF",1,0) | AS9: =IF(UPPER(TRIM(P9))="BAF",1,0) | AT9: =IF(UPPER(TRIM(P9))="MKT",1,0) | AU9: =IF(AO9="221d4",1,0) | AV9: =IF(AO9="223a7",1,0) | AW9: =IF(AO9="232",1,0) | AX9: =IF(AO9="538",1,0) | AY9: =IF(AO9="241",1,0) | AZ9: =IF(AO9="220",1,0) | BA9: =IF(AO9="OTHER",1,0) | BB9: =IF(UPPER(TRIM(C9))="LM",1,0) | BC9: =IF(UPPER(TRIM(C9))="PN",1,0) | BD9: =IF(UPPER(TRIM(C9))="LS",1,0) | BE9: =IF(UPPER(TRIM(C9))="RX",1,0) | BF9: =IFERROR((Parameters!$C$6*AM9+Parameters!$C$7*MAX(AM9-(-150),0)+Parameters!$C$8*MAX(AM9-(-50),0)+Parameters!$C$9*MAX(AM9-(0),0)+Parameters!$C$10*MAX(AM9-(50),0)+Parameters!$C$11*MAX(AM9-(100),0)+Parameters!$C$12*MAX(AM9-(150),0)+Parameters!$C$13*MAX(AM9-(250),0)),0) | BG9: =IFERROR((Parameters!$C$14*AA9+Parameters!$C$15*MAX(AA9-(12),0)+Parameters!$C$16*MAX(AA9-(36),0)+Parameters!$C$17*MAX(AA9-(60),0)+Parameters!$C$18*MAX(AA9-(84),0)+Parameters!$C$19*MAX(AA9-(120),0)+Parameters!$C$20*MAX(AA9-(180),0)),0) | BH9: =IFERROR((Parameters!$C$21*AK9+Parameters!$C$22*MAX(AK9-(0),0)+Parameters!$C$23*MAX(AK9-(2),0)+Parameters!$C$24*MAX(AK9-(5),0)+Parameters!$C$25*MAX(AK9-(8),0)),0) | BI9: =IFERROR((Parameters!$C$26*AI9+Parameters!$C$27*MAX(AI9-(-100),0)+Parameters!$C$28*MAX(AI9-(-25),0)+Parameters!$C$29*MAX(AI9-(25),0)+Parameters!$C$30*MAX(AI9-(100),0)),0) | BJ9: =IFERROR((Parameters!$C$31*AN9+Parameters!$C$32*MAX(AN9-(2),0)+Parameters!$C$33*MAX(AN9-(10),0)+Parameters!$C$34*MAX(AN9-(25),0)),0) | BK9: =IFERROR((Parameters!$C$35*AB9+Parameters!$C$36*MAX(AB9-(12),0)+Parameters!$C$37*MAX(AB9-(24),0)+Parameters!$C$38*MAX(AB9-(60),0)),0) | BL9: =IFERROR((Parameters!$C$39*AC9+Parameters!$C$40*MAX(AC9-(6),0)+Parameters!$C$41*MAX(AC9-(12),0)+Parameters!$C$42*MAX(AC9-(24),0)),0) | BM9: =IFERROR(Parameters!$C$43*(MAX(AM9,0)*MIN(MAX(AK9,0),10))/100,0) | BN9: =Parameters!$C$44*AE9 | BO9: =Parameters!$C$45*AU9 + Parameters!$C$46*AV9 + Parameters!$C$47*AW9 + Parameters!$C$48*AX9 + Parameters!$C$49*AY9 + Parameters!$C$50*AZ9 + Parameters!$C$51*BA9 | BP9: =Parameters!$C$52*AQ9 | BQ9: =Parameters!$C$53*AR9+Parameters!$C$54*AS9+Parameters!$C$55*AT9 | BR9: =Parameters!$C$56*BB9+Parameters!$C$57*BC9+Parameters!$C$58*BD9+Parameters!$C$59*BE9 | BS9: =Parameters!$B$2 | BT9: =BS9+BF9 + BG9 + BH9 + BI9 + BJ9 + BK9 + BL9 + BM9 + BN9 + BO9 + BP9 + BQ9 + BR9 | BU9: =IF(AD9=1,0,1/(1+EXP(-BT9))*Parameters!$B$3) | BV9: =(1-(1-BU9)^12)*100 | BW9: =IF(AD9=1,0,(1-(1-1/(1+EXP(-Parameters!$B$2)))^12)*100) | BX9: =IF(AD9=1,0,BV9-(1-(1-(1/(1+EXP(-(BT9-BF9)))*Parameters!$B$3))^12)*100) | BY9: =IF(AD9=1,0,BV9-(1-(1-(1/(1+EXP(-(BT9-BG9)))*Parameters!$B$3))^12)*100) | BZ9: =IF(AD9=1,0,BV9-(1-(1-(1/(1+EXP(-(BT9-BH9)))*Parameters!$B$3))^12)*100) | CA9: =IF(AD9=1,0,BV9-(1-(1-(1/(1+EXP(-(BT9-BI9)))*Parameters!$B$3))^12)*100) | CB9: =IF(AD9=1,0,BV9-(1-(1-(1/(1+EXP(-(BT9-BJ9)))*Parameters!$B$3))^12)*100) | CC9: =IF(AD9=1,0,BV9-(1-(1-(1/(1+EXP(-(BT9-BK9)))*Parameters!$B$3))^12)*100) | CD9: =IF(AD9=1,0,BV9-(1-(1-(1/(1+EXP(-(BT9-BL9)))*Parameters!$B$3))^12)*100) | CE9: =IF(AD9=1,0,BV9-(1-(1-(1/(1+EXP(-(BT9-BM9)))*Parameters!$B$3))^12)*100) | CF9: =IF(AD9=1,0,BV9-(1-(1-(1/(1+EXP(-(BT9-BN9)))*Parameters!$B$3))^12)*100) | CG9: =IF(AD9=1,0,BV9-(1-(1-(1/(1+EXP(-(BT9-BO9)))*Parameters!$B$3))^12)*100) | CH9: =IF(AD9=1,0,BV9-(1-(1-(1/(1+EXP(-(BT9-BP9)))*Parameters!$B$3))^12)*100) | CI9: =IF(AD9=1,0,BV9-(1-(1-(1/(1+EXP(-(BT9-BQ9)))*Parameters!$B$3))^12)*100) | CJ9: =IF(AD9=1,0,BV9-(1-(1-(1/(1+EXP(-(BT9-BR9)))*Parameters!$B$3))^12)*100)
A10: GNR_2024_NEW | B10: 3618JS5S9 | C10: PN | D10: BERKADIA COMMERCIAL MORTGAGE, LLC | E10: 3618JS5S9_000000005422124 | F10: 202603 | G10: 5.88 | H10: 6297447.2 | I10: 360 | J10: 20250115 | K10: 20550401 | M10: 20350501 | N10: 10 | O10: 232/223(f) | T10: SC | U10: 60 | V10: 490.5 | W10: 14 | X10: 2025 | Y10: 6 | Z10: 0 | AA10: =IF(ISNUMBER(W10),W10,IFERROR(MAX(0,(VALUE(LEFT(F10,4))-VALUE(LEFT(TEXT(J10,"00000000"),4)))*12+(VALUE(MID(F10,5,2))-VALUE(MID(TEXT(J10,"00000000"),5,2)))),"")) | AB10: =IFERROR((VALUE(LEFT(TEXT(K10,"00000000"),4))-VALUE(LEFT(F10,4)))*12+(VALUE(MID(TEXT(K10,"00000000"),5,2))-VALUE(MID(F10,5,2))),"") | AC10: =IF(OR(L10="",NOT(ISNUMBER(L10))),0,MAX(0,MIN(60,(VALUE(LEFT(F10,4))-VALUE(LEFT(TEXT(L10,"00000000"),4)))*12+(VALUE(MID(F10,5,2))-VALUE(MID(TEXT(L10,"00000000"),5,2)))))) | AD10: =IF(OR(L10="",NOT(ISNUMBER(L10))),0,IF(VALUE(F10)<VALUE(LEFT(TEXT(L10,"00000000"),6)),1,0)) | AE10: =IF(OR(M10="",NOT(ISNUMBER(M10))),0,IF(VALUE(F10)<VALUE(LEFT(TEXT(M10,"00000000"),6)),1,0)) | AF10: =IF(AND(AD10=0,AE10=0),1,0) | AG10: =IF(ISNUMBER(X10),X10,IFERROR(VALUE(LEFT(TEXT(J10,"00000000"),4)),"")) | AH10: =IFERROR(XLOOKUP(AG10,Vintage_Rates!$A$2:$A$1000,Vintage_Rates!$B$2:$B$1000,""),"") | AI10: =IF(ISNUMBER(Y10),Y10,IFERROR((G10-AH10)*100,"")) | AJ10: =IF(ISNUMBER(V10),V10,IFERROR(XLOOKUP(VALUE(F10),PLC_Rates!$A$2:$A$1000,PLC_Rates!$B$2:$B$1000,""),"")) | AK10: =IF(ISNUMBER(Z10),Z10,IF(AE10=0,0,MAX(0,MIN(10,((VALUE(LEFT(TEXT(M10,"00000000"),4))-VALUE(LEFT(F10,4)))*12+(VALUE(MID(TEXT(M10,"00000000"),5,2))-VALUE(MID(F10,5,2))))/12)))) | AL10: =IFERROR(G10*100-AJ10,"") | AM10: =IFERROR(G10*100-(AJ10+(1+AK10)*12.5),"") | AN10: =IFERROR(MIN(H10/1000000,100),"") | AO10: =IFERROR(INDEX(FHA_Lookup!$B$2:$B$11,MATCH(TRUE,ISNUMBER(SEARCH(FHA_Lookup!$A$2:$A$11,UPPER(SUBSTITUTE(O10," ","")))),0)),"OTHER") | AP10: =IFERROR(INDEX(FHA_Lookup!$C$2:$C$11,MATCH(TRUE,ISNUMBER(SEARCH(FHA_Lookup!$A$2:$A$11,UPPER(SUBSTITUTE(O10," ","")))),0)),"OTHER") | AQ10: =IF(AP10="NC",1,0) | AR10: =IF(UPPER(TRIM(P10))="AFF",1,0) | AS10: =IF(UPPER(TRIM(P10))="BAF",1,0) | AT10: =IF(UPPER(TRIM(P10))="MKT",1,0) | AU10: =IF(AO10="221d4",1,0) | AV10: =IF(AO10="223a7",1,0) | AW10: =IF(AO10="232",1,0) | AX10: =IF(AO10="538",1,0) | AY10: =IF(AO10="241",1,0) | AZ10: =IF(AO10="220",1,0) | BA10: =IF(AO10="OTHER",1,0) | BB10: =IF(UPPER(TRIM(C10))="LM",1,0) | BC10: =IF(UPPER(TRIM(C10))="PN",1,0) | BD10: =IF(UPPER(TRIM(C10))="LS",1,0) | BE10: =IF(UPPER(TRIM(C10))="RX",1,0) | BF10: =IFERROR((Parameters!$C$6*AM10+Parameters!$C$7*MAX(AM10-(-150),0)+Parameters!$C$8*MAX(AM10-(-50),0)+Parameters!$C$9*MAX(AM10-(0),0)+Parameters!$C$10*MAX(AM10-(50),0)+Parameters!$C$11*MAX(AM10-(100),0)+Parameters!$C$12*MAX(AM10-(150),0)+Parameters!$C$13*MAX(AM10-(250),0)),0) | BG10: =IFERROR((Parameters!$C$14*AA10+Parameters!$C$15*MAX(AA10-(12),0)+Parameters!$C$16*MAX(AA10-(36),0)+Parameters!$C$17*MAX(AA10-(60),0)+Parameters!$C$18*MAX(AA10-(84),0)+Parameters!$C$19*MAX(AA10-(120),0)+Parameters!$C$20*MAX(AA10-(180),0)),0) | BH10: =IFERROR((Parameters!$C$21*AK10+Parameters!$C$22*MAX(AK10-(0),0)+Parameters!$C$23*MAX(AK10-(2),0)+Parameters!$C$24*MAX(AK10-(5),0)+Parameters!$C$25*MAX(AK10-(8),0)),0) | BI10: =IFERROR((Parameters!$C$26*AI10+Parameters!$C$27*MAX(AI10-(-100),0)+Parameters!$C$28*MAX(AI10-(-25),0)+Parameters!$C$29*MAX(AI10-(25),0)+Parameters!$C$30*MAX(AI10-(100),0)),0) | BJ10: =IFERROR((Parameters!$C$31*AN10+Parameters!$C$32*MAX(AN10-(2),0)+Parameters!$C$33*MAX(AN10-(10),0)+Parameters!$C$34*MAX(AN10-(25),0)),0) | BK10: =IFERROR((Parameters!$C$35*AB10+Parameters!$C$36*MAX(AB10-(12),0)+Parameters!$C$37*MAX(AB10-(24),0)+Parameters!$C$38*MAX(AB10-(60),0)),0) | BL10: =IFERROR((Parameters!$C$39*AC10+Parameters!$C$40*MAX(AC10-(6),0)+Parameters!$C$41*MAX(AC10-(12),0)+Parameters!$C$42*MAX(AC10-(24),0)),0) | BM10: =IFERROR(Parameters!$C$43*(MAX(AM10,0)*MIN(MAX(AK10,0),10))/100,0) | BN10: =Parameters!$C$44*AE10 | BO10: =Parameters!$C$45*AU10 + Parameters!$C$46*AV10 + Parameters!$C$47*AW10 + Parameters!$C$48*AX10 + Parameters!$C$49*AY10 + Parameters!$C$50*AZ10 + Parameters!$C$51*BA10 | BP10: =Parameters!$C$52*AQ10 | BQ10: =Parameters!$C$53*AR10+Parameters!$C$54*AS10+Parameters!$C$55*AT10 | BR10: =Parameters!$C$56*BB10+Parameters!$C$57*BC10+Parameters!$C$58*BD10+Parameters!$C$59*BE10 | BS10: =Parameters!$B$2 | BT10: =BS10+BF10 + BG10 + BH10 + BI10 + BJ10 + BK10 + BL10 + BM10 + BN10 + BO10 + BP10 + BQ10 + BR10 | BU10: =IF(AD10=1,0,1/(1+EXP(-BT10))*Parameters!$B$3) | BV10: =(1-(1-BU10)^12)*100 | BW10: =IF(AD10=1,0,(1-(1-1/(1+EXP(-Parameters!$B$2)))^12)*100) | BX10: =IF(AD10=1,0,BV10-(1-(1-(1/(1+EXP(-(BT10-BF10)))*Parameters!$B$3))^12)*100) | BY10: =IF(AD10=1,0,BV10-(1-(1-(1/(1+EXP(-(BT10-BG10)))*Parameters!$B$3))^12)*100) | BZ10: =IF(AD10=1,0,BV10-(1-(1-(1/(1+EXP(-(BT10-BH10)))*Parameters!$B$3))^12)*100) | CA10: =IF(AD10=1,0,BV10-(1-(1-(1/(1+EXP(-(BT10-BI10)))*Parameters!$B$3))^12)*100) | CB10: =IF(AD10=1,0,BV10-(1-(1-(1/(1+EXP(-(BT10-BJ10)))*Parameters!$B$3))^12)*100) | CC10: =IF(AD10=1,0,BV10-(1-(1-(1/(1+EXP(-(BT10-BK10)))*Parameters!$B$3))^12)*100) | CD10: =IF(AD10=1,0,BV10-(1-(1-(1/(1+EXP(-(BT10-BL10)))*Parameters!$B$3))^12)*100) | CE10: =IF(AD10=1,0,BV10-(1-(1-(1/(1+EXP(-(BT10-BM10)))*Parameters!$B$3))^12)*100) | CF10: =IF(AD10=1,0,BV10-(1-(1-(1/(1+EXP(-(BT10-BN10)))*Parameters!$B$3))^12)*100) | CG10: =IF(AD10=1,0,BV10-(1-(1-(1/(1+EXP(-(BT10-BO10)))*Parameters!$B$3))^12)*100) | CH10: =IF(AD10=1,0,BV10-(1-(1-(1/(1+EXP(-(BT10-BP10)))*Parameters!$B$3))^12)*100) | CI10: =IF(AD10=1,0,BV10-(1-(1-(1/(1+EXP(-(BT10-BQ10)))*Parameters!$B$3))^12)*100) | CJ10: =IF(AD10=1,0,BV10-(1-(1-(1/(1+EXP(-(BT10-BR10)))*Parameters!$B$3))^12)*100)
A11: GNR_2024_NEW | B11: 3618AVAN6 | C11: PN | D11: GREYSTONE FUNDING COMPANY LLC | E11: 3618AVAN6_000000001211578 | F11: 202603 | G11: 5.42 | H11: 62488944 | I11: 420 | J11: 20230228 | K11: 20580301 | M11: 20330401 | N11: 10 | O11: 207/223(F) | P11: BAF | T11: NY | U11: 251 | V11: 490.5 | W11: 37 | X11: 2023 | Y11: -16.5 | Z11: 8 | AA11: =IF(ISNUMBER(W11),W11,IFERROR(MAX(0,(VALUE(LEFT(F11,4))-VALUE(LEFT(TEXT(J11,"00000000"),4)))*12+(VALUE(MID(F11,5,2))-VALUE(MID(TEXT(J11,"00000000"),5,2)))),"")) | AB11: =IFERROR((VALUE(LEFT(TEXT(K11,"00000000"),4))-VALUE(LEFT(F11,4)))*12+(VALUE(MID(TEXT(K11,"00000000"),5,2))-VALUE(MID(F11,5,2))),"") | AC11: =IF(OR(L11="",NOT(ISNUMBER(L11))),0,MAX(0,MIN(60,(VALUE(LEFT(F11,4))-VALUE(LEFT(TEXT(L11,"00000000"),4)))*12+(VALUE(MID(F11,5,2))-VALUE(MID(TEXT(L11,"00000000"),5,2)))))) | AD11: =IF(OR(L11="",NOT(ISNUMBER(L11))),0,IF(VALUE(F11)<VALUE(LEFT(TEXT(L11,"00000000"),6)),1,0)) | AE11: =IF(OR(M11="",NOT(ISNUMBER(M11))),0,IF(VALUE(F11)<VALUE(LEFT(TEXT(M11,"00000000"),6)),1,0)) | AF11: =IF(AND(AD11=0,AE11=0),1,0) | AG11: =IF(ISNUMBER(X11),X11,IFERROR(VALUE(LEFT(TEXT(J11,"00000000"),4)),"")) | AH11: =IFERROR(XLOOKUP(AG11,Vintage_Rates!$A$2:$A$1000,Vintage_Rates!$B$2:$B$1000,""),"") | AI11: =IF(ISNUMBER(Y11),Y11,IFERROR((G11-AH11)*100,"")) | AJ11: =IF(ISNUMBER(V11),V11,IFERROR(XLOOKUP(VALUE(F11),PLC_Rates!$A$2:$A$1000,PLC_Rates!$B$2:$B$1000,""),"")) | AK11: =IF(ISNUMBER(Z11),Z11,IF(AE11=0,0,MAX(0,MIN(10,((VALUE(LEFT(TEXT(M11,"00000000"),4))-VALUE(LEFT(F11,4)))*12+(VALUE(MID(TEXT(M11,"00000000"),5,2))-VALUE(MID(F11,5,2))))/12)))) | AL11: =IFERROR(G11*100-AJ11,"") | AM11: =IFERROR(G11*100-(AJ11+(1+AK11)*12.5),"") | AN11: =IFERROR(MIN(H11/1000000,100),"") | AO11: =IFERROR(INDEX(FHA_Lookup!$B$2:$B$11,MATCH(TRUE,ISNUMBER(SEARCH(FHA_Lookup!$A$2:$A$11,UPPER(SUBSTITUTE(O11," ","")))),0)),"OTHER") | AP11: =IFERROR(INDEX(FHA_Lookup!$C$2:$C$11,MATCH(TRUE,ISNUMBER(SEARCH(FHA_Lookup!$A$2:$A$11,UPPER(SUBSTITUTE(O11," ","")))),0)),"OTHER") | AQ11: =IF(AP11="NC",1,0) | AR11: =IF(UPPER(TRIM(P11))="AFF",1,0) | AS11: =IF(UPPER(TRIM(P11))="BAF",1,0) | AT11: =IF(UPPER(TRIM(P11))="MKT",1,0) | AU11: =IF(AO11="221d4",1,0) | AV11: =IF(AO11="223a7",1,0) | AW11: =IF(AO11="232",1,0) | AX11: =IF(AO11="538",1,0) | AY11: =IF(AO11="241",1,0) | AZ11: =IF(AO11="220",1,0) | BA11: =IF(AO11="OTHER",1,0) | BB11: =IF(UPPER(TRIM(C11))="LM",1,0) | BC11: =IF(UPPER(TRIM(C11))="PN",1,0) | BD11: =IF(UPPER(TRIM(C11))="LS",1,0) | BE11: =IF(UPPER(TRIM(C11))="RX",1,0) | BF11: =IFERROR((Parameters!$C$6*AM11+Parameters!$C$7*MAX(AM11-(-150),0)+Parameters!$C$8*MAX(AM11-(-50),0)+Parameters!$C$9*MAX(AM11-(0),0)+Parameters!$C$10*MAX(AM11-(50),0)+Parameters!$C$11*MAX(AM11-(100),0)+Parameters!$C$12*MAX(AM11-(150),0)+Parameters!$C$13*MAX(AM11-(250),0)),0) | BG11: =IFERROR((Parameters!$C$14*AA11+Parameters!$C$15*MAX(AA11-(12),0)+Parameters!$C$16*MAX(AA11-(36),0)+Parameters!$C$17*MAX(AA11-(60),0)+Parameters!$C$18*MAX(AA11-(84),0)+Parameters!$C$19*MAX(AA11-(120),0)+Parameters!$C$20*MAX(AA11-(180),0)),0) | BH11: =IFERROR((Parameters!$C$21*AK11+Parameters!$C$22*MAX(AK11-(0),0)+Parameters!$C$23*MAX(AK11-(2),0)+Parameters!$C$24*MAX(AK11-(5),0)+Parameters!$C$25*MAX(AK11-(8),0)),0) | BI11: =IFERROR((Parameters!$C$26*AI11+Parameters!$C$27*MAX(AI11-(-100),0)+Parameters!$C$28*MAX(AI11-(-25),0)+Parameters!$C$29*MAX(AI11-(25),0)+Parameters!$C$30*MAX(AI11-(100),0)),0) | BJ11: =IFERROR((Parameters!$C$31*AN11+Parameters!$C$32*MAX(AN11-(2),0)+Parameters!$C$33*MAX(AN11-(10),0)+Parameters!$C$34*MAX(AN11-(25),0)),0) | BK11: =IFERROR((Parameters!$C$35*AB11+Parameters!$C$36*MAX(AB11-(12),0)+Parameters!$C$37*MAX(AB11-(24),0)+Parameters!$C$38*MAX(AB11-(60),0)),0) | BL11: =IFERROR((Parameters!$C$39*AC11+Parameters!$C$40*MAX(AC11-(6),0)+Parameters!$C$41*MAX(AC11-(12),0)+Parameters!$C$42*MAX(AC11-(24),0)),0) | BM11: =IFERROR(Parameters!$C$43*(MAX(AM11,0)*MIN(MAX(AK11,0),10))/100,0) | BN11: =Parameters!$C$44*AE11 | BO11: =Parameters!$C$45*AU11 + Parameters!$C$46*AV11 + Parameters!$C$47*AW11 + Parameters!$C$48*AX11 + Parameters!$C$49*AY11 + Parameters!$C$50*AZ11 + Parameters!$C$51*BA11 | BP11: =Parameters!$C$52*AQ11 | BQ11: =Parameters!$C$53*AR11+Parameters!$C$54*AS11+Parameters!$C$55*AT11 | BR11: =Parameters!$C$56*BB11+Parameters!$C$57*BC11+Parameters!$C$58*BD11+Parameters!$C$59*BE11 | BS11: =Parameters!$B$2 | BT11: =BS11+BF11 + BG11 + BH11 + BI11 + BJ11 + BK11 + BL11 + BM11 + BN11 + BO11 + BP11 + BQ11 + BR11 | BU11: =IF(AD11=1,0,1/(1+EXP(-BT11))*Parameters!$B$3) | BV11: =(1-(1-BU11)^12)*100 | BW11: =IF(AD11=1,0,(1-(1-1/(1+EXP(-Parameters!$B$2)))^12)*100) | BX11: =IF(AD11=1,0,BV11-(1-(1-(1/(1+EXP(-(BT11-BF11)))*Parameters!$B$3))^12)*100) | BY11: =IF(AD11=1,0,BV11-(1-(1-(1/(1+EXP(-(BT11-BG11)))*Parameters!$B$3))^12)*100) | BZ11: =IF(AD11=1,0,BV11-(1-(1-(1/(1+EXP(-(BT11-BH11)))*Parameters!$B$3))^12)*100) | CA11: =IF(AD11=1,0,BV11-(1-(1-(1/(1+EXP(-(BT11-BI11)))*Parameters!$B$3))^12)*100) | CB11: =IF(AD11=1,0,BV11-(1-(1-(1/(1+EXP(-(BT11-BJ11)))*Parameters!$B$3))^12)*100) | CC11: =IF(AD11=1,0,BV11-(1-(1-(1/(1+EXP(-(BT11-BK11)))*Parameters!$B$3))^12)*100) | CD11: =IF(AD11=1,0,BV11-(1-(1-(1/(1+EXP(-(BT11-BL11)))*Parameters!$B$3))^12)*100) | CE11: =IF(AD11=1,0,BV11-(1-(1-(1/(1+EXP(-(BT11-BM11)))*Parameters!$B$3))^12)*100) | CF11: =IF(AD11=1,0,BV11-(1-(1-(1/(1+EXP(-(BT11-BN11)))*Parameters!$B$3))^12)*100) | CG11: =IF(AD11=1,0,BV11-(1-(1-(1/(1+EXP(-(BT11-BO11)))*Parameters!$B$3))^12)*100) | CH11: =IF(AD11=1,0,BV11-(1-(1-(1/(1+EXP(-(BT11-BP11)))*Parameters!$B$3))^12)*100) | CI11: =IF(AD11=1,0,BV11-(1-(1-(1/(1+EXP(-(BT11-BQ11)))*Parameters!$B$3))^12)*100) | CJ11: =IF(AD11=1,0,BV11-(1-(1-(1/(1+EXP(-(BT11-BR11)))*Parameters!$B$3))^12)*100)
A12: GNR_2024_NEW | B12: 3618G0RF7 | C12: PN | D12: VIUM CAPITAL MORTGAGE, LLC. | E12: 3618G0RF7_000000011422143 | F12: 202603 | G12: 6.69 | H12: 15740254 | I12: 420 | J12: 20240501 | K12: 20590601 | M12: 20340701 | N12: 10 | O12: 232/223(F) | P12: MKT | T12: TX | U12: 62 | V12: 490.5 | W12: 22 | X12: 2024 | Y12: 91 | Z12: 10 | AA12: =IF(ISNUMBER(W12),W12,IFERROR(MAX(0,(VALUE(LEFT(F12,4))-VALUE(LEFT(TEXT(J12,"00000000"),4)))*12+(VALUE(MID(F12,5,2))-VALUE(MID(TEXT(J12,"00000000"),5,2)))),"")) | AB12: =IFERROR((VALUE(LEFT(TEXT(K12,"00000000"),4))-VALUE(LEFT(F12,4)))*12+(VALUE(MID(TEXT(K12,"00000000"),5,2))-VALUE(MID(F12,5,2))),"") | AC12: =IF(OR(L12="",NOT(ISNUMBER(L12))),0,MAX(0,MIN(60,(VALUE(LEFT(F12,4))-VALUE(LEFT(TEXT(L12,"00000000"),4)))*12+(VALUE(MID(F12,5,2))-VALUE(MID(TEXT(L12,"00000000"),5,2)))))) | AD12: =IF(OR(L12="",NOT(ISNUMBER(L12))),0,IF(VALUE(F12)<VALUE(LEFT(TEXT(L12,"00000000"),6)),1,0)) | AE12: =IF(OR(M12="",NOT(ISNUMBER(M12))),0,IF(VALUE(F12)<VALUE(LEFT(TEXT(M12,"00000000"),6)),1,0)) | AF12: =IF(AND(AD12=0,AE12=0),1,0) | AG12: =IF(ISNUMBER(X12),X12,IFERROR(VALUE(LEFT(TEXT(J12,"00000000"),4)),"")) | AH12: =IFERROR(XLOOKUP(AG12,Vintage_Rates!$A$2:$A$1000,Vintage_Rates!$B$2:$B$1000,""),"") | AI12: =IF(ISNUMBER(Y12),Y12,IFERROR((G12-AH12)*100,"")) | AJ12: =IF(ISNUMBER(V12),V12,IFERROR(XLOOKUP(VALUE(F12),PLC_Rates!$A$2:$A$1000,PLC_Rates!$B$2:$B$1000,""),"")) | AK12: =IF(ISNUMBER(Z12),Z12,IF(AE12=0,0,MAX(0,MIN(10,((VALUE(LEFT(TEXT(M12,"00000000"),4))-VALUE(LEFT(F12,4)))*12+(VALUE(MID(TEXT(M12,"00000000"),5,2))-VALUE(MID(F12,5,2))))/12)))) | AL12: =IFERROR(G12*100-AJ12,"") | AM12: =IFERROR(G12*100-(AJ12+(1+AK12)*12.5),"") | AN12: =IFERROR(MIN(H12/1000000,100),"") | AO12: =IFERROR(INDEX(FHA_Lookup!$B$2:$B$11,MATCH(TRUE,ISNUMBER(SEARCH(FHA_Lookup!$A$2:$A$11,UPPER(SUBSTITUTE(O12," ","")))),0)),"OTHER") | AP12: =IFERROR(INDEX(FHA_Lookup!$C$2:$C$11,MATCH(TRUE,ISNUMBER(SEARCH(FHA_Lookup!$A$2:$A$11,UPPER(SUBSTITUTE(O12," ","")))),0)),"OTHER") | AQ12: =IF(AP12="NC",1,0) | AR12: =IF(UPPER(TRIM(P12))="AFF",1,0) | AS12: =IF(UPPER(TRIM(P12))="BAF",1,0) | AT12: =IF(UPPER(TRIM(P12))="MKT",1,0) | AU12: =IF(AO12="221d4",1,0) | AV12: =IF(AO12="223a7",1,0) | AW12: =IF(AO12="232",1,0) | AX12: =IF(AO12="538",1,0) | AY12: =IF(AO12="241",1,0) | AZ12: =IF(AO12="220",1,0) | BA12: =IF(AO12="OTHER",1,0) | BB12: =IF(UPPER(TRIM(C12))="LM",1,0) | BC12: =IF(UPPER(TRIM(C12))="PN",1,0) | BD12: =IF(UPPER(TRIM(C12))="LS",1,0) | BE12: =IF(UPPER(TRIM(C12))="RX",1,0) | BF12: =IFERROR((Parameters!$C$6*AM12+Parameters!$C$7*MAX(AM12-(-150),0)+Parameters!$C$8*MAX(AM12-(-50),0)+Parameters!$C$9*MAX(AM12-(0),0)+Parameters!$C$10*MAX(AM12-(50),0)+Parameters!$C$11*MAX(AM12-(100),0)+Parameters!$C$12*MAX(AM12-(150),0)+Parameters!$C$13*MAX(AM12-(250),0)),0) | BG12: =IFERROR((Parameters!$C$14*AA12+Parameters!$C$15*MAX(AA12-(12),0)+Parameters!$C$16*MAX(AA12-(36),0)+Parameters!$C$17*MAX(AA12-(60),0)+Parameters!$C$18*MAX(AA12-(84),0)+Parameters!$C$19*MAX(AA12-(120),0)+Parameters!$C$20*MAX(AA12-(180),0)),0) | BH12: =IFERROR((Parameters!$C$21*AK12+Parameters!$C$22*MAX(AK12-(0),0)+Parameters!$C$23*MAX(AK12-(2),0)+Parameters!$C$24*MAX(AK12-(5),0)+Parameters!$C$25*MAX(AK12-(8),0)),0) | BI12: =IFERROR((Parameters!$C$26*AI12+Parameters!$C$27*MAX(AI12-(-100),0)+Parameters!$C$28*MAX(AI12-(-25),0)+Parameters!$C$29*MAX(AI12-(25),0)+Parameters!$C$30*MAX(AI12-(100),0)),0) | BJ12: =IFERROR((Parameters!$C$31*AN12+Parameters!$C$32*MAX(AN12-(2),0)+Parameters!$C$33*MAX(AN12-(10),0)+Parameters!$C$34*MAX(AN12-(25),0)),0) | BK12: =IFERROR((Parameters!$C$35*AB12+Parameters!$C$36*MAX(AB12-(12),0)+Parameters!$C$37*MAX(AB12-(24),0)+Parameters!$C$38*MAX(AB12-(60),0)),0) | BL12: =IFERROR((Parameters!$C$39*AC12+Parameters!$C$40*MAX(AC12-(6),0)+Parameters!$C$41*MAX(AC12-(12),0)+Parameters!$C$42*MAX(AC12-(24),0)),0) | BM12: =IFERROR(Parameters!$C$43*(MAX(AM12,0)*MIN(MAX(AK12,0),10))/100,0) | BN12: =Parameters!$C$44*AE12 | BO12: =Parameters!$C$45*AU12 + Parameters!$C$46*AV12 + Parameters!$C$47*AW12 + Parameters!$C$48*AX12 + Parameters!$C$49*AY12 + Parameters!$C$50*AZ12 + Parameters!$C$51*BA12 | BP12: =Parameters!$C$52*AQ12 | BQ12: =Parameters!$C$53*AR12+Parameters!$C$54*AS12+Parameters!$C$55*AT12 | BR12: =Parameters!$C$56*BB12+Parameters!$C$57*BC12+Parameters!$C$58*BD12+Parameters!$C$59*BE12 | BS12: =Parameters!$B$2 | BT12: =BS12+BF12 + BG12 + BH12 + BI12 + BJ12 + BK12 + BL12 + BM12 + BN12 + BO12 + BP12 + BQ12 + BR12 | BU12: =IF(AD12=1,0,1/(1+EXP(-BT12))*Parameters!$B$3) | BV12: =(1-(1-BU12)^12)*100 | BW12: =IF(AD12=1,0,(1-(1-1/(1+EXP(-Parameters!$B$2)))^12)*100) | BX12: =IF(AD12=1,0,BV12-(1-(1-(1/(1+EXP(-(BT12-BF12)))*Parameters!$B$3))^12)*100) | BY12: =IF(AD12=1,0,BV12-(1-(1-(1/(1+EXP(-(BT12-BG12)))*Parameters!$B$3))^12)*100) | BZ12: =IF(AD12=1,0,BV12-(1-(1-(1/(1+EXP(-(BT12-BH12)))*Parameters!$B$3))^12)*100) | CA12: =IF(AD12=1,0,BV12-(1-(1-(1/(1+EXP(-(BT12-BI12)))*Parameters!$B$3))^12)*100) | CB12: =IF(AD12=1,0,BV12-(1-(1-(1/(1+EXP(-(BT12-BJ12)))*Parameters!$B$3))^12)*100) | CC12: =IF(AD12=1,0,BV12-(1-(1-(1/(1+EXP(-(BT12-BK12)))*Parameters!$B$3))^12)*100) | CD12: =IF(AD12=1,0,BV12-(1-(1-(1/(1+EXP(-(BT12-BL12)))*Parameters!$B$3))^12)*100) | CE12: =IF(AD12=1,0,BV12-(1-(1-(1/(1+EXP(-(BT12-BM12)))*Parameters!$B$3))^12)*100) | CF12: =IF(AD12=1,0,BV12-(1-(1-(1/(1+EXP(-(BT12-BN12)))*Parameters!$B$3))^12)*100) | CG12: =IF(AD12=1,0,BV12-(1-(1-(1/(1+EXP(-(BT12-BO12)))*Parameters!$B$3))^12)*100) | CH12: =IF(AD12=1,0,BV12-(1-(1-(1/(1+EXP(-(BT12-BP12)))*Parameters!$B$3))^12)*100) | CI12: =IF(AD12=1,0,BV12-(1-(1-(1/(1+EXP(-(BT12-BQ12)))*Parameters!$B$3))^12)*100) | CJ12: =IF(AD12=1,0,BV12-(1-(1-(1/(1+EXP(-(BT12-BR12)))*Parameters!$B$3))^12)*100)
A13: GNR_2024_NEW | B13: 3618HNBE6 | C13: PN | D13: LUMENT REAL ESTATE CAPITAL,LLC | E13: 3618HNBE6_000000012122264 | F13: 202603 | G13: 5.85 | H13: 10076796 | I13: 420 | J13: 20250301 | K13: 20600401 | M13: 20350501 | N13: 10 | O13: 232/223(F) | T13: CA | U13: 44 | V13: 490.5 | W13: 12 | X13: 2025 | Y13: 3 | Z13: 10 | AA13: =IF(ISNUMBER(W13),W13,IFERROR(MAX(0,(VALUE(LEFT(F13,4))-VALUE(LEFT(TEXT(J13,"00000000"),4)))*12+(VALUE(MID(F13,5,2))-VALUE(MID(TEXT(J13,"00000000"),5,2)))),"")) | AB13: =IFERROR((VALUE(LEFT(TEXT(K13,"00000000"),4))-VALUE(LEFT(F13,4)))*12+(VALUE(MID(TEXT(K13,"00000000"),5,2))-VALUE(MID(F13,5,2))),"") | AC13: =IF(OR(L13="",NOT(ISNUMBER(L13))),0,MAX(0,MIN(60,(VALUE(LEFT(F13,4))-VALUE(LEFT(TEXT(L13,"00000000"),4)))*12+(VALUE(MID(F13,5,2))-VALUE(MID(TEXT(L13,"00000000"),5,2)))))) | AD13: =IF(OR(L13="",NOT(ISNUMBER(L13))),0,IF(VALUE(F13)<VALUE(LEFT(TEXT(L13,"00000000"),6)),1,0)) | AE13: =IF(OR(M13="",NOT(ISNUMBER(M13))),0,IF(VALUE(F13)<VALUE(LEFT(TEXT(M13,"00000000"),6)),1,0)) | AF13: =IF(AND(AD13=0,AE13=0),1,0) | AG13: =IF(ISNUMBER(X13),X13,IFERROR(VALUE(LEFT(TEXT(J13,"00000000"),4)),"")) | AH13: =IFERROR(XLOOKUP(AG13,Vintage_Rates!$A$2:$A$1000,Vintage_Rates!$B$2:$B$1000,""),"") | AI13: =IF(ISNUMBER(Y13),Y13,IFERROR((G13-AH13)*100,"")) | AJ13: =IF(ISNUMBER(V13),V13,IFERROR(XLOOKUP(VALUE(F13),PLC_Rates!$A$2:$A$1000,PLC_Rates!$B$2:$B$1000,""),"")) | AK13: =IF(ISNUMBER(Z13),Z13,IF(AE13=0,0,MAX(0,MIN(10,((VALUE(LEFT(TEXT(M13,"00000000"),4))-VALUE(LEFT(F13,4)))*12+(VALUE(MID(TEXT(M13,"00000000"),5,2))-VALUE(MID(F13,5,2))))/12)))) | AL13: =IFERROR(G13*100-AJ13,"") | AM13: =IFERROR(G13*100-(AJ13+(1+AK13)*12.5),"") | AN13: =IFERROR(MIN(H13/1000000,100),"") | AO13: =IFERROR(INDEX(FHA_Lookup!$B$2:$B$11,MATCH(TRUE,ISNUMBER(SEARCH(FHA_Lookup!$A$2:$A$11,UPPER(SUBSTITUTE(O13," ","")))),0)),"OTHER") | AP13: =IFERROR(INDEX(FHA_Lookup!$C$2:$C$11,MATCH(TRUE,ISNUMBER(SEARCH(FHA_Lookup!$A$2:$A$11,UPPER(SUBSTITUTE(O13," ","")))),0)),"OTHER") | AQ13: =IF(AP13="NC",1,0) | AR13: =IF(UPPER(TRIM(P13))="AFF",1,0) | AS13: =IF(UPPER(TRIM(P13))="BAF",1,0) | AT13: =IF(UPPER(TRIM(P13))="MKT",1,0) | AU13: =IF(AO13="221d4",1,0) | AV13: =IF(AO13="223a7",1,0) | AW13: =IF(AO13="232",1,0) | AX13: =IF(AO13="538",1,0) | AY13: =IF(AO13="241",1,0) | AZ13: =IF(AO13="220",1,0) | BA13: =IF(AO13="OTHER",1,0) | BB13: =IF(UPPER(TRIM(C13))="LM",1,0) | BC13: =IF(UPPER(TRIM(C13))="PN",1,0) | BD13: =IF(UPPER(TRIM(C13))="LS",1,0) | BE13: =IF(UPPER(TRIM(C13))="RX",1,0) | BF13: =IFERROR((Parameters!$C$6*AM13+Parameters!$C$7*MAX(AM13-(-150),0)+Parameters!$C$8*MAX(AM13-(-50),0)+Parameters!$C$9*MAX(AM13-(0),0)+Parameters!$C$10*MAX(AM13-(50),0)+Parameters!$C$11*MAX(AM13-(100),0)+Parameters!$C$12*MAX(AM13-(150),0)+Parameters!$C$13*MAX(AM13-(250),0)),0) | BG13: =IFERROR((Parameters!$C$14*AA13+Parameters!$C$15*MAX(AA13-(12),0)+Parameters!$C$16*MAX(AA13-(36),0)+Parameters!$C$17*MAX(AA13-(60),0)+Parameters!$C$18*MAX(AA13-(84),0)+Parameters!$C$19*MAX(AA13-(120),0)+Parameters!$C$20*MAX(AA13-(180),0)),0) | BH13: =IFERROR((Parameters!$C$21*AK13+Parameters!$C$22*MAX(AK13-(0),0)+Parameters!$C$23*MAX(AK13-(2),0)+Parameters!$C$24*MAX(AK13-(5),0)+Parameters!$C$25*MAX(AK13-(8),0)),0) | BI13: =IFERROR((Parameters!$C$26*AI13+Parameters!$C$27*MAX(AI13-(-100),0)+Parameters!$C$28*MAX(AI13-(-25),0)+Parameters!$C$29*MAX(AI13-(25),0)+Parameters!$C$30*MAX(AI13-(100),0)),0) | BJ13: =IFERROR((Parameters!$C$31*AN13+Parameters!$C$32*MAX(AN13-(2),0)+Parameters!$C$33*MAX(AN13-(10),0)+Parameters!$C$34*MAX(AN13-(25),0)),0) | BK13: =IFERROR((Parameters!$C$35*AB13+Parameters!$C$36*MAX(AB13-(12),0)+Parameters!$C$37*MAX(AB13-(24),0)+Parameters!$C$38*MAX(AB13-(60),0)),0) | BL13: =IFERROR((Parameters!$C$39*AC13+Parameters!$C$40*MAX(AC13-(6),0)+Parameters!$C$41*MAX(AC13-(12),0)+Parameters!$C$42*MAX(AC13-(24),0)),0) | BM13: =IFERROR(Parameters!$C$43*(MAX(AM13,0)*MIN(MAX(AK13,0),10))/100,0) | BN13: =Parameters!$C$44*AE13 | BO13: =Parameters!$C$45*AU13 + Parameters!$C$46*AV13 + Parameters!$C$47*AW13 + Parameters!$C$48*AX13 + Parameters!$C$49*AY13 + Parameters!$C$50*AZ13 + Parameters!$C$51*BA13 | BP13: =Parameters!$C$52*AQ13 | BQ13: =Parameters!$C$53*AR13+Parameters!$C$54*AS13+Parameters!$C$55*AT13 | BR13: =Parameters!$C$56*BB13+Parameters!$C$57*BC13+Parameters!$C$58*BD13+Parameters!$C$59*BE13 | BS13: =Parameters!$B$2 | BT13: =BS13+BF13 + BG13 + BH13 + BI13 + BJ13 + BK13 + BL13 + BM13 + BN13 + BO13 + BP13 + BQ13 + BR13 | BU13: =IF(AD13=1,0,1/(1+EXP(-BT13))*Parameters!$B$3) | BV13: =(1-(1-BU13)^12)*100 | BW13: =IF(AD13=1,0,(1-(1-1/(1+EXP(-Parameters!$B$2)))^12)*100) | BX13: =IF(AD13=1,0,BV13-(1-(1-(1/(1+EXP(-(BT13-BF13)))*Parameters!$B$3))^12)*100) | BY13: =IF(AD13=1,0,BV13-(1-(1-(1/(1+EXP(-(BT13-BG13)))*Parameters!$B$3))^12)*100) | BZ13: =IF(AD13=1,0,BV13-(1-(1-(1/(1+EXP(-(BT13-BH13)))*Parameters!$B$3))^12)*100) | CA13: =IF(AD13=1,0,BV13-(1-(1-(1/(1+EXP(-(BT13-BI13)))*Parameters!$B$3))^12)*100) | CB13: =IF(AD13=1,0,BV13-(1-(1-(1/(1+EXP(-(BT13-BJ13)))*Parameters!$B$3))^12)*100) | CC13: =IF(AD13=1,0,BV13-(1-(1-(1/(1+EXP(-(BT13-BK13)))*Parameters!$B$3))^12)*100) | CD13: =IF(AD13=1,0,BV13-(1-(1-(1/(1+EXP(-(BT13-BL13)))*Parameters!$B$3))^12)*100) | CE13: =IF(AD13=1,0,BV13-(1-(1-(1/(1+EXP(-(BT13-BM13)))*Parameters!$B$3))^12)*100) | CF13: =IF(AD13=1,0,BV13-(1-(1-(1/(1+EXP(-(BT13-BN13)))*Parameters!$B$3))^12)*100) | CG13: =IF(AD13=1,0,BV13-(1-(1-(1/(1+EXP(-(BT13-BO13)))*Parameters!$B$3))^12)*100) | CH13: =IF(AD13=1,0,BV13-(1-(1-(1/(1+EXP(-(BT13-BP13)))*Parameters!$B$3))^12)*100) | CI13: =IF(AD13=1,0,BV13-(1-(1-(1/(1+EXP(-(BT13-BQ13)))*Parameters!$B$3))^12)*100) | CJ13: =IF(AD13=1,0,BV13-(1-(1-(1/(1+EXP(-(BT13-BR13)))*Parameters!$B$3))^12)*100)
A14: GNR_2024_NEW | B14: 3618H6UH5 | C14: PN | D14: VIUM CAPITAL MORTGAGE, LLC. | E14: 3618H6UH5_000000007322340 | F14: 202603 | G14: 5.9 | H14: 9849441.7 | I14: 420 | J14: 20240724 | K14: 20590801 | M14: 20340901 | N14: 10 | O14: 232/223(F) | P14: MKT | T14: IN | U14: 44 | V14: 490.5 | W14: 20 | X14: 2024 | Y14: 12 | Z14: 9 | AA14: =IF(ISNUMBER(W14),W14,IFERROR(MAX(0,(VALUE(LEFT(F14,4))-VALUE(LEFT(TEXT(J14,"00000000"),4)))*12+(VALUE(MID(F14,5,2))-VALUE(MID(TEXT(J14,"00000000"),5,2)))),"")) | AB14: =IFERROR((VALUE(LEFT(TEXT(K14,"00000000"),4))-VALUE(LEFT(F14,4)))*12+(VALUE(MID(TEXT(K14,"00000000"),5,2))-VALUE(MID(F14,5,2))),"") | AC14: =IF(OR(L14="",NOT(ISNUMBER(L14))),0,MAX(0,MIN(60,(VALUE(LEFT(F14,4))-VALUE(LEFT(TEXT(L14,"00000000"),4)))*12+(VALUE(MID(F14,5,2))-VALUE(MID(TEXT(L14,"00000000"),5,2)))))) | AD14: =IF(OR(L14="",NOT(ISNUMBER(L14))),0,IF(VALUE(F14)<VALUE(LEFT(TEXT(L14,"00000000"),6)),1,0)) | AE14: =IF(OR(M14="",NOT(ISNUMBER(M14))),0,IF(VALUE(F14)<VALUE(LEFT(TEXT(M14,"00000000"),6)),1,0)) | AF14: =IF(AND(AD14=0,AE14=0),1,0) | AG14: =IF(ISNUMBER(X14),X14,IFERROR(VALUE(LEFT(TEXT(J14,"00000000"),4)),"")) | AH14: =IFERROR(XLOOKUP(AG14,Vintage_Rates!$A$2:$A$1000,Vintage_Rates!$B$2:$B$1000,""),"") | AI14: =IF(ISNUMBER(Y14),Y14,IFERROR((G14-AH14)*100,"")) | AJ14: =IF(ISNUMBER(V14),V14,IFERROR(XLOOKUP(VALUE(F14),PLC_Rates!$A$2:$A$1000,PLC_Rates!$B$2:$B$1000,""),"")) | AK14: =IF(ISNUMBER(Z14),Z14,IF(AE14=0,0,MAX(0,MIN(10,((VALUE(LEFT(TEXT(M14,"00000000"),4))-VALUE(LEFT(F14,4)))*12+(VALUE(MID(TEXT(M14,"00000000"),5,2))-VALUE(MID(F14,5,2))))/12)))) | AL14: =IFERROR(G14*100-AJ14,"") | AM14: =IFERROR(G14*100-(AJ14+(1+AK14)*12.5),"") | AN14: =IFERROR(MIN(H14/1000000,100),"") | AO14: =IFERROR(INDEX(FHA_Lookup!$B$2:$B$11,MATCH(TRUE,ISNUMBER(SEARCH(FHA_Lookup!$A$2:$A$11,UPPER(SUBSTITUTE(O14," ","")))),0)),"OTHER") | AP14: =IFERROR(INDEX(FHA_Lookup!$C$2:$C$11,MATCH(TRUE,ISNUMBER(SEARCH(FHA_Lookup!$A$2:$A$11,UPPER(SUBSTITUTE(O14," ","")))),0)),"OTHER") | AQ14: =IF(AP14="NC",1,0) | AR14: =IF(UPPER(TRIM(P14))="AFF",1,0) | AS14: =IF(UPPER(TRIM(P14))="BAF",1,0) | AT14: =IF(UPPER(TRIM(P14))="MKT",1,0) | AU14: =IF(AO14="221d4",1,0) | AV14: =IF(AO14="223a7",1,0) | AW14: =IF(AO14="232",1,0) | AX14: =IF(AO14="538",1,0) | AY14: =IF(AO14="241",1,0) | AZ14: =IF(AO14="220",1,0) | BA14: =IF(AO14="OTHER",1,0) | BB14: =IF(UPPER(TRIM(C14))="LM",1,0) | BC14: =IF(UPPER(TRIM(C14))="PN",1,0) | BD14: =IF(UPPER(TRIM(C14))="LS",1,0) | BE14: =IF(UPPER(TRIM(C14))="RX",1,0) | BF14: =IFERROR((Parameters!$C$6*AM14+Parameters!$C$7*MAX(AM14-(-150),0)+Parameters!$C$8*MAX(AM14-(-50),0)+Parameters!$C$9*MAX(AM14-(0),0)+Parameters!$C$10*MAX(AM14-(50),0)+Parameters!$C$11*MAX(AM14-(100),0)+Parameters!$C$12*MAX(AM14-(150),0)+Parameters!$C$13*MAX(AM14-(250),0)),0) | BG14: =IFERROR((Parameters!$C$14*AA14+Parameters!$C$15*MAX(AA14-(12),0)+Parameters!$C$16*MAX(AA14-(36),0)+Parameters!$C$17*MAX(AA14-(60),0)+Parameters!$C$18*MAX(AA14-(84),0)+Parameters!$C$19*MAX(AA14-(120),0)+Parameters!$C$20*MAX(AA14-(180),0)),0) | BH14: =IFERROR((Parameters!$C$21*AK14+Parameters!$C$22*MAX(AK14-(0),0)+Parameters!$C$23*MAX(AK14-(2),0)+Parameters!$C$24*MAX(AK14-(5),0)+Parameters!$C$25*MAX(AK14-(8),0)),0) | BI14: =IFERROR((Parameters!$C$26*AI14+Parameters!$C$27*MAX(AI14-(-100),0)+Parameters!$C$28*MAX(AI14-(-25),0)+Parameters!$C$29*MAX(AI14-(25),0)+Parameters!$C$30*MAX(AI14-(100),0)),0) | BJ14: =IFERROR((Parameters!$C$31*AN14+Parameters!$C$32*MAX(AN14-(2),0)+Parameters!$C$33*MAX(AN14-(10),0)+Parameters!$C$34*MAX(AN14-(25),0)),0) | BK14: =IFERROR((Parameters!$C$35*AB14+Parameters!$C$36*MAX(AB14-(12),0)+Parameters!$C$37*MAX(AB14-(24),0)+Parameters!$C$38*MAX(AB14-(60),0)),0) | BL14: =IFERROR((Parameters!$C$39*AC14+Parameters!$C$40*MAX(AC14-(6),0)+Parameters!$C$41*MAX(AC14-(12),0)+Parameters!$C$42*MAX(AC14-(24),0)),0) | BM14: =IFERROR(Parameters!$C$43*(MAX(AM14,0)*MIN(MAX(AK14,0),10))/100,0) | BN14: =Parameters!$C$44*AE14 | BO14: =Parameters!$C$45*AU14 + Parameters!$C$46*AV14 + Parameters!$C$47*AW14 + Parameters!$C$48*AX14 + Parameters!$C$49*AY14 + Parameters!$C$50*AZ14 + Parameters!$C$51*BA14 | BP14: =Parameters!$C$52*AQ14 | BQ14: =Parameters!$C$53*AR14+Parameters!$C$54*AS14+Parameters!$C$55*AT14 | BR14: =Parameters!$C$56*BB14+Parameters!$C$57*BC14+Parameters!$C$58*BD14+Parameters!$C$59*BE14 | BS14: =Parameters!$B$2 | BT14: =BS14+BF14 + BG14 + BH14 + BI14 + BJ14 + BK14 + BL14 + BM14 + BN14 + BO14 + BP14 + BQ14 + BR14 | BU14: =IF(AD14=1,0,1/(1+EXP(-BT14))*Parameters!$B$3) | BV14: =(1-(1-BU14)^12)*100 | BW14: =IF(AD14=1,0,(1-(1-1/(1+EXP(-Parameters!$B$2)))^12)*100) | BX14: =IF(AD14=1,0,BV14-(1-(1-(1/(1+EXP(-(BT14-BF14)))*Parameters!$B$3))^12)*100) | BY14: =IF(AD14=1,0,BV14-(1-(1-(1/(1+EXP(-(BT14-BG14)))*Parameters!$B$3))^12)*100) | BZ14: =IF(AD14=1,0,BV14-(1-(1-(1/(1+EXP(-(BT14-BH14)))*Parameters!$B$3))^12)*100) | CA14: =IF(AD14=1,0,BV14-(1-(1-(1/(1+EXP(-(BT14-BI14)))*Parameters!$B$3))^12)*100) | CB14: =IF(AD14=1,0,BV14-(1-(1-(1/(1+EXP(-(BT14-BJ14)))*Parameters!$B$3))^12)*100) | CC14: =IF(AD14=1,0,BV14-(1-(1-(1/(1+EXP(-(BT14-BK14)))*Parameters!$B$3))^12)*100) | CD14: =IF(AD14=1,0,BV14-(1-(1-(1/(1+EXP(-(BT14-BL14)))*Parameters!$B$3))^12)*100) | CE14: =IF(AD14=1,0,BV14-(1-(1-(1/(1+EXP(-(BT14-BM14)))*Parameters!$B$3))^12)*100) | CF14: =IF(AD14=1,0,BV14-(1-(1-(1/(1+EXP(-(BT14-BN14)))*Parameters!$B$3))^12)*100) | CG14: =IF(AD14=1,0,BV14-(1-(1-(1/(1+EXP(-(BT14-BO14)))*Parameters!$B$3))^12)*100) | CH14: =IF(AD14=1,0,BV14-(1-(1-(1/(1+EXP(-(BT14-BP14)))*Parameters!$B$3))^12)*100) | CI14: =IF(AD14=1,0,BV14-(1-(1-(1/(1+EXP(-(BT14-BQ14)))*Parameters!$B$3))^12)*100) | CJ14: =IF(AD14=1,0,BV14-(1-(1-(1/(1+EXP(-(BT14-BR14)))*Parameters!$B$3))^12)*100)
A15: GNR_2024_NEW | B15: 3618BCU88 | C15: PN | D15: BELLWETHER ENTERPRISE REAL ESTATE CAPITA | E15: 3618BCU88_000000005135861 | F15: 202603 | G15: 5.25 | H15: 13809145 | I15: 480 | J15: 20230601 | K15: 20641001 | M15: 20341031 | N15: 10 | O15: 221(D)(4) | P15: BAF | T15: VA | U15: 120 | V15: 490.5 | W15: 33 | X15: 2023 | Y15: -33.5 | Z15: 10 | AA15: =IF(ISNUMBER(W15),W15,IFERROR(MAX(0,(VALUE(LEFT(F15,4))-VALUE(LEFT(TEXT(J15,"00000000"),4)))*12+(VALUE(MID(F15,5,2))-VALUE(MID(TEXT(J15,"00000000"),5,2)))),"")) | AB15: =IFERROR((VALUE(LEFT(TEXT(K15,"00000000"),4))-VALUE(LEFT(F15,4)))*12+(VALUE(MID(TEXT(K15,"00000000"),5,2))-VALUE(MID(F15,5,2))),"") | AC15: =IF(OR(L15="",NOT(ISNUMBER(L15))),0,MAX(0,MIN(60,(VALUE(LEFT(F15,4))-VALUE(LEFT(TEXT(L15,"00000000"),4)))*12+(VALUE(MID(F15,5,2))-VALUE(MID(TEXT(L15,"00000000"),5,2)))))) | AD15: =IF(OR(L15="",NOT(ISNUMBER(L15))),0,IF(VALUE(F15)<VALUE(LEFT(TEXT(L15,"00000000"),6)),1,0)) | AE15: =IF(OR(M15="",NOT(ISNUMBER(M15))),0,IF(VALUE(F15)<VALUE(LEFT(TEXT(M15,"00000000"),6)),1,0)) | AF15: =IF(AND(AD15=0,AE15=0),1,0) | AG15: =IF(ISNUMBER(X15),X15,IFERROR(VALUE(LEFT(TEXT(J15,"00000000"),4)),"")) | AH15: =IFERROR(XLOOKUP(AG15,Vintage_Rates!$A$2:$A$1000,Vintage_Rates!$B$2:$B$1000,""),"") | AI15: =IF(ISNUMBER(Y15),Y15,IFERROR((G15-AH15)*100,"")) | AJ15: =IF(ISNUMBER(V15),V15,IFERROR(XLOOKUP(VALUE(F15),PLC_Rates!$A$2:$A$1000,PLC_Rates!$B$2:$B$1000,""),"")) | AK15: =IF(ISNUMBER(Z15),Z15,IF(AE15=0,0,MAX(0,MIN(10,((VALUE(LEFT(TEXT(M15,"00000000"),4))-VALUE(LEFT(F15,4)))*12+(VALUE(MID(TEXT(M15,"00000000"),5,2))-VALUE(MID(F15,5,2))))/12)))) | AL15: =IFERROR(G15*100-AJ15,"") | AM15: =IFERROR(G15*100-(AJ15+(1+AK15)*12.5),"") | AN15: =IFERROR(MIN(H15/1000000,100),"") | AO15: =IFERROR(INDEX(FHA_Lookup!$B$2:$B$11,MATCH(TRUE,ISNUMBER(SEARCH(FHA_Lookup!$A$2:$A$11,UPPER(SUBSTITUTE(O15," ","")))),0)),"OTHER") | AP15: =IFERROR(INDEX(FHA_Lookup!$C$2:$C$11,MATCH(TRUE,ISNUMBER(SEARCH(FHA_Lookup!$A$2:$A$11,UPPER(SUBSTITUTE(O15," ","")))),0)),"OTHER") | AQ15: =IF(AP15="NC",1,0) | AR15: =IF(UPPER(TRIM(P15))="AFF",1,0) | AS15: =IF(UPPER(TRIM(P15))="BAF",1,0) | AT15: =IF(UPPER(TRIM(P15))="MKT",1,0) | AU15: =IF(AO15="221d4",1,0) | AV15: =IF(AO15="223a7",1,0) | AW15: =IF(AO15="232",1,0) | AX15: =IF(AO15="538",1,0) | AY15: =IF(AO15="241",1,0) | AZ15: =IF(AO15="220",1,0) | BA15: =IF(AO15="OTHER",1,0) | BB15: =IF(UPPER(TRIM(C15))="LM",1,0) | BC15: =IF(UPPER(TRIM(C15))="PN",1,0) | BD15: =IF(UPPER(TRIM(C15))="LS",1,0) | BE15: =IF(UPPER(TRIM(C15))="RX",1,0) | BF15: =IFERROR((Parameters!$C$6*AM15+Parameters!$C$7*MAX(AM15-(-150),0)+Parameters!$C$8*MAX(AM15-(-50),0)+Parameters!$C$9*MAX(AM15-(0),0)+Parameters!$C$10*MAX(AM15-(50),0)+Parameters!$C$11*MAX(AM15-(100),0)+Parameters!$C$12*MAX(AM15-(150),0)+Parameters!$C$13*MAX(AM15-(250),0)),0) | BG15: =IFERROR((Parameters!$C$14*AA15+Parameters!$C$15*MAX(AA15-(12),0)+Parameters!$C$16*MAX(AA15-(36),0)+Parameters!$C$17*MAX(AA15-(60),0)+Parameters!$C$18*MAX(AA15-(84),0)+Parameters!$C$19*MAX(AA15-(120),0)+Parameters!$C$20*MAX(AA15-(180),0)),0) | BH15: =IFERROR((Parameters!$C$21*AK15+Parameters!$C$22*MAX(AK15-(0),0)+Parameters!$C$23*MAX(AK15-(2),0)+Parameters!$C$24*MAX(AK15-(5),0)+Parameters!$C$25*MAX(AK15-(8),0)),0) | BI15: =IFERROR((Parameters!$C$26*AI15+Parameters!$C$27*MAX(AI15-(-100),0)+Parameters!$C$28*MAX(AI15-(-25),0)+Parameters!$C$29*MAX(AI15-(25),0)+Parameters!$C$30*MAX(AI15-(100),0)),0) | BJ15: =IFERROR((Parameters!$C$31*AN15+Parameters!$C$32*MAX(AN15-(2),0)+Parameters!$C$33*MAX(AN15-(10),0)+Parameters!$C$34*MAX(AN15-(25),0)),0) | BK15: =IFERROR((Parameters!$C$35*AB15+Parameters!$C$36*MAX(AB15-(12),0)+Parameters!$C$37*MAX(AB15-(24),0)+Parameters!$C$38*MAX(AB15-(60),0)),0) | BL15: =IFERROR((Parameters!$C$39*AC15+Parameters!$C$40*MAX(AC15-(6),0)+Parameters!$C$41*MAX(AC15-(12),0)+Parameters!$C$42*MAX(AC15-(24),0)),0) | BM15: =IFERROR(Parameters!$C$43*(MAX(AM15,0)*MIN(MAX(AK15,0),10))/100,0) | BN15: =Parameters!$C$44*AE15 | BO15: =Parameters!$C$45*AU15 + Parameters!$C$46*AV15 + Parameters!$C$47*AW15 + Parameters!$C$48*AX15 + Parameters!$C$49*AY15 + Parameters!$C$50*AZ15 + Parameters!$C$51*BA15 | BP15: =Parameters!$C$52*AQ15 | BQ15: =Parameters!$C$53*AR15+Parameters!$C$54*AS15+Parameters!$C$55*AT15 | BR15: =Parameters!$C$56*BB15+Parameters!$C$57*BC15+Parameters!$C$58*BD15+Parameters!$C$59*BE15 | BS15: =Parameters!$B$2 | BT15: =BS15+BF15 + BG15 + BH15 + BI15 + BJ15 + BK15 + BL15 + BM15 + BN15 + BO15 + BP15 + BQ15 + BR15 | BU15: =IF(AD15=1,0,1/(1+EXP(-BT15))*Parameters!$B$3) | BV15: =(1-(1-BU15)^12)*100 | BW15: =IF(AD15=1,0,(1-(1-1/(1+EXP(-Parameters!$B$2)))^12)*100) | BX15: =IF(AD15=1,0,BV15-(1-(1-(1/(1+EXP(-(BT15-BF15)))*Parameters!$B$3))^12)*100) | BY15: =IF(AD15=1,0,BV15-(1-(1-(1/(1+EXP(-(BT15-BG15)))*Parameters!$B$3))^12)*100) | BZ15: =IF(AD15=1,0,BV15-(1-(1-(1/(1+EXP(-(BT15-BH15)))*Parameters!$B$3))^12)*100) | CA15: =IF(AD15=1,0,BV15-(1-(1-(1/(1+EXP(-(BT15-BI15)))*Parameters!$B$3))^12)*100) | CB15: =IF(AD15=1,0,BV15-(1-(1-(1/(1+EXP(-(BT15-BJ15)))*Parameters!$B$3))^12)*100) | CC15: =IF(AD15=1,0,BV15-(1-(1-(1/(1+EXP(-(BT15-BK15)))*Parameters!$B$3))^12)*100) | CD15: =IF(AD15=1,0,BV15-(1-(1-(1/(1+EXP(-(BT15-BL15)))*Parameters!$B$3))^12)*100) | CE15: =IF(AD15=1,0,BV15-(1-(1-(1/(1+EXP(-(BT15-BM15)))*Parameters!$B$3))^12)*100) | CF15: =IF(AD15=1,0,BV15-(1-(1-(1/(1+EXP(-(BT15-BN15)))*Parameters!$B$3))^12)*100) | CG15: =IF(AD15=1,0,BV15-(1-(1-(1/(1+EXP(-(BT15-BO15)))*Parameters!$B$3))^12)*100) | CH15: =IF(AD15=1,0,BV15-(1-(1-(1/(1+EXP(-(BT15-BP15)))*Parameters!$B$3))^12)*100) | CI15: =IF(AD15=1,0,BV15-(1-(1-(1/(1+EXP(-(BT15-BQ15)))*Parameters!$B$3))^12)*100) | CJ15: =IF(AD15=1,0,BV15-(1-(1-(1/(1+EXP(-(BT15-BR15)))*Parameters!$B$3))^12)*100)
A16: GNR_2024_NEW | B16: 3618HXGV1 | C16: PN | D16: WALKER & DUNLOP, LLC | E16: 3618HXGV1_000000002311760 | F16: 202603 | G16: 5.38 | H16: 14025078 | I16: 420 | J16: 20250529 | K16: 20600601 | M16: 20350701 | N16: 10 | O16: 207/223(F) | R16: P | T16: MA | U16: 64 | V16: 490.5 | W16: 10 | X16: 2025 | Y16: -44 | Z16: 10 | AA16: =IF(ISNUMBER(W16),W16,IFERROR(MAX(0,(VALUE(LEFT(F16,4))-VALUE(LEFT(TEXT(J16,"00000000"),4)))*12+(VALUE(MID(F16,5,2))-VALUE(MID(TEXT(J16,"00000000"),5,2)))),"")) | AB16: =IFERROR((VALUE(LEFT(TEXT(K16,"00000000"),4))-VALUE(LEFT(F16,4)))*12+(VALUE(MID(TEXT(K16,"00000000"),5,2))-VALUE(MID(F16,5,2))),"") | AC16: =IF(OR(L16="",NOT(ISNUMBER(L16))),0,MAX(0,MIN(60,(VALUE(LEFT(F16,4))-VALUE(LEFT(TEXT(L16,"00000000"),4)))*12+(VALUE(MID(F16,5,2))-VALUE(MID(TEXT(L16,"00000000"),5,2)))))) | AD16: =IF(OR(L16="",NOT(ISNUMBER(L16))),0,IF(VALUE(F16)<VALUE(LEFT(TEXT(L16,"00000000"),6)),1,0)) | AE16: =IF(OR(M16="",NOT(ISNUMBER(M16))),0,IF(VALUE(F16)<VALUE(LEFT(TEXT(M16,"00000000"),6)),1,0)) | AF16: =IF(AND(AD16=0,AE16=0),1,0) | AG16: =IF(ISNUMBER(X16),X16,IFERROR(VALUE(LEFT(TEXT(J16,"00000000"),4)),"")) | AH16: =IFERROR(XLOOKUP(AG16,Vintage_Rates!$A$2:$A$1000,Vintage_Rates!$B$2:$B$1000,""),"") | AI16: =IF(ISNUMBER(Y16),Y16,IFERROR((G16-AH16)*100,"")) | AJ16: =IF(ISNUMBER(V16),V16,IFERROR(XLOOKUP(VALUE(F16),PLC_Rates!$A$2:$A$1000,PLC_Rates!$B$2:$B$1000,""),"")) | AK16: =IF(ISNUMBER(Z16),Z16,IF(AE16=0,0,MAX(0,MIN(10,((VALUE(LEFT(TEXT(M16,"00000000"),4))-VALUE(LEFT(F16,4)))*12+(VALUE(MID(TEXT(M16,"00000000"),5,2))-VALUE(MID(F16,5,2))))/12)))) | AL16: =IFERROR(G16*100-AJ16,"") | AM16: =IFERROR(G16*100-(AJ16+(1+AK16)*12.5),"") | AN16: =IFERROR(MIN(H16/1000000,100),"") | AO16: =IFERROR(INDEX(FHA_Lookup!$B$2:$B$11,MATCH(TRUE,ISNUMBER(SEARCH(FHA_Lookup!$A$2:$A$11,UPPER(SUBSTITUTE(O16," ","")))),0)),"OTHER") | AP16: =IFERROR(INDEX(FHA_Lookup!$C$2:$C$11,MATCH(TRUE,ISNUMBER(SEARCH(FHA_Lookup!$A$2:$A$11,UPPER(SUBSTITUTE(O16," ","")))),0)),"OTHER") | AQ16: =IF(AP16="NC",1,0) | AR16: =IF(UPPER(TRIM(P16))="AFF",1,0) | AS16: =IF(UPPER(TRIM(P16))="BAF",1,0) | AT16: =IF(UPPER(TRIM(P16))="MKT",1,0) | AU16: =IF(AO16="221d4",1,0) | AV16: =IF(AO16="223a7",1,0) | AW16: =IF(AO16="232",1,0) | AX16: =IF(AO16="538",1,0) | AY16: =IF(AO16="241",1,0) | AZ16: =IF(AO16="220",1,0) | BA16: =IF(AO16="OTHER",1,0) | BB16: =IF(UPPER(TRIM(C16))="LM",1,0) | BC16: =IF(UPPER(TRIM(C16))="PN",1,0) | BD16: =IF(UPPER(TRIM(C16))="LS",1,0) | BE16: =IF(UPPER(TRIM(C16))="RX",1,0) | BF16: =IFERROR((Parameters!$C$6*AM16+Parameters!$C$7*MAX(AM16-(-150),0)+Parameters!$C$8*MAX(AM16-(-50),0)+Parameters!$C$9*MAX(AM16-(0),0)+Parameters!$C$10*MAX(AM16-(50),0)+Parameters!$C$11*MAX(AM16-(100),0)+Parameters!$C$12*MAX(AM16-(150),0)+Parameters!$C$13*MAX(AM16-(250),0)),0) | BG16: =IFERROR((Parameters!$C$14*AA16+Parameters!$C$15*MAX(AA16-(12),0)+Parameters!$C$16*MAX(AA16-(36),0)+Parameters!$C$17*MAX(AA16-(60),0)+Parameters!$C$18*MAX(AA16-(84),0)+Parameters!$C$19*MAX(AA16-(120),0)+Parameters!$C$20*MAX(AA16-(180),0)),0) | BH16: =IFERROR((Parameters!$C$21*AK16+Parameters!$C$22*MAX(AK16-(0),0)+Parameters!$C$23*MAX(AK16-(2),0)+Parameters!$C$24*MAX(AK16-(5),0)+Parameters!$C$25*MAX(AK16-(8),0)),0) | BI16: =IFERROR((Parameters!$C$26*AI16+Parameters!$C$27*MAX(AI16-(-100),0)+Parameters!$C$28*MAX(AI16-(-25),0)+Parameters!$C$29*MAX(AI16-(25),0)+Parameters!$C$30*MAX(AI16-(100),0)),0) | BJ16: =IFERROR((Parameters!$C$31*AN16+Parameters!$C$32*MAX(AN16-(2),0)+Parameters!$C$33*MAX(AN16-(10),0)+Parameters!$C$34*MAX(AN16-(25),0)),0) | BK16: =IFERROR((Parameters!$C$35*AB16+Parameters!$C$36*MAX(AB16-(12),0)+Parameters!$C$37*MAX(AB16-(24),0)+Parameters!$C$38*MAX(AB16-(60),0)),0) | BL16: =IFERROR((Parameters!$C$39*AC16+Parameters!$C$40*MAX(AC16-(6),0)+Parameters!$C$41*MAX(AC16-(12),0)+Parameters!$C$42*MAX(AC16-(24),0)),0) | BM16: =IFERROR(Parameters!$C$43*(MAX(AM16,0)*MIN(MAX(AK16,0),10))/100,0) | BN16: =Parameters!$C$44*AE16 | BO16: =Parameters!$C$45*AU16 + Parameters!$C$46*AV16 + Parameters!$C$47*AW16 + Parameters!$C$48*AX16 + Parameters!$C$49*AY16 + Parameters!$C$50*AZ16 + Parameters!$C$51*BA16 | BP16: =Parameters!$C$52*AQ16 | BQ16: =Parameters!$C$53*AR16+Parameters!$C$54*AS16+Parameters!$C$55*AT16 | BR16: =Parameters!$C$56*BB16+Parameters!$C$57*BC16+Parameters!$C$58*BD16+Parameters!$C$59*BE16 | BS16: =Parameters!$B$2 | BT16: =BS16+BF16 + BG16 + BH16 + BI16 + BJ16 + BK16 + BL16 + BM16 + BN16 + BO16 + BP16 + BQ16 + BR16 | BU16: =IF(AD16=1,0,1/(1+EXP(-BT16))*Parameters!$B$3) | BV16: =(1-(1-BU16)^12)*100 | BW16: =IF(AD16=1,0,(1-(1-1/(1+EXP(-Parameters!$B$2)))^12)*100) | BX16: =IF(AD16=1,0,BV16-(1-(1-(1/(1+EXP(-(BT16-BF16)))*Parameters!$B$3))^12)*100) | BY16: =IF(AD16=1,0,BV16-(1-(1-(1/(1+EXP(-(BT16-BG16)))*Parameters!$B$3))^12)*100) | BZ16: =IF(AD16=1,0,BV16-(1-(1-(1/(1+EXP(-(BT16-BH16)))*Parameters!$B$3))^12)*100) | CA16: =IF(AD16=1,0,BV16-(1-(1-(1/(1+EXP(-(BT16-BI16)))*Parameters!$B$3))^12)*100) | CB16: =IF(AD16=1,0,BV16-(1-(1-(1/(1+EXP(-(BT16-BJ16)))*Parameters!$B$3))^12)*100) | CC16: =IF(AD16=1,0,BV16-(1-(1-(1/(1+EXP(-(BT16-BK16)))*Parameters!$B$3))^12)*100) | CD16: =IF(AD16=1,0,BV16-(1-(1-(1/(1+EXP(-(BT16-BL16)))*Parameters!$B$3))^12)*100) | CE16: =IF(AD16=1,0,BV16-(1-(1-(1/(1+EXP(-(BT16-BM16)))*Parameters!$B$3))^12)*100) | CF16: =IF(AD16=1,0,BV16-(1-(1-(1/(1+EXP(-(BT16-BN16)))*Parameters!$B$3))^12)*100) | CG16: =IF(AD16=1,0,BV16-(1-(1-(1/(1+EXP(-(BT16-BO16)))*Parameters!$B$3))^12)*100) | CH16: =IF(AD16=1,0,BV16-(1-(1-(1/(1+EXP(-(BT16-BP16)))*Parameters!$B$3))^12)*100) | CI16: =IF(AD16=1,0,BV16-(1-(1-(1/(1+EXP(-(BT16-BQ16)))*Parameters!$B$3))^12)*100) | CJ16: =IF(AD16=1,0,BV16-(1-(1-(1/(1+EXP(-(BT16-BR16)))*Parameters!$B$3))^12)*100)
A17: GNR_2024_NEW | B17: 3618JBFJ5 | C17: PN | D17: GREYSTONE FUNDING COMPANY LLC | E17: 3618JBFJ5_000000005111548 | F17: 202603 | G17: 5.61 | H17: 48002322 | I17: 420 | J17: 20250101 | K17: 20600201 | M17: 20350301 | N17: 10 | O17: 207/223(F) | T17: VA | U17: 312 | V17: 490.5 | W17: 14 | X17: 2025 | Y17: -21 | Z17: 9 | AA17: =IF(ISNUMBER(W17),W17,IFERROR(MAX(0,(VALUE(LEFT(F17,4))-VALUE(LEFT(TEXT(J17,"00000000"),4)))*12+(VALUE(MID(F17,5,2))-VALUE(MID(TEXT(J17,"00000000"),5,2)))),"")) | AB17: =IFERROR((VALUE(LEFT(TEXT(K17,"00000000"),4))-VALUE(LEFT(F17,4)))*12+(VALUE(MID(TEXT(K17,"00000000"),5,2))-VALUE(MID(F17,5,2))),"") | AC17: =IF(OR(L17="",NOT(ISNUMBER(L17))),0,MAX(0,MIN(60,(VALUE(LEFT(F17,4))-VALUE(LEFT(TEXT(L17,"00000000"),4)))*12+(VALUE(MID(F17,5,2))-VALUE(MID(TEXT(L17,"00000000"),5,2)))))) | AD17: =IF(OR(L17="",NOT(ISNUMBER(L17))),0,IF(VALUE(F17)<VALUE(LEFT(TEXT(L17,"00000000"),6)),1,0)) | AE17: =IF(OR(M17="",NOT(ISNUMBER(M17))),0,IF(VALUE(F17)<VALUE(LEFT(TEXT(M17,"00000000"),6)),1,0)) | AF17: =IF(AND(AD17=0,AE17=0),1,0) | AG17: =IF(ISNUMBER(X17),X17,IFERROR(VALUE(LEFT(TEXT(J17,"00000000"),4)),"")) | AH17: =IFERROR(XLOOKUP(AG17,Vintage_Rates!$A$2:$A$1000,Vintage_Rates!$B$2:$B$1000,""),"") | AI17: =IF(ISNUMBER(Y17),Y17,IFERROR((G17-AH17)*100,"")) | AJ17: =IF(ISNUMBER(V17),V17,IFERROR(XLOOKUP(VALUE(F17),PLC_Rates!$A$2:$A$1000,PLC_Rates!$B$2:$B$1000,""),"")) | AK17: =IF(ISNUMBER(Z17),Z17,IF(AE17=0,0,MAX(0,MIN(10,((VALUE(LEFT(TEXT(M17,"00000000"),4))-VALUE(LEFT(F17,4)))*12+(VALUE(MID(TEXT(M17,"00000000"),5,2))-VALUE(MID(F17,5,2))))/12)))) | AL17: =IFERROR(G17*100-AJ17,"") | AM17: =IFERROR(G17*100-(AJ17+(1+AK17)*12.5),"") | AN17: =IFERROR(MIN(H17/1000000,100),"") | AO17: =IFERROR(INDEX(FHA_Lookup!$B$2:$B$11,MATCH(TRUE,ISNUMBER(SEARCH(FHA_Lookup!$A$2:$A$11,UPPER(SUBSTITUTE(O17," ","")))),0)),"OTHER") | AP17: =IFERROR(INDEX(FHA_Lookup!$C$2:$C$11,MATCH(TRUE,ISNUMBER(SEARCH(FHA_Lookup!$A$2:$A$11,UPPER(SUBSTITUTE(O17," ","")))),0)),"OTHER") | AQ17: =IF(AP17="NC",1,0) | AR17: =IF(UPPER(TRIM(P17))="AFF",1,0) | AS17: =IF(UPPER(TRIM(P17))="BAF",1,0) | AT17: =IF(UPPER(TRIM(P17))="MKT",1,0) | AU17: =IF(AO17="221d4",1,0) | AV17: =IF(AO17="223a7",1,0) | AW17: =IF(AO17="232",1,0) | AX17: =IF(AO17="538",1,0) | AY17: =IF(AO17="241",1,0) | AZ17: =IF(AO17="220",1,0) | BA17: =IF(AO17="OTHER",1,0) | BB17: =IF(UPPER(TRIM(C17))="LM",1,0) | BC17: =IF(UPPER(TRIM(C17))="PN",1,0) | BD17: =IF(UPPER(TRIM(C17))="LS",1,0) | BE17: =IF(UPPER(TRIM(C17))="RX",1,0) | BF17: =IFERROR((Parameters!$C$6*AM17+Parameters!$C$7*MAX(AM17-(-150),0)+Parameters!$C$8*MAX(AM17-(-50),0)+Parameters!$C$9*MAX(AM17-(0),0)+Parameters!$C$10*MAX(AM17-(50),0)+Parameters!$C$11*MAX(AM17-(100),0)+Parameters!$C$12*MAX(AM17-(150),0)+Parameters!$C$13*MAX(AM17-(250),0)),0) | BG17: =IFERROR((Parameters!$C$14*AA17+Parameters!$C$15*MAX(AA17-(12),0)+Parameters!$C$16*MAX(AA17-(36),0)+Parameters!$C$17*MAX(AA17-(60),0)+Parameters!$C$18*MAX(AA17-(84),0)+Parameters!$C$19*MAX(AA17-(120),0)+Parameters!$C$20*MAX(AA17-(180),0)),0) | BH17: =IFERROR((Parameters!$C$21*AK17+Parameters!$C$22*MAX(AK17-(0),0)+Parameters!$C$23*MAX(AK17-(2),0)+Parameters!$C$24*MAX(AK17-(5),0)+Parameters!$C$25*MAX(AK17-(8),0)),0) | BI17: =IFERROR((Parameters!$C$26*AI17+Parameters!$C$27*MAX(AI17-(-100),0)+Parameters!$C$28*MAX(AI17-(-25),0)+Parameters!$C$29*MAX(AI17-(25),0)+Parameters!$C$30*MAX(AI17-(100),0)),0) | BJ17: =IFERROR((Parameters!$C$31*AN17+Parameters!$C$32*MAX(AN17-(2),0)+Parameters!$C$33*MAX(AN17-(10),0)+Parameters!$C$34*MAX(AN17-(25),0)),0) | BK17: =IFERROR((Parameters!$C$35*AB17+Parameters!$C$36*MAX(AB17-(12),0)+Parameters!$C$37*MAX(AB17-(24),0)+Parameters!$C$38*MAX(AB17-(60),0)),0) | BL17: =IFERROR((Parameters!$C$39*AC17+Parameters!$C$40*MAX(AC17-(6),0)+Parameters!$C$41*MAX(AC17-(12),0)+Parameters!$C$42*MAX(AC17-(24),0)),0) | BM17: =IFERROR(Parameters!$C$43*(MAX(AM17,0)*MIN(MAX(AK17,0),10))/100,0) | BN17: =Parameters!$C$44*AE17 | BO17: =Parameters!$C$45*AU17 + Parameters!$C$46*AV17 + Parameters!$C$47*AW17 + Parameters!$C$48*AX17 + Parameters!$C$49*AY17 + Parameters!$C$50*AZ17 + Parameters!$C$51*BA17 | BP17: =Parameters!$C$52*AQ17 | BQ17: =Parameters!$C$53*AR17+Parameters!$C$54*AS17+Parameters!$C$55*AT17 | BR17: =Parameters!$C$56*BB17+Parameters!$C$57*BC17+Parameters!$C$58*BD17+Parameters!$C$59*BE17 | BS17: =Parameters!$B$2 | BT17: =BS17+BF17 + BG17 + BH17 + BI17 + BJ17 + BK17 + BL17 + BM17 + BN17 + BO17 + BP17 + BQ17 + BR17 | BU17: =IF(AD17=1,0,1/(1+EXP(-BT17))*Parameters!$B$3) | BV17: =(1-(1-BU17)^12)*100 | BW17: =IF(AD17=1,0,(1-(1-1/(1+EXP(-Parameters!$B$2)))^12)*100) | BX17: =IF(AD17=1,0,BV17-(1-(1-(1/(1+EXP(-(BT17-BF17)))*Parameters!$B$3))^12)*100) | BY17: =IF(AD17=1,0,BV17-(1-(1-(1/(1+EXP(-(BT17-BG17)))*Parameters!$B$3))^12)*100) | BZ17: =IF(AD17=1,0,BV17-(1-(1-(1/(1+EXP(-(BT17-BH17)))*Parameters!$B$3))^12)*100) | CA17: =IF(AD17=1,0,BV17-(1-(1-(1/(1+EXP(-(BT17-BI17)))*Parameters!$B$3))^12)*100) | CB17: =IF(AD17=1,0,BV17-(1-(1-(1/(1+EXP(-(BT17-BJ17)))*Parameters!$B$3))^12)*100) | CC17: =IF(AD17=1,0,BV17-(1-(1-(1/(1+EXP(-(BT17-BK17)))*Parameters!$B$3))^12)*100) | CD17: =IF(AD17=1,0,BV17-(1-(1-(1/(1+EXP(-(BT17-BL17)))*Parameters!$B$3))^12)*100) | CE17: =IF(AD17=1,0,BV17-(1-(1-(1/(1+EXP(-(BT17-BM17)))*Parameters!$B$3))^12)*100) | CF17: =IF(AD17=1,0,BV17-(1-(1-(1/(1+EXP(-(BT17-BN17)))*Parameters!$B$3))^12)*100) | CG17: =IF(AD17=1,0,BV17-(1-(1-(1/(1+EXP(-(BT17-BO17)))*Parameters!$B$3))^12)*100) | CH17: =IF(AD17=1,0,BV17-(1-(1-(1/(1+EXP(-(BT17-BP17)))*Parameters!$B$3))^12)*100) | CI17: =IF(AD17=1,0,BV17-(1-(1-(1/(1+EXP(-(BT17-BQ17)))*Parameters!$B$3))^12)*100) | CJ17: =IF(AD17=1,0,BV17-(1-(1-(1/(1+EXP(-(BT17-BR17)))*Parameters!$B$3))^12)*100)
A18: GNR_2024_NEW | B18: 3617YPGE9 | C18: PN | D18: JLL REAL ESTATE CAPITAL, LLC | E18: 3617YPGE9_000000004611207 | F18: 202603 | G18: 5.7 | H18: 10724476 | I18: 420 | J18: 20230721 | K18: 20580801 | M18: 20330901 | N18: 10 | O18: 207/223(F) | P18: BAF | T18: OH | U18: 149 | V18: 490.5 | W18: 32 | X18: 2023 | Y18: 11.5 | Z18: 10 | AA18: =IF(ISNUMBER(W18),W18,IFERROR(MAX(0,(VALUE(LEFT(F18,4))-VALUE(LEFT(TEXT(J18,"00000000"),4)))*12+(VALUE(MID(F18,5,2))-VALUE(MID(TEXT(J18,"00000000"),5,2)))),"")) | AB18: =IFERROR((VALUE(LEFT(TEXT(K18,"00000000"),4))-VALUE(LEFT(F18,4)))*12+(VALUE(MID(TEXT(K18,"00000000"),5,2))-VALUE(MID(F18,5,2))),"") | AC18: =IF(OR(L18="",NOT(ISNUMBER(L18))),0,MAX(0,MIN(60,(VALUE(LEFT(F18,4))-VALUE(LEFT(TEXT(L18,"00000000"),4)))*12+(VALUE(MID(F18,5,2))-VALUE(MID(TEXT(L18,"00000000"),5,2)))))) | AD18: =IF(OR(L18="",NOT(ISNUMBER(L18))),0,IF(VALUE(F18)<VALUE(LEFT(TEXT(L18,"00000000"),6)),1,0)) | AE18: =IF(OR(M18="",NOT(ISNUMBER(M18))),0,IF(VALUE(F18)<VALUE(LEFT(TEXT(M18,"00000000"),6)),1,0)) | AF18: =IF(AND(AD18=0,AE18=0),1,0) | AG18: =IF(ISNUMBER(X18),X18,IFERROR(VALUE(LEFT(TEXT(J18,"00000000"),4)),"")) | AH18: =IFERROR(XLOOKUP(AG18,Vintage_Rates!$A$2:$A$1000,Vintage_Rates!$B$2:$B$1000,""),"") | AI18: =IF(ISNUMBER(Y18),Y18,IFERROR((G18-AH18)*100,"")) | AJ18: =IF(ISNUMBER(V18),V18,IFERROR(XLOOKUP(VALUE(F18),PLC_Rates!$A$2:$A$1000,PLC_Rates!$B$2:$B$1000,""),"")) | AK18: =IF(ISNUMBER(Z18),Z18,IF(AE18=0,0,MAX(0,MIN(10,((VALUE(LEFT(TEXT(M18,"00000000"),4))-VALUE(LEFT(F18,4)))*12+(VALUE(MID(TEXT(M18,"00000000"),5,2))-VALUE(MID(F18,5,2))))/12)))) | AL18: =IFERROR(G18*100-AJ18,"") | AM18: =IFERROR(G18*100-(AJ18+(1+AK18)*12.5),"") | AN18: =IFERROR(MIN(H18/1000000,100),"") | AO18: =IFERROR(INDEX(FHA_Lookup!$B$2:$B$11,MATCH(TRUE,ISNUMBER(SEARCH(FHA_Lookup!$A$2:$A$11,UPPER(SUBSTITUTE(O18," ","")))),0)),"OTHER") | AP18: =IFERROR(INDEX(FHA_Lookup!$C$2:$C$11,MATCH(TRUE,ISNUMBER(SEARCH(FHA_Lookup!$A$2:$A$11,UPPER(SUBSTITUTE(O18," ","")))),0)),"OTHER") | AQ18: =IF(AP18="NC",1,0) | AR18: =IF(UPPER(TRIM(P18))="AFF",1,0) | AS18: =IF(UPPER(TRIM(P18))="BAF",1,0) | AT18: =IF(UPPER(TRIM(P18))="MKT",1,0) | AU18: =IF(AO18="221d4",1,0) | AV18: =IF(AO18="223a7",1,0) | AW18: =IF(AO18="232",1,0) | AX18: =IF(AO18="538",1,0) | AY18: =IF(AO18="241",1,0) | AZ18: =IF(AO18="220",1,0) | BA18: =IF(AO18="OTHER",1,0) | BB18: =IF(UPPER(TRIM(C18))="LM",1,0) | BC18: =IF(UPPER(TRIM(C18))="PN",1,0) | BD18: =IF(UPPER(TRIM(C18))="LS",1,0) | BE18: =IF(UPPER(TRIM(C18))="RX",1,0) | BF18: =IFERROR((Parameters!$C$6*AM18+Parameters!$C$7*MAX(AM18-(-150),0)+Parameters!$C$8*MAX(AM18-(-50),0)+Parameters!$C$9*MAX(AM18-(0),0)+Parameters!$C$10*MAX(AM18-(50),0)+Parameters!$C$11*MAX(AM18-(100),0)+Parameters!$C$12*MAX(AM18-(150),0)+Parameters!$C$13*MAX(AM18-(250),0)),0) | BG18: =IFERROR((Parameters!$C$14*AA18+Parameters!$C$15*MAX(AA18-(12),0)+Parameters!$C$16*MAX(AA18-(36),0)+Parameters!$C$17*MAX(AA18-(60),0)+Parameters!$C$18*MAX(AA18-(84),0)+Parameters!$C$19*MAX(AA18-(120),0)+Parameters!$C$20*MAX(AA18-(180),0)),0) | BH18: =IFERROR((Parameters!$C$21*AK18+Parameters!$C$22*MAX(AK18-(0),0)+Parameters!$C$23*MAX(AK18-(2),0)+Parameters!$C$24*MAX(AK18-(5),0)+Parameters!$C$25*MAX(AK18-(8),0)),0) | BI18: =IFERROR((Parameters!$C$26*AI18+Parameters!$C$27*MAX(AI18-(-100),0)+Parameters!$C$28*MAX(AI18-(-25),0)+Parameters!$C$29*MAX(AI18-(25),0)+Parameters!$C$30*MAX(AI18-(100),0)),0) | BJ18: =IFERROR((Parameters!$C$31*AN18+Parameters!$C$32*MAX(AN18-(2),0)+Parameters!$C$33*MAX(AN18-(10),0)+Parameters!$C$34*MAX(AN18-(25),0)),0) | BK18: =IFERROR((Parameters!$C$35*AB18+Parameters!$C$36*MAX(AB18-(12),0)+Parameters!$C$37*MAX(AB18-(24),0)+Parameters!$C$38*MAX(AB18-(60),0)),0) | BL18: =IFERROR((Parameters!$C$39*AC18+Parameters!$C$40*MAX(AC18-(6),0)+Parameters!$C$41*MAX(AC18-(12),0)+Parameters!$C$42*MAX(AC18-(24),0)),0) | BM18: =IFERROR(Parameters!$C$43*(MAX(AM18,0)*MIN(MAX(AK18,0),10))/100,0) | BN18: =Parameters!$C$44*AE18 | BO18: =Parameters!$C$45*AU18 + Parameters!$C$46*AV18 + Parameters!$C$47*AW18 + Parameters!$C$48*AX18 + Parameters!$C$49*AY18 + Parameters!$C$50*AZ18 + Parameters!$C$51*BA18 | BP18: =Parameters!$C$52*AQ18 | BQ18: =Parameters!$C$53*AR18+Parameters!$C$54*AS18+Parameters!$C$55*AT18 | BR18: =Parameters!$C$56*BB18+Parameters!$C$57*BC18+Parameters!$C$58*BD18+Parameters!$C$59*BE18 | BS18: =Parameters!$B$2 | BT18: =BS18+BF18 + BG18 + BH18 + BI18 + BJ18 + BK18 + BL18 + BM18 + BN18 + BO18 + BP18 + BQ18 + BR18 | BU18: =IF(AD18=1,0,1/(1+EXP(-BT18))*Parameters!$B$3) | BV18: =(1-(1-BU18)^12)*100 | BW18: =IF(AD18=1,0,(1-(1-1/(1+EXP(-Parameters!$B$2)))^12)*100) | BX18: =IF(AD18=1,0,BV18-(1-(1-(1/(1+EXP(-(BT18-BF18)))*Parameters!$B$3))^12)*100) | BY18: =IF(AD18=1,0,BV18-(1-(1-(1/(1+EXP(-(BT18-BG18)))*Parameters!$B$3))^12)*100) | BZ18: =IF(AD18=1,0,BV18-(1-(1-(1/(1+EXP(-(BT18-BH18)))*Parameters!$B$3))^12)*100) | CA18: =IF(AD18=1,0,BV18-(1-(1-(1/(1+EXP(-(BT18-BI18)))*Parameters!$B$3))^12)*100) | CB18: =IF(AD18=1,0,BV18-(1-(1-(1/(1+EXP(-(BT18-BJ18)))*Parameters!$B$3))^12)*100) | CC18: =IF(AD18=1,0,BV18-(1-(1-(1/(1+EXP(-(BT18-BK18)))*Parameters!$B$3))^12)*100) | CD18: =IF(AD18=1,0,BV18-(1-(1-(1/(1+EXP(-(BT18-BL18)))*Parameters!$B$3))^12)*100) | CE18: =IF(AD18=1,0,BV18-(1-(1-(1/(1+EXP(-(BT18-BM18)))*Parameters!$B$3))^12)*100) | CF18: =IF(AD18=1,0,BV18-(1-(1-(1/(1+EXP(-(BT18-BN18)))*Parameters!$B$3))^12)*100) | CG18: =IF(AD18=1,0,BV18-(1-(1-(1/(1+EXP(-(BT18-BO18)))*Parameters!$B$3))^12)*100) | CH18: =IF(AD18=1,0,BV18-(1-(1-(1/(1+EXP(-(BT18-BP18)))*Parameters!$B$3))^12)*100) | CI18: =IF(AD18=1,0,BV18-(1-(1-(1/(1+EXP(-(BT18-BQ18)))*Parameters!$B$3))^12)*100) | CJ18: =IF(AD18=1,0,BV18-(1-(1-(1/(1+EXP(-(BT18-BR18)))*Parameters!$B$3))^12)*100)
A19: GNR_2024_NEW | B19: 3618JBEW7 | C19: PN | D19: GREYSTONE FUNDING COMPANY LLC | E19: 3618JBEW7_000000006122231 | F19: 202603 | G19: 5.46 | H19: 32331261 | I19: 300 | J19: 20240901 | K19: 20491001 | L19: 20341101 | N19: 0 | O19: 242/223(f) | T19: AL | U19: 338 | V19: 490.5 | W19: 18 | X19: 2024 | Y19: -32 | Z19: 0 | AA19: =IF(ISNUMBER(W19),W19,IFERROR(MAX(0,(VALUE(LEFT(F19,4))-VALUE(LEFT(TEXT(J19,"00000000"),4)))*12+(VALUE(MID(F19,5,2))-VALUE(MID(TEXT(J19,"00000000"),5,2)))),"")) | AB19: =IFERROR((VALUE(LEFT(TEXT(K19,"00000000"),4))-VALUE(LEFT(F19,4)))*12+(VALUE(MID(TEXT(K19,"00000000"),5,2))-VALUE(MID(F19,5,2))),"") | AC19: =IF(OR(L19="",NOT(ISNUMBER(L19))),0,MAX(0,MIN(60,(VALUE(LEFT(F19,4))-VALUE(LEFT(TEXT(L19,"00000000"),4)))*12+(VALUE(MID(F19,5,2))-VALUE(MID(TEXT(L19,"00000000"),5,2)))))) | AD19: =IF(OR(L19="",NOT(ISNUMBER(L19))),0,IF(VALUE(F19)<VALUE(LEFT(TEXT(L19,"00000000"),6)),1,0)) | AE19: =IF(OR(M19="",NOT(ISNUMBER(M19))),0,IF(VALUE(F19)<VALUE(LEFT(TEXT(M19,"00000000"),6)),1,0)) | AF19: =IF(AND(AD19=0,AE19=0),1,0) | AG19: =IF(ISNUMBER(X19),X19,IFERROR(VALUE(LEFT(TEXT(J19,"00000000"),4)),"")) | AH19: =IFERROR(XLOOKUP(AG19,Vintage_Rates!$A$2:$A$1000,Vintage_Rates!$B$2:$B$1000,""),"") | AI19: =IF(ISNUMBER(Y19),Y19,IFERROR((G19-AH19)*100,"")) | AJ19: =IF(ISNUMBER(V19),V19,IFERROR(XLOOKUP(VALUE(F19),PLC_Rates!$A$2:$A$1000,PLC_Rates!$B$2:$B$1000,""),"")) | AK19: =IF(ISNUMBER(Z19),Z19,IF(AE19=0,0,MAX(0,MIN(10,((VALUE(LEFT(TEXT(M19,"00000000"),4))-VALUE(LEFT(F19,4)))*12+(VALUE(MID(TEXT(M19,"00000000"),5,2))-VALUE(MID(F19,5,2))))/12)))) | AL19: =IFERROR(G19*100-AJ19,"") | AM19: =IFERROR(G19*100-(AJ19+(1+AK19)*12.5),"") | AN19: =IFERROR(MIN(H19/1000000,100),"") | AO19: =IFERROR(INDEX(FHA_Lookup!$B$2:$B$11,MATCH(TRUE,ISNUMBER(SEARCH(FHA_Lookup!$A$2:$A$11,UPPER(SUBSTITUTE(O19," ","")))),0)),"OTHER") | AP19: =IFERROR(INDEX(FHA_Lookup!$C$2:$C$11,MATCH(TRUE,ISNUMBER(SEARCH(FHA_Lookup!$A$2:$A$11,UPPER(SUBSTITUTE(O19," ","")))),0)),"OTHER") | AQ19: =IF(AP19="NC",1,0) | AR19: =IF(UPPER(TRIM(P19))="AFF",1,0) | AS19: =IF(UPPER(TRIM(P19))="BAF",1,0) | AT19: =IF(UPPER(TRIM(P19))="MKT",1,0) | AU19: =IF(AO19="221d4",1,0) | AV19: =IF(AO19="223a7",1,0) | AW19: =IF(AO19="232",1,0) | AX19: =IF(AO19="538",1,0) | AY19: =IF(AO19="241",1,0) | AZ19: =IF(AO19="220",1,0) | BA19: =IF(AO19="OTHER",1,0) | BB19: =IF(UPPER(TRIM(C19))="LM",1,0) | BC19: =IF(UPPER(TRIM(C19))="PN",1,0) | BD19: =IF(UPPER(TRIM(C19))="LS",1,0) | BE19: =IF(UPPER(TRIM(C19))="RX",1,0) | BF19: =IFERROR((Parameters!$C$6*AM19+Parameters!$C$7*MAX(AM19-(-150),0)+Parameters!$C$8*MAX(AM19-(-50),0)+Parameters!$C$9*MAX(AM19-(0),0)+Parameters!$C$10*MAX(AM19-(50),0)+Parameters!$C$11*MAX(AM19-(100),0)+Parameters!$C$12*MAX(AM19-(150),0)+Parameters!$C$13*MAX(AM19-(250),0)),0) | BG19: =IFERROR((Parameters!$C$14*AA19+Parameters!$C$15*MAX(AA19-(12),0)+Parameters!$C$16*MAX(AA19-(36),0)+Parameters!$C$17*MAX(AA19-(60),0)+Parameters!$C$18*MAX(AA19-(84),0)+Parameters!$C$19*MAX(AA19-(120),0)+Parameters!$C$20*MAX(AA19-(180),0)),0) | BH19: =IFERROR((Parameters!$C$21*AK19+Parameters!$C$22*MAX(AK19-(0),0)+Parameters!$C$23*MAX(AK19-(2),0)+Parameters!$C$24*MAX(AK19-(5),0)+Parameters!$C$25*MAX(AK19-(8),0)),0) | BI19: =IFERROR((Parameters!$C$26*AI19+Parameters!$C$27*MAX(AI19-(-100),0)+Parameters!$C$28*MAX(AI19-(-25),0)+Parameters!$C$29*MAX(AI19-(25),0)+Parameters!$C$30*MAX(AI19-(100),0)),0) | BJ19: =IFERROR((Parameters!$C$31*AN19+Parameters!$C$32*MAX(AN19-(2),0)+Parameters!$C$33*MAX(AN19-(10),0)+Parameters!$C$34*MAX(AN19-(25),0)),0) | BK19: =IFERROR((Parameters!$C$35*AB19+Parameters!$C$36*MAX(AB19-(12),0)+Parameters!$C$37*MAX(AB19-(24),0)+Parameters!$C$38*MAX(AB19-(60),0)),0) | BL19: =IFERROR((Parameters!$C$39*AC19+Parameters!$C$40*MAX(AC19-(6),0)+Parameters!$C$41*MAX(AC19-(12),0)+Parameters!$C$42*MAX(AC19-(24),0)),0) | BM19: =IFERROR(Parameters!$C$43*(MAX(AM19,0)*MIN(MAX(AK19,0),10))/100,0) | BN19: =Parameters!$C$44*AE19 | BO19: =Parameters!$C$45*AU19 + Parameters!$C$46*AV19 + Parameters!$C$47*AW19 + Parameters!$C$48*AX19 + Parameters!$C$49*AY19 + Parameters!$C$50*AZ19 + Parameters!$C$51*BA19 | BP19: =Parameters!$C$52*AQ19 | BQ19: =Parameters!$C$53*AR19+Parameters!$C$54*AS19+Parameters!$C$55*AT19 | BR19: =Parameters!$C$56*BB19+Parameters!$C$57*BC19+Parameters!$C$58*BD19+Parameters!$C$59*BE19 | BS19: =Parameters!$B$2 | BT19: =BS19+BF19 + BG19 + BH19 + BI19 + BJ19 + BK19 + BL19 + BM19 + BN19 + BO19 + BP19 + BQ19 + BR19 | BU19: =IF(AD19=1,0,1/(1+EXP(-BT19))*Parameters!$B$3) | BV19: =(1-(1-BU19)^12)*100 | BW19: =IF(AD19=1,0,(1-(1-1/(1+EXP(-Parameters!$B$2)))^12)*100) | BX19: =IF(AD19=1,0,BV19-(1-(1-(1/(1+EXP(-(BT19-BF19)))*Parameters!$B$3))^12)*100) | BY19: =IF(AD19=1,0,BV19-(1-(1-(1/(1+EXP(-(BT19-BG19)))*Parameters!$B$3))^12)*100) | BZ19: =IF(AD19=1,0,BV19-(1-(1-(1/(1+EXP(-(BT19-BH19)))*Parameters!$B$3))^12)*100) | CA19: =IF(AD19=1,0,BV19-(1-(1-(1/(1+EXP(-(BT19-BI19)))*Parameters!$B$3))^12)*100) | CB19: =IF(AD19=1,0,BV19-(1-(1-(1/(1+EXP(-(BT19-BJ19)))*Parameters!$B$3))^12)*100) | CC19: =IF(AD19=1,0,BV19-(1-(1-(1/(1+EXP(-(BT19-BK19)))*Parameters!$B$3))^12)*100) | CD19: =IF(AD19=1,0,BV19-(1-(1-(1/(1+EXP(-(BT19-BL19)))*Parameters!$B$3))^12)*100) | CE19: =IF(AD19=1,0,BV19-(1-(1-(1/(1+EXP(-(BT19-BM19)))*Parameters!$B$3))^12)*100) | CF19: =IF(AD19=1,0,BV19-(1-(1-(1/(1+EXP(-(BT19-BN19)))*Parameters!$B$3))^12)*100) | CG19: =IF(AD19=1,0,BV19-(1-(1-(1/(1+EXP(-(BT19-BO19)))*Parameters!$B$3))^12)*100) | CH19: =IF(AD19=1,0,BV19-(1-(1-(1/(1+EXP(-(BT19-BP19)))*Parameters!$B$3))^12)*100) | CI19: =IF(AD19=1,0,BV19-(1-(1-(1/(1+EXP(-(BT19-BQ19)))*Parameters!$B$3))^12)*100) | CJ19: =IF(AD19=1,0,BV19-(1-(1-(1/(1+EXP(-(BT19-BR19)))*Parameters!$B$3))^12)*100)
A20: GNR_2024_NEW | B20: 3617FTC63 | C20: PN | D20: LUMENT REAL ESTATE CAPITAL,LLC | E20: 3617FTC63_000000002311705 | F20: 202603 | G20: 5.05 | H20: 10068907 | I20: 420 | J20: 20230201 | K20: 20580301 | M20: 20330401 | N20: 10 | O20: 207/223(F) | P20: BAF | T20: MA | U20: 59 | V20: 490.5 | W20: 37 | X20: 2023 | Y20: -53.5 | Z20: 8 | AA20: =IF(ISNUMBER(W20),W20,IFERROR(MAX(0,(VALUE(LEFT(F20,4))-VALUE(LEFT(TEXT(J20,"00000000"),4)))*12+(VALUE(MID(F20,5,2))-VALUE(MID(TEXT(J20,"00000000"),5,2)))),"")) | AB20: =IFERROR((VALUE(LEFT(TEXT(K20,"00000000"),4))-VALUE(LEFT(F20,4)))*12+(VALUE(MID(TEXT(K20,"00000000"),5,2))-VALUE(MID(F20,5,2))),"") | AC20: =IF(OR(L20="",NOT(ISNUMBER(L20))),0,MAX(0,MIN(60,(VALUE(LEFT(F20,4))-VALUE(LEFT(TEXT(L20,"00000000"),4)))*12+(VALUE(MID(F20,5,2))-VALUE(MID(TEXT(L20,"00000000"),5,2)))))) | AD20: =IF(OR(L20="",NOT(ISNUMBER(L20))),0,IF(VALUE(F20)<VALUE(LEFT(TEXT(L20,"00000000"),6)),1,0)) | AE20: =IF(OR(M20="",NOT(ISNUMBER(M20))),0,IF(VALUE(F20)<VALUE(LEFT(TEXT(M20,"00000000"),6)),1,0)) | AF20: =IF(AND(AD20=0,AE20=0),1,0) | AG20: =IF(ISNUMBER(X20),X20,IFERROR(VALUE(LEFT(TEXT(J20,"00000000"),4)),"")) | AH20: =IFERROR(XLOOKUP(AG20,Vintage_Rates!$A$2:$A$1000,Vintage_Rates!$B$2:$B$1000,""),"") | AI20: =IF(ISNUMBER(Y20),Y20,IFERROR((G20-AH20)*100,"")) | AJ20: =IF(ISNUMBER(V20),V20,IFERROR(XLOOKUP(VALUE(F20),PLC_Rates!$A$2:$A$1000,PLC_Rates!$B$2:$B$1000,""),"")) | AK20: =IF(ISNUMBER(Z20),Z20,IF(AE20=0,0,MAX(0,MIN(10,((VALUE(LEFT(TEXT(M20,"00000000"),4))-VALUE(LEFT(F20,4)))*12+(VALUE(MID(TEXT(M20,"00000000"),5,2))-VALUE(MID(F20,5,2))))/12)))) | AL20: =IFERROR(G20*100-AJ20,"") | AM20: =IFERROR(G20*100-(AJ20+(1+AK20)*12.5),"") | AN20: =IFERROR(MIN(H20/1000000,100),"") | AO20: =IFERROR(INDEX(FHA_Lookup!$B$2:$B$11,MATCH(TRUE,ISNUMBER(SEARCH(FHA_Lookup!$A$2:$A$11,UPPER(SUBSTITUTE(O20," ","")))),0)),"OTHER") | AP20: =IFERROR(INDEX(FHA_Lookup!$C$2:$C$11,MATCH(TRUE,ISNUMBER(SEARCH(FHA_Lookup!$A$2:$A$11,UPPER(SUBSTITUTE(O20," ","")))),0)),"OTHER") | AQ20: =IF(AP20="NC",1,0) | AR20: =IF(UPPER(TRIM(P20))="AFF",1,0) | AS20: =IF(UPPER(TRIM(P20))="BAF",1,0) | AT20: =IF(UPPER(TRIM(P20))="MKT",1,0) | AU20: =IF(AO20="221d4",1,0) | AV20: =IF(AO20="223a7",1,0) | AW20: =IF(AO20="232",1,0) | AX20: =IF(AO20="538",1,0) | AY20: =IF(AO20="241",1,0) | AZ20: =IF(AO20="220",1,0) | BA20: =IF(AO20="OTHER",1,0) | BB20: =IF(UPPER(TRIM(C20))="LM",1,0) | BC20: =IF(UPPER(TRIM(C20))="PN",1,0) | BD20: =IF(UPPER(TRIM(C20))="LS",1,0) | BE20: =IF(UPPER(TRIM(C20))="RX",1,0) | BF20: =IFERROR((Parameters!$C$6*AM20+Parameters!$C$7*MAX(AM20-(-150),0)+Parameters!$C$8*MAX(AM20-(-50),0)+Parameters!$C$9*MAX(AM20-(0),0)+Parameters!$C$10*MAX(AM20-(50),0)+Parameters!$C$11*MAX(AM20-(100),0)+Parameters!$C$12*MAX(AM20-(150),0)+Parameters!$C$13*MAX(AM20-(250),0)),0) | BG20: =IFERROR((Parameters!$C$14*AA20+Parameters!$C$15*MAX(AA20-(12),0)+Parameters!$C$16*MAX(AA20-(36),0)+Parameters!$C$17*MAX(AA20-(60),0)+Parameters!$C$18*MAX(AA20-(84),0)+Parameters!$C$19*MAX(AA20-(120),0)+Parameters!$C$20*MAX(AA20-(180),0)),0) | BH20: =IFERROR((Parameters!$C$21*AK20+Parameters!$C$22*MAX(AK20-(0),0)+Parameters!$C$23*MAX(AK20-(2),0)+Parameters!$C$24*MAX(AK20-(5),0)+Parameters!$C$25*MAX(AK20-(8),0)),0) | BI20: =IFERROR((Parameters!$C$26*AI20+Parameters!$C$27*MAX(AI20-(-100),0)+Parameters!$C$28*MAX(AI20-(-25),0)+Parameters!$C$29*MAX(AI20-(25),0)+Parameters!$C$30*MAX(AI20-(100),0)),0) | BJ20: =IFERROR((Parameters!$C$31*AN20+Parameters!$C$32*MAX(AN20-(2),0)+Parameters!$C$33*MAX(AN20-(10),0)+Parameters!$C$34*MAX(AN20-(25),0)),0) | BK20: =IFERROR((Parameters!$C$35*AB20+Parameters!$C$36*MAX(AB20-(12),0)+Parameters!$C$37*MAX(AB20-(24),0)+Parameters!$C$38*MAX(AB20-(60),0)),0) | BL20: =IFERROR((Parameters!$C$39*AC20+Parameters!$C$40*MAX(AC20-(6),0)+Parameters!$C$41*MAX(AC20-(12),0)+Parameters!$C$42*MAX(AC20-(24),0)),0) | BM20: =IFERROR(Parameters!$C$43*(MAX(AM20,0)*MIN(MAX(AK20,0),10))/100,0) | BN20: =Parameters!$C$44*AE20 | BO20: =Parameters!$C$45*AU20 + Parameters!$C$46*AV20 + Parameters!$C$47*AW20 + Parameters!$C$48*AX20 + Parameters!$C$49*AY20 + Parameters!$C$50*AZ20 + Parameters!$C$51*BA20 | BP20: =Parameters!$C$52*AQ20 | BQ20: =Parameters!$C$53*AR20+Parameters!$C$54*AS20+Parameters!$C$55*AT20 | BR20: =Parameters!$C$56*BB20+Parameters!$C$57*BC20+Parameters!$C$58*BD20+Parameters!$C$59*BE20 | BS20: =Parameters!$B$2 | BT20: =BS20+BF20 + BG20 + BH20 + BI20 + BJ20 + BK20 + BL20 + BM20 + BN20 + BO20 + BP20 + BQ20 + BR20 | BU20: =IF(AD20=1,0,1/(1+EXP(-BT20))*Parameters!$B$3) | BV20: =(1-(1-BU20)^12)*100 | BW20: =IF(AD20=1,0,(1-(1-1/(1+EXP(-Parameters!$B$2)))^12)*100) | BX20: =IF(AD20=1,0,BV20-(1-(1-(1/(1+EXP(-(BT20-BF20)))*Parameters!$B$3))^12)*100) | BY20: =IF(AD20=1,0,BV20-(1-(1-(1/(1+EXP(-(BT20-BG20)))*Parameters!$B$3))^12)*100) | BZ20: =IF(AD20=1,0,BV20-(1-(1-(1/(1+EXP(-(BT20-BH20)))*Parameters!$B$3))^12)*100) | CA20: =IF(AD20=1,0,BV20-(1-(1-(1/(1+EXP(-(BT20-BI20)))*Parameters!$B$3))^12)*100) | CB20: =IF(AD20=1,0,BV20-(1-(1-(1/(1+EXP(-(BT20-BJ20)))*Parameters!$B$3))^12)*100) | CC20: =IF(AD20=1,0,BV20-(1-(1-(1/(1+EXP(-(BT20-BK20)))*Parameters!$B$3))^12)*100) | CD20: =IF(AD20=1,0,BV20-(1-(1-(1/(1+EXP(-(BT20-BL20)))*Parameters!$B$3))^12)*100) | CE20: =IF(AD20=1,0,BV20-(1-(1-(1/(1+EXP(-(BT20-BM20)))*Parameters!$B$3))^12)*100) | CF20: =IF(AD20=1,0,BV20-(1-(1-(1/(1+EXP(-(BT20-BN20)))*Parameters!$B$3))^12)*100) | CG20: =IF(AD20=1,0,BV20-(1-(1-(1/(1+EXP(-(BT20-BO20)))*Parameters!$B$3))^12)*100) | CH20: =IF(AD20=1,0,BV20-(1-(1-(1/(1+EXP(-(BT20-BP20)))*Parameters!$B$3))^12)*100) | CI20: =IF(AD20=1,0,BV20-(1-(1-(1/(1+EXP(-(BT20-BQ20)))*Parameters!$B$3))^12)*100) | CJ20: =IF(AD20=1,0,BV20-(1-(1-(1/(1+EXP(-(BT20-BR20)))*Parameters!$B$3))^12)*100)
A21: GNR_2024_NEW | B21: 3618LKKV9 | C21: PN | D21: BERKADIA COMMERCIAL MORTGAGE, LLC | E21: 3618LKKV9_000000017122060 | F21: 202603 | G21: 5.87 | H21: 26770474 | I21: 396 | J21: 20250722 | K21: 20581001 | M21: 20351101 | N21: 10 | O21: 232/223(F) | T21: WA | U21: 208 | V21: 490.5 | W21: 8 | X21: 2025 | Y21: 5 | Z21: 0 | AA21: =IF(ISNUMBER(W21),W21,IFERROR(MAX(0,(VALUE(LEFT(F21,4))-VALUE(LEFT(TEXT(J21,"00000000"),4)))*12+(VALUE(MID(F21,5,2))-VALUE(MID(TEXT(J21,"00000000"),5,2)))),"")) | AB21: =IFERROR((VALUE(LEFT(TEXT(K21,"00000000"),4))-VALUE(LEFT(F21,4)))*12+(VALUE(MID(TEXT(K21,"00000000"),5,2))-VALUE(MID(F21,5,2))),"") | AC21: =IF(OR(L21="",NOT(ISNUMBER(L21))),0,MAX(0,MIN(60,(VALUE(LEFT(F21,4))-VALUE(LEFT(TEXT(L21,"00000000"),4)))*12+(VALUE(MID(F21,5,2))-VALUE(MID(TEXT(L21,"00000000"),5,2)))))) | AD21: =IF(OR(L21="",NOT(ISNUMBER(L21))),0,IF(VALUE(F21)<VALUE(LEFT(TEXT(L21,"00000000"),6)),1,0)) | AE21: =IF(OR(M21="",NOT(ISNUMBER(M21))),0,IF(VALUE(F21)<VALUE(LEFT(TEXT(M21,"00000000"),6)),1,0)) | AF21: =IF(AND(AD21=0,AE21=0),1,0) | AG21: =IF(ISNUMBER(X21),X21,IFERROR(VALUE(LEFT(TEXT(J21,"00000000"),4)),"")) | AH21: =IFERROR(XLOOKUP(AG21,Vintage_Rates!$A$2:$A$1000,Vintage_Rates!$B$2:$B$1000,""),"") | AI21: =IF(ISNUMBER(Y21),Y21,IFERROR((G21-AH21)*100,"")) | AJ21: =IF(ISNUMBER(V21),V21,IFERROR(XLOOKUP(VALUE(F21),PLC_Rates!$A$2:$A$1000,PLC_Rates!$B$2:$B$1000,""),"")) | AK21: =IF(ISNUMBER(Z21),Z21,IF(AE21=0,0,MAX(0,MIN(10,((VALUE(LEFT(TEXT(M21,"00000000"),4))-VALUE(LEFT(F21,4)))*12+(VALUE(MID(TEXT(M21,"00000000"),5,2))-VALUE(MID(F21,5,2))))/12)))) | AL21: =IFERROR(G21*100-AJ21,"") | AM21: =IFERROR(G21*100-(AJ21+(1+AK21)*12.5),"") | AN21: =IFERROR(MIN(H21/1000000,100),"") | AO21: =IFERROR(INDEX(FHA_Lookup!$B$2:$B$11,MATCH(TRUE,ISNUMBER(SEARCH(FHA_Lookup!$A$2:$A$11,UPPER(SUBSTITUTE(O21," ","")))),0)),"OTHER") | AP21: =IFERROR(INDEX(FHA_Lookup!$C$2:$C$11,MATCH(TRUE,ISNUMBER(SEARCH(FHA_Lookup!$A$2:$A$11,UPPER(SUBSTITUTE(O21," ","")))),0)),"OTHER") | AQ21: =IF(AP21="NC",1,0) | AR21: =IF(UPPER(TRIM(P21))="AFF",1,0) | AS21: =IF(UPPER(TRIM(P21))="BAF",1,0) | AT21: =IF(UPPER(TRIM(P21))="MKT",1,0) | AU21: =IF(AO21="221d4",1,0) | AV21: =IF(AO21="223a7",1,0) | AW21: =IF(AO21="232",1,0) | AX21: =IF(AO21="538",1,0) | AY21: =IF(AO21="241",1,0) | AZ21: =IF(AO21="220",1,0) | BA21: =IF(AO21="OTHER",1,0) | BB21: =IF(UPPER(TRIM(C21))="LM",1,0) | BC21: =IF(UPPER(TRIM(C21))="PN",1,0) | BD21: =IF(UPPER(TRIM(C21))="LS",1,0) | BE21: =IF(UPPER(TRIM(C21))="RX",1,0) | BF21: =IFERROR((Parameters!$C$6*AM21+Parameters!$C$7*MAX(AM21-(-150),0)+Parameters!$C$8*MAX(AM21-(-50),0)+Parameters!$C$9*MAX(AM21-(0),0)+Parameters!$C$10*MAX(AM21-(50),0)+Parameters!$C$11*MAX(AM21-(100),0)+Parameters!$C$12*MAX(AM21-(150),0)+Parameters!$C$13*MAX(AM21-(250),0)),0) | BG21: =IFERROR((Parameters!$C$14*AA21+Parameters!$C$15*MAX(AA21-(12),0)+Parameters!$C$16*MAX(AA21-(36),0)+Parameters!$C$17*MAX(AA21-(60),0)+Parameters!$C$18*MAX(AA21-(84),0)+Parameters!$C$19*MAX(AA21-(120),0)+Parameters!$C$20*MAX(AA21-(180),0)),0) | BH21: =IFERROR((Parameters!$C$21*AK21+Parameters!$C$22*MAX(AK21-(0),0)+Parameters!$C$23*MAX(AK21-(2),0)+Parameters!$C$24*MAX(AK21-(5),0)+Parameters!$C$25*MAX(AK21-(8),0)),0) | BI21: =IFERROR((Parameters!$C$26*AI21+Parameters!$C$27*MAX(AI21-(-100),0)+Parameters!$C$28*MAX(AI21-(-25),0)+Parameters!$C$29*MAX(AI21-(25),0)+Parameters!$C$30*MAX(AI21-(100),0)),0) | BJ21: =IFERROR((Parameters!$C$31*AN21+Parameters!$C$32*MAX(AN21-(2),0)+Parameters!$C$33*MAX(AN21-(10),0)+Parameters!$C$34*MAX(AN21-(25),0)),0) | BK21: =IFERROR((Parameters!$C$35*AB21+Parameters!$C$36*MAX(AB21-(12),0)+Parameters!$C$37*MAX(AB21-(24),0)+Parameters!$C$38*MAX(AB21-(60),0)),0) | BL21: =IFERROR((Parameters!$C$39*AC21+Parameters!$C$40*MAX(AC21-(6),0)+Parameters!$C$41*MAX(AC21-(12),0)+Parameters!$C$42*MAX(AC21-(24),0)),0) | BM21: =IFERROR(Parameters!$C$43*(MAX(AM21,0)*MIN(MAX(AK21,0),10))/100,0) | BN21: =Parameters!$C$44*AE21 | BO21: =Parameters!$C$45*AU21 + Parameters!$C$46*AV21 + Parameters!$C$47*AW21 + Parameters!$C$48*AX21 + Parameters!$C$49*AY21 + Parameters!$C$50*AZ21 + Parameters!$C$51*BA21 | BP21: =Parameters!$C$52*AQ21 | BQ21: =Parameters!$C$53*AR21+Parameters!$C$54*AS21+Parameters!$C$55*AT21 | BR21: =Parameters!$C$56*BB21+Parameters!$C$57*BC21+Parameters!$C$58*BD21+Parameters!$C$59*BE21 | BS21: =Parameters!$B$2 | BT21: =BS21+BF21 + BG21 + BH21 + BI21 + BJ21 + BK21 + BL21 + BM21 + BN21 + BO21 + BP21 + BQ21 + BR21 | BU21: =IF(AD21=1,0,1/(1+EXP(-BT21))*Parameters!$B$3) | BV21: =(1-(1-BU21)^12)*100 | BW21: =IF(AD21=1,0,(1-(1-1/(1+EXP(-Parameters!$B$2)))^12)*100) | BX21: =IF(AD21=1,0,BV21-(1-(1-(1/(1+EXP(-(BT21-BF21)))*Parameters!$B$3))^12)*100) | BY21: =IF(AD21=1,0,BV21-(1-(1-(1/(1+EXP(-(BT21-BG21)))*Parameters!$B$3))^12)*100) | BZ21: =IF(AD21=1,0,BV21-(1-(1-(1/(1+EXP(-(BT21-BH21)))*Parameters!$B$3))^12)*100) | CA21: =IF(AD21=1,0,BV21-(1-(1-(1/(1+EXP(-(BT21-BI21)))*Parameters!$B$3))^12)*100) | CB21: =IF(AD21=1,0,BV21-(1-(1-(1/(1+EXP(-(BT21-BJ21)))*Parameters!$B$3))^12)*100) | CC21: =IF(AD21=1,0,BV21-(1-(1-(1/(1+EXP(-(BT21-BK21)))*Parameters!$B$3))^12)*100) | CD21: =IF(AD21=1,0,BV21-(1-(1-(1/(1+EXP(-(BT21-BL21)))*Parameters!$B$3))^12)*100) | CE21: =IF(AD21=1,0,BV21-(1-(1-(1/(1+EXP(-(BT21-BM21)))*Parameters!$B$3))^12)*100) | CF21: =IF(AD21=1,0,BV21-(1-(1-(1/(1+EXP(-(BT21-BN21)))*Parameters!$B$3))^12)*100) | CG21: =IF(AD21=1,0,BV21-(1-(1-(1/(1+EXP(-(BT21-BO21)))*Parameters!$B$3))^12)*100) | CH21: =IF(AD21=1,0,BV21-(1-(1-(1/(1+EXP(-(BT21-BP21)))*Parameters!$B$3))^12)*100) | CI21: =IF(AD21=1,0,BV21-(1-(1-(1/(1+EXP(-(BT21-BQ21)))*Parameters!$B$3))^12)*100) | CJ21: =IF(AD21=1,0,BV21-(1-(1-(1/(1+EXP(-(BT21-BR21)))*Parameters!$B$3))^12)*100)
A22: GNR_2024_NEW | B22: 3618KU4M6 | C22: PN | D22: DWIGHT CAPITAL LLC | E22: 3618KU4M6_000000012111340 | F22: 202603 | G22: 4.54 | H22: 18355142 | I22: 420 | J22: 20250722 | K22: 20600801 | M22: 20350901 | N22: 10 | O22: 207/223(F) | T22: CA | U22: 79 | V22: 490.5 | W22: 8 | X22: 2025 | Y22: -128 | Z22: 0 | AA22: =IF(ISNUMBER(W22),W22,IFERROR(MAX(0,(VALUE(LEFT(F22,4))-VALUE(LEFT(TEXT(J22,"00000000"),4)))*12+(VALUE(MID(F22,5,2))-VALUE(MID(TEXT(J22,"00000000"),5,2)))),"")) | AB22: =IFERROR((VALUE(LEFT(TEXT(K22,"00000000"),4))-VALUE(LEFT(F22,4)))*12+(VALUE(MID(TEXT(K22,"00000000"),5,2))-VALUE(MID(F22,5,2))),"") | AC22: =IF(OR(L22="",NOT(ISNUMBER(L22))),0,MAX(0,MIN(60,(VALUE(LEFT(F22,4))-VALUE(LEFT(TEXT(L22,"00000000"),4)))*12+(VALUE(MID(F22,5,2))-VALUE(MID(TEXT(L22,"00000000"),5,2)))))) | AD22: =IF(OR(L22="",NOT(ISNUMBER(L22))),0,IF(VALUE(F22)<VALUE(LEFT(TEXT(L22,"00000000"),6)),1,0)) | AE22: =IF(OR(M22="",NOT(ISNUMBER(M22))),0,IF(VALUE(F22)<VALUE(LEFT(TEXT(M22,"00000000"),6)),1,0)) | AF22: =IF(AND(AD22=0,AE22=0),1,0) | AG22: =IF(ISNUMBER(X22),X22,IFERROR(VALUE(LEFT(TEXT(J22,"00000000"),4)),"")) | AH22: =IFERROR(XLOOKUP(AG22,Vintage_Rates!$A$2:$A$1000,Vintage_Rates!$B$2:$B$1000,""),"") | AI22: =IF(ISNUMBER(Y22),Y22,IFERROR((G22-AH22)*100,"")) | AJ22: =IF(ISNUMBER(V22),V22,IFERROR(XLOOKUP(VALUE(F22),PLC_Rates!$A$2:$A$1000,PLC_Rates!$B$2:$B$1000,""),"")) | AK22: =IF(ISNUMBER(Z22),Z22,IF(AE22=0,0,MAX(0,MIN(10,((VALUE(LEFT(TEXT(M22,"00000000"),4))-VALUE(LEFT(F22,4)))*12+(VALUE(MID(TEXT(M22,"00000000"),5,2))-VALUE(MID(F22,5,2))))/12)))) | AL22: =IFERROR(G22*100-AJ22,"") | AM22: =IFERROR(G22*100-(AJ22+(1+AK22)*12.5),"") | AN22: =IFERROR(MIN(H22/1000000,100),"") | AO22: =IFERROR(INDEX(FHA_Lookup!$B$2:$B$11,MATCH(TRUE,ISNUMBER(SEARCH(FHA_Lookup!$A$2:$A$11,UPPER(SUBSTITUTE(O22," ","")))),0)),"OTHER") | AP22: =IFERROR(INDEX(FHA_Lookup!$C$2:$C$11,MATCH(TRUE,ISNUMBER(SEARCH(FHA_Lookup!$A$2:$A$11,UPPER(SUBSTITUTE(O22," ","")))),0)),"OTHER") | AQ22: =IF(AP22="NC",1,0) | AR22: =IF(UPPER(TRIM(P22))="AFF",1,0) | AS22: =IF(UPPER(TRIM(P22))="BAF",1,0) | AT22: =IF(UPPER(TRIM(P22))="MKT",1,0) | AU22: =IF(AO22="221d4",1,0) | AV22: =IF(AO22="223a7",1,0) | AW22: =IF(AO22="232",1,0) | AX22: =IF(AO22="538",1,0) | AY22: =IF(AO22="241",1,0) | AZ22: =IF(AO22="220",1,0) | BA22: =IF(AO22="OTHER",1,0) | BB22: =IF(UPPER(TRIM(C22))="LM",1,0) | BC22: =IF(UPPER(TRIM(C22))="PN",1,0) | BD22: =IF(UPPER(TRIM(C22))="LS",1,0) | BE22: =IF(UPPER(TRIM(C22))="RX",1,0) | BF22: =IFERROR((Parameters!$C$6*AM22+Parameters!$C$7*MAX(AM22-(-150),0)+Parameters!$C$8*MAX(AM22-(-50),0)+Parameters!$C$9*MAX(AM22-(0),0)+Parameters!$C$10*MAX(AM22-(50),0)+Parameters!$C$11*MAX(AM22-(100),0)+Parameters!$C$12*MAX(AM22-(150),0)+Parameters!$C$13*MAX(AM22-(250),0)),0) | BG22: =IFERROR((Parameters!$C$14*AA22+Parameters!$C$15*MAX(AA22-(12),0)+Parameters!$C$16*MAX(AA22-(36),0)+Parameters!$C$17*MAX(AA22-(60),0)+Parameters!$C$18*MAX(AA22-(84),0)+Parameters!$C$19*MAX(AA22-(120),0)+Parameters!$C$20*MAX(AA22-(180),0)),0) | BH22: =IFERROR((Parameters!$C$21*AK22+Parameters!$C$22*MAX(AK22-(0),0)+Parameters!$C$23*MAX(AK22-(2),0)+Parameters!$C$24*MAX(AK22-(5),0)+Parameters!$C$25*MAX(AK22-(8),0)),0) | BI22: =IFERROR((Parameters!$C$26*AI22+Parameters!$C$27*MAX(AI22-(-100),0)+Parameters!$C$28*MAX(AI22-(-25),0)+Parameters!$C$29*MAX(AI22-(25),0)+Parameters!$C$30*MAX(AI22-(100),0)),0) | BJ22: =IFERROR((Parameters!$C$31*AN22+Parameters!$C$32*MAX(AN22-(2),0)+Parameters!$C$33*MAX(AN22-(10),0)+Parameters!$C$34*MAX(AN22-(25),0)),0) | BK22: =IFERROR((Parameters!$C$35*AB22+Parameters!$C$36*MAX(AB22-(12),0)+Parameters!$C$37*MAX(AB22-(24),0)+Parameters!$C$38*MAX(AB22-(60),0)),0) | BL22: =IFERROR((Parameters!$C$39*AC22+Parameters!$C$40*MAX(AC22-(6),0)+Parameters!$C$41*MAX(AC22-(12),0)+Parameters!$C$42*MAX(AC22-(24),0)),0) | BM22: =IFERROR(Parameters!$C$43*(MAX(AM22,0)*MIN(MAX(AK22,0),10))/100,0) | BN22: =Parameters!$C$44*AE22 | BO22: =Parameters!$C$45*AU22 + Parameters!$C$46*AV22 + Parameters!$C$47*AW22 + Parameters!$C$48*AX22 + Parameters!$C$49*AY22 + Parameters!$C$50*AZ22 + Parameters!$C$51*BA22 | BP22: =Parameters!$C$52*AQ22 | BQ22: =Parameters!$C$53*AR22+Parameters!$C$54*AS22+Parameters!$C$55*AT22 | BR22: =Parameters!$C$56*BB22+Parameters!$C$57*BC22+Parameters!$C$58*BD22+Parameters!$C$59*BE22 | BS22: =Parameters!$B$2 | BT22: =BS22+BF22 + BG22 + BH22 + BI22 + BJ22 + BK22 + BL22 + BM22 + BN22 + BO22 + BP22 + BQ22 + BR22 | BU22: =IF(AD22=1,0,1/(1+EXP(-BT22))*Parameters!$B$3) | BV22: =(1-(1-BU22)^12)*100 | BW22: =IF(AD22=1,0,(1-(1-1/(1+EXP(-Parameters!$B$2)))^12)*100) | BX22: =IF(AD22=1,0,BV22-(1-(1-(1/(1+EXP(-(BT22-BF22)))*Parameters!$B$3))^12)*100) | BY22: =IF(AD22=1,0,BV22-(1-(1-(1/(1+EXP(-(BT22-BG22)))*Parameters!$B$3))^12)*100) | BZ22: =IF(AD22=1,0,BV22-(1-(1-(1/(1+EXP(-(BT22-BH22)))*Parameters!$B$3))^12)*100) | CA22: =IF(AD22=1,0,BV22-(1-(1-(1/(1+EXP(-(BT22-BI22)))*Parameters!$B$3))^12)*100) | CB22: =IF(AD22=1,0,BV22-(1-(1-(1/(1+EXP(-(BT22-BJ22)))*Parameters!$B$3))^12)*100) | CC22: =IF(AD22=1,0,BV22-(1-(1-(1/(1+EXP(-(BT22-BK22)))*Parameters!$B$3))^12)*100) | CD22: =IF(AD22=1,0,BV22-(1-(1-(1/(1+EXP(-(BT22-BL22)))*Parameters!$B$3))^12)*100) | CE22: =IF(AD22=1,0,BV22-(1-(1-(1/(1+EXP(-(BT22-BM22)))*Parameters!$B$3))^12)*100) | CF22: =IF(AD22=1,0,BV22-(1-(1-(1/(1+EXP(-(BT22-BN22)))*Parameters!$B$3))^12)*100) | CG22: =IF(AD22=1,0,BV22-(1-(1-(1/(1+EXP(-(BT22-BO22)))*Parameters!$B$3))^12)*100) | CH22: =IF(AD22=1,0,BV22-(1-(1-(1/(1+EXP(-(BT22-BP22)))*Parameters!$B$3))^12)*100) | CI22: =IF(AD22=1,0,BV22-(1-(1-(1/(1+EXP(-(BT22-BQ22)))*Parameters!$B$3))^12)*100) | CJ22: =IF(AD22=1,0,BV22-(1-(1-(1/(1+EXP(-(BT22-BR22)))*Parameters!$B$3))^12)*100)
A23: GNR_2024_NEW | B23: 3618G8D57 | C23: PN | D23: GREYSTONE FUNDING COMPANY LLC | E23: 3618G8D57_000000005211349 | F23: 202603 | G23: 5.97 | H23: 11740375 | I23: 420 | J23: 20240101 | K23: 20590201 | M23: 20340301 | N23: 10 | O23: 207/223(F) | P23: MKT | T23: MD | U23: 104 | V23: 490.5 | W23: 26 | X23: 2024 | Y23: 19 | Z23: 8 | AA23: =IF(ISNUMBER(W23),W23,IFERROR(MAX(0,(VALUE(LEFT(F23,4))-VALUE(LEFT(TEXT(J23,"00000000"),4)))*12+(VALUE(MID(F23,5,2))-VALUE(MID(TEXT(J23,"00000000"),5,2)))),"")) | AB23: =IFERROR((VALUE(LEFT(TEXT(K23,"00000000"),4))-VALUE(LEFT(F23,4)))*12+(VALUE(MID(TEXT(K23,"00000000"),5,2))-VALUE(MID(F23,5,2))),"") | AC23: =IF(OR(L23="",NOT(ISNUMBER(L23))),0,MAX(0,MIN(60,(VALUE(LEFT(F23,4))-VALUE(LEFT(TEXT(L23,"00000000"),4)))*12+(VALUE(MID(F23,5,2))-VALUE(MID(TEXT(L23,"00000000"),5,2)))))) | AD23: =IF(OR(L23="",NOT(ISNUMBER(L23))),0,IF(VALUE(F23)<VALUE(LEFT(TEXT(L23,"00000000"),6)),1,0)) | AE23: =IF(OR(M23="",NOT(ISNUMBER(M23))),0,IF(VALUE(F23)<VALUE(LEFT(TEXT(M23,"00000000"),6)),1,0)) | AF23: =IF(AND(AD23=0,AE23=0),1,0) | AG23: =IF(ISNUMBER(X23),X23,IFERROR(VALUE(LEFT(TEXT(J23,"00000000"),4)),"")) | AH23: =IFERROR(XLOOKUP(AG23,Vintage_Rates!$A$2:$A$1000,Vintage_Rates!$B$2:$B$1000,""),"") | AI23: =IF(ISNUMBER(Y23),Y23,IFERROR((G23-AH23)*100,"")) | AJ23: =IF(ISNUMBER(V23),V23,IFERROR(XLOOKUP(VALUE(F23),PLC_Rates!$A$2:$A$1000,PLC_Rates!$B$2:$B$1000,""),"")) | AK23: =IF(ISNUMBER(Z23),Z23,IF(AE23=0,0,MAX(0,MIN(10,((VALUE(LEFT(TEXT(M23,"00000000"),4))-VALUE(LEFT(F23,4)))*12+(VALUE(MID(TEXT(M23,"00000000"),5,2))-VALUE(MID(F23,5,2))))/12)))) | AL23: =IFERROR(G23*100-AJ23,"") | AM23: =IFERROR(G23*100-(AJ23+(1+AK23)*12.5),"") | AN23: =IFERROR(MIN(H23/1000000,100),"") | AO23: =IFERROR(INDEX(FHA_Lookup!$B$2:$B$11,MATCH(TRUE,ISNUMBER(SEARCH(FHA_Lookup!$A$2:$A$11,UPPER(SUBSTITUTE(O23," ","")))),0)),"OTHER") | AP23: =IFERROR(INDEX(FHA_Lookup!$C$2:$C$11,MATCH(TRUE,ISNUMBER(SEARCH(FHA_Lookup!$A$2:$A$11,UPPER(SUBSTITUTE(O23," ","")))),0)),"OTHER") | AQ23: =IF(AP23="NC",1,0) | AR23: =IF(UPPER(TRIM(P23))="AFF",1,0) | AS23: =IF(UPPER(TRIM(P23))="BAF",1,0) | AT23: =IF(UPPER(TRIM(P23))="MKT",1,0) | AU23: =IF(AO23="221d4",1,0) | AV23: =IF(AO23="223a7",1,0) | AW23: =IF(AO23="232",1,0) | AX23: =IF(AO23="538",1,0) | AY23: =IF(AO23="241",1,0) | AZ23: =IF(AO23="220",1,0) | BA23: =IF(AO23="OTHER",1,0) | BB23: =IF(UPPER(TRIM(C23))="LM",1,0) | BC23: =IF(UPPER(TRIM(C23))="PN",1,0) | BD23: =IF(UPPER(TRIM(C23))="LS",1,0) | BE23: =IF(UPPER(TRIM(C23))="RX",1,0) | BF23: =IFERROR((Parameters!$C$6*AM23+Parameters!$C$7*MAX(AM23-(-150),0)+Parameters!$C$8*MAX(AM23-(-50),0)+Parameters!$C$9*MAX(AM23-(0),0)+Parameters!$C$10*MAX(AM23-(50),0)+Parameters!$C$11*MAX(AM23-(100),0)+Parameters!$C$12*MAX(AM23-(150),0)+Parameters!$C$13*MAX(AM23-(250),0)),0) | BG23: =IFERROR((Parameters!$C$14*AA23+Parameters!$C$15*MAX(AA23-(12),0)+Parameters!$C$16*MAX(AA23-(36),0)+Parameters!$C$17*MAX(AA23-(60),0)+Parameters!$C$18*MAX(AA23-(84),0)+Parameters!$C$19*MAX(AA23-(120),0)+Parameters!$C$20*MAX(AA23-(180),0)),0) | BH23: =IFERROR((Parameters!$C$21*AK23+Parameters!$C$22*MAX(AK23-(0),0)+Parameters!$C$23*MAX(AK23-(2),0)+Parameters!$C$24*MAX(AK23-(5),0)+Parameters!$C$25*MAX(AK23-(8),0)),0) | BI23: =IFERROR((Parameters!$C$26*AI23+Parameters!$C$27*MAX(AI23-(-100),0)+Parameters!$C$28*MAX(AI23-(-25),0)+Parameters!$C$29*MAX(AI23-(25),0)+Parameters!$C$30*MAX(AI23-(100),0)),0) | BJ23: =IFERROR((Parameters!$C$31*AN23+Parameters!$C$32*MAX(AN23-(2),0)+Parameters!$C$33*MAX(AN23-(10),0)+Parameters!$C$34*MAX(AN23-(25),0)),0) | BK23: =IFERROR((Parameters!$C$35*AB23+Parameters!$C$36*MAX(AB23-(12),0)+Parameters!$C$37*MAX(AB23-(24),0)+Parameters!$C$38*MAX(AB23-(60),0)),0) | BL23: =IFERROR((Parameters!$C$39*AC23+Parameters!$C$40*MAX(AC23-(6),0)+Parameters!$C$41*MAX(AC23-(12),0)+Parameters!$C$42*MAX(AC23-(24),0)),0) | BM23: =IFERROR(Parameters!$C$43*(MAX(AM23,0)*MIN(MAX(AK23,0),10))/100,0) | BN23: =Parameters!$C$44*AE23 | BO23: =Parameters!$C$45*AU23 + Parameters!$C$46*AV23 + Parameters!$C$47*AW23 + Parameters!$C$48*AX23 + Parameters!$C$49*AY23 + Parameters!$C$50*AZ23 + Parameters!$C$51*BA23 | BP23: =Parameters!$C$52*AQ23 | BQ23: =Parameters!$C$53*AR23+Parameters!$C$54*AS23+Parameters!$C$55*AT23 | BR23: =Parameters!$C$56*BB23+Parameters!$C$57*BC23+Parameters!$C$58*BD23+Parameters!$C$59*BE23 | BS23: =Parameters!$B$2 | BT23: =BS23+BF23 + BG23 + BH23 + BI23 + BJ23 + BK23 + BL23 + BM23 + BN23 + BO23 + BP23 + BQ23 + BR23 | BU23: =IF(AD23=1,0,1/(1+EXP(-BT23))*Parameters!$B$3) | BV23: =(1-(1-BU23)^12)*100 | BW23: =IF(AD23=1,0,(1-(1-1/(1+EXP(-Parameters!$B$2)))^12)*100) | BX23: =IF(AD23=1,0,BV23-(1-(1-(1/(1+EXP(-(BT23-BF23)))*Parameters!$B$3))^12)*100) | BY23: =IF(AD23=1,0,BV23-(1-(1-(1/(1+EXP(-(BT23-BG23)))*Parameters!$B$3))^12)*100) | BZ23: =IF(AD23=1,0,BV23-(1-(1-(1/(1+EXP(-(BT23-BH23)))*Parameters!$B$3))^12)*100) | CA23: =IF(AD23=1,0,BV23-(1-(1-(1/(1+EXP(-(BT23-BI23)))*Parameters!$B$3))^12)*100) | CB23: =IF(AD23=1,0,BV23-(1-(1-(1/(1+EXP(-(BT23-BJ23)))*Parameters!$B$3))^12)*100) | CC23: =IF(AD23=1,0,BV23-(1-(1-(1/(1+EXP(-(BT23-BK23)))*Parameters!$B$3))^12)*100) | CD23: =IF(AD23=1,0,BV23-(1-(1-(1/(1+EXP(-(BT23-BL23)))*Parameters!$B$3))^12)*100) | CE23: =IF(AD23=1,0,BV23-(1-(1-(1/(1+EXP(-(BT23-BM23)))*Parameters!$B$3))^12)*100) | CF23: =IF(AD23=1,0,BV23-(1-(1-(1/(1+EXP(-(BT23-BN23)))*Parameters!$B$3))^12)*100) | CG23: =IF(AD23=1,0,BV23-(1-(1-(1/(1+EXP(-(BT23-BO23)))*Parameters!$B$3))^12)*100) | CH23: =IF(AD23=1,0,BV23-(1-(1-(1/(1+EXP(-(BT23-BP23)))*Parameters!$B$3))^12)*100) | CI23: =IF(AD23=1,0,BV23-(1-(1-(1/(1+EXP(-(BT23-BQ23)))*Parameters!$B$3))^12)*100) | CJ23: =IF(AD23=1,0,BV23-(1-(1-(1/(1+EXP(-(BT23-BR23)))*Parameters!$B$3))^12)*100)
A24: GNR_2024_NEW | B24: 3618B24L0 | C24: PN | D24: BERKADIA COMMERCIAL MORTGAGE, LLC | E24: 3618B24L0_000000006622155 | F24: 202603 | G24: 5.97 | H24: 9338255.8 | I24: 420 | J24: 20240729 | K24: 20590801 | M24: 20340901 | N24: 10 | O24: 232/223(F) | P24: MKT | T24: FL | U24: 62 | V24: 490.5 | W24: 20 | X24: 2024 | Y24: 19 | Z24: 10 | AA24: =IF(ISNUMBER(W24),W24,IFERROR(MAX(0,(VALUE(LEFT(F24,4))-VALUE(LEFT(TEXT(J24,"00000000"),4)))*12+(VALUE(MID(F24,5,2))-VALUE(MID(TEXT(J24,"00000000"),5,2)))),"")) | AB24: =IFERROR((VALUE(LEFT(TEXT(K24,"00000000"),4))-VALUE(LEFT(F24,4)))*12+(VALUE(MID(TEXT(K24,"00000000"),5,2))-VALUE(MID(F24,5,2))),"") | AC24: =IF(OR(L24="",NOT(ISNUMBER(L24))),0,MAX(0,MIN(60,(VALUE(LEFT(F24,4))-VALUE(LEFT(TEXT(L24,"00000000"),4)))*12+(VALUE(MID(F24,5,2))-VALUE(MID(TEXT(L24,"00000000"),5,2)))))) | AD24: =IF(OR(L24="",NOT(ISNUMBER(L24))),0,IF(VALUE(F24)<VALUE(LEFT(TEXT(L24,"00000000"),6)),1,0)) | AE24: =IF(OR(M24="",NOT(ISNUMBER(M24))),0,IF(VALUE(F24)<VALUE(LEFT(TEXT(M24,"00000000"),6)),1,0)) | AF24: =IF(AND(AD24=0,AE24=0),1,0) | AG24: =IF(ISNUMBER(X24),X24,IFERROR(VALUE(LEFT(TEXT(J24,"00000000"),4)),"")) | AH24: =IFERROR(XLOOKUP(AG24,Vintage_Rates!$A$2:$A$1000,Vintage_Rates!$B$2:$B$1000,""),"") | AI24: =IF(ISNUMBER(Y24),Y24,IFERROR((G24-AH24)*100,"")) | AJ24: =IF(ISNUMBER(V24),V24,IFERROR(XLOOKUP(VALUE(F24),PLC_Rates!$A$2:$A$1000,PLC_Rates!$B$2:$B$1000,""),"")) | AK24: =IF(ISNUMBER(Z24),Z24,IF(AE24=0,0,MAX(0,MIN(10,((VALUE(LEFT(TEXT(M24,"00000000"),4))-VALUE(LEFT(F24,4)))*12+(VALUE(MID(TEXT(M24,"00000000"),5,2))-VALUE(MID(F24,5,2))))/12)))) | AL24: =IFERROR(G24*100-AJ24,"") | AM24: =IFERROR(G24*100-(AJ24+(1+AK24)*12.5),"") | AN24: =IFERROR(MIN(H24/1000000,100),"") | AO24: =IFERROR(INDEX(FHA_Lookup!$B$2:$B$11,MATCH(TRUE,ISNUMBER(SEARCH(FHA_Lookup!$A$2:$A$11,UPPER(SUBSTITUTE(O24," ","")))),0)),"OTHER") | AP24: =IFERROR(INDEX(FHA_Lookup!$C$2:$C$11,MATCH(TRUE,ISNUMBER(SEARCH(FHA_Lookup!$A$2:$A$11,UPPER(SUBSTITUTE(O24," ","")))),0)),"OTHER") | AQ24: =IF(AP24="NC",1,0) | AR24: =IF(UPPER(TRIM(P24))="AFF",1,0) | AS24: =IF(UPPER(TRIM(P24))="BAF",1,0) | AT24: =IF(UPPER(TRIM(P24))="MKT",1,0) | AU24: =IF(AO24="221d4",1,0) | AV24: =IF(AO24="223a7",1,0) | AW24: =IF(AO24="232",1,0) | AX24: =IF(AO24="538",1,0) | AY24: =IF(AO24="241",1,0) | AZ24: =IF(AO24="220",1,0) | BA24: =IF(AO24="OTHER",1,0) | BB24: =IF(UPPER(TRIM(C24))="LM",1,0) | BC24: =IF(UPPER(TRIM(C24))="PN",1,0) | BD24: =IF(UPPER(TRIM(C24))="LS",1,0) | BE24: =IF(UPPER(TRIM(C24))="RX",1,0) | BF24: =IFERROR((Parameters!$C$6*AM24+Parameters!$C$7*MAX(AM24-(-150),0)+Parameters!$C$8*MAX(AM24-(-50),0)+Parameters!$C$9*MAX(AM24-(0),0)+Parameters!$C$10*MAX(AM24-(50),0)+Parameters!$C$11*MAX(AM24-(100),0)+Parameters!$C$12*MAX(AM24-(150),0)+Parameters!$C$13*MAX(AM24-(250),0)),0) | BG24: =IFERROR((Parameters!$C$14*AA24+Parameters!$C$15*MAX(AA24-(12),0)+Parameters!$C$16*MAX(AA24-(36),0)+Parameters!$C$17*MAX(AA24-(60),0)+Parameters!$C$18*MAX(AA24-(84),0)+Parameters!$C$19*MAX(AA24-(120),0)+Parameters!$C$20*MAX(AA24-(180),0)),0) | BH24: =IFERROR((Parameters!$C$21*AK24+Parameters!$C$22*MAX(AK24-(0),0)+Parameters!$C$23*MAX(AK24-(2),0)+Parameters!$C$24*MAX(AK24-(5),0)+Parameters!$C$25*MAX(AK24-(8),0)),0) | BI24: =IFERROR((Parameters!$C$26*AI24+Parameters!$C$27*MAX(AI24-(-100),0)+Parameters!$C$28*MAX(AI24-(-25),0)+Parameters!$C$29*MAX(AI24-(25),0)+Parameters!$C$30*MAX(AI24-(100),0)),0) | BJ24: =IFERROR((Parameters!$C$31*AN24+Parameters!$C$32*MAX(AN24-(2),0)+Parameters!$C$33*MAX(AN24-(10),0)+Parameters!$C$34*MAX(AN24-(25),0)),0) | BK24: =IFERROR((Parameters!$C$35*AB24+Parameters!$C$36*MAX(AB24-(12),0)+Parameters!$C$37*MAX(AB24-(24),0)+Parameters!$C$38*MAX(AB24-(60),0)),0) | BL24: =IFERROR((Parameters!$C$39*AC24+Parameters!$C$40*MAX(AC24-(6),0)+Parameters!$C$41*MAX(AC24-(12),0)+Parameters!$C$42*MAX(AC24-(24),0)),0) | BM24: =IFERROR(Parameters!$C$43*(MAX(AM24,0)*MIN(MAX(AK24,0),10))/100,0) | BN24: =Parameters!$C$44*AE24 | BO24: =Parameters!$C$45*AU24 + Parameters!$C$46*AV24 + Parameters!$C$47*AW24 + Parameters!$C$48*AX24 + Parameters!$C$49*AY24 + Parameters!$C$50*AZ24 + Parameters!$C$51*BA24 | BP24: =Parameters!$C$52*AQ24 | BQ24: =Parameters!$C$53*AR24+Parameters!$C$54*AS24+Parameters!$C$55*AT24 | BR24: =Parameters!$C$56*BB24+Parameters!$C$57*BC24+Parameters!$C$58*BD24+Parameters!$C$59*BE24 | BS24: =Parameters!$B$2 | BT24: =BS24+BF24 + BG24 + BH24 + BI24 + BJ24 + BK24 + BL24 + BM24 + BN24 + BO24 + BP24 + BQ24 + BR24 | BU24: =IF(AD24=1,0,1/(1+EXP(-BT24))*Parameters!$B$3) | BV24: =(1-(1-BU24)^12)*100 | BW24: =IF(AD24=1,0,(1-(1-1/(1+EXP(-Parameters!$B$2)))^12)*100) | BX24: =IF(AD24=1,0,BV24-(1-(1-(1/(1+EXP(-(BT24-BF24)))*Parameters!$B$3))^12)*100) | BY24: =IF(AD24=1,0,BV24-(1-(1-(1/(1+EXP(-(BT24-BG24)))*Parameters!$B$3))^12)*100) | BZ24: =IF(AD24=1,0,BV24-(1-(1-(1/(1+EXP(-(BT24-BH24)))*Parameters!$B$3))^12)*100) | CA24: =IF(AD24=1,0,BV24-(1-(1-(1/(1+EXP(-(BT24-BI24)))*Parameters!$B$3))^12)*100) | CB24: =IF(AD24=1,0,BV24-(1-(1-(1/(1+EXP(-(BT24-BJ24)))*Parameters!$B$3))^12)*100) | CC24: =IF(AD24=1,0,BV24-(1-(1-(1/(1+EXP(-(BT24-BK24)))*Parameters!$B$3))^12)*100) | CD24: =IF(AD24=1,0,BV24-(1-(1-(1/(1+EXP(-(BT24-BL24)))*Parameters!$B$3))^12)*100) | CE24: =IF(AD24=1,0,BV24-(1-(1-(1/(1+EXP(-(BT24-BM24)))*Parameters!$B$3))^12)*100) | CF24: =IF(AD24=1,0,BV24-(1-(1-(1/(1+EXP(-(BT24-BN24)))*Parameters!$B$3))^12)*100) | CG24: =IF(AD24=1,0,BV24-(1-(1-(1/(1+EXP(-(BT24-BO24)))*Parameters!$B$3))^12)*100) | CH24: =IF(AD24=1,0,BV24-(1-(1-(1/(1+EXP(-(BT24-BP24)))*Parameters!$B$3))^12)*100) | CI24: =IF(AD24=1,0,BV24-(1-(1-(1/(1+EXP(-(BT24-BQ24)))*Parameters!$B$3))^12)*100) | CJ24: =IF(AD24=1,0,BV24-(1-(1-(1/(1+EXP(-(BT24-BR24)))*Parameters!$B$3))^12)*100)
A25: GNR_2024_NEW | B25: 3617FTER5 | C25: PN | D25: KEYBANK NATIONAL ASSOCIATION | E25: 3617FTER5_000000007322353 | F25: 202603 | G25: 5.49 | H25: 13529928 | I25: 420 | J25: 20230501 | K25: 20580601 | M25: 20330630 | N25: 10 | O25: 232/223(F) | P25: MKT | T25: IN | U25: 51 | V25: 490.5 | W25: 34 | X25: 2023 | Y25: -9.5 | Z25: 8 | AA25: =IF(ISNUMBER(W25),W25,IFERROR(MAX(0,(VALUE(LEFT(F25,4))-VALUE(LEFT(TEXT(J25,"00000000"),4)))*12+(VALUE(MID(F25,5,2))-VALUE(MID(TEXT(J25,"00000000"),5,2)))),"")) | AB25: =IFERROR((VALUE(LEFT(TEXT(K25,"00000000"),4))-VALUE(LEFT(F25,4)))*12+(VALUE(MID(TEXT(K25,"00000000"),5,2))-VALUE(MID(F25,5,2))),"") | AC25: =IF(OR(L25="",NOT(ISNUMBER(L25))),0,MAX(0,MIN(60,(VALUE(LEFT(F25,4))-VALUE(LEFT(TEXT(L25,"00000000"),4)))*12+(VALUE(MID(F25,5,2))-VALUE(MID(TEXT(L25,"00000000"),5,2)))))) | AD25: =IF(OR(L25="",NOT(ISNUMBER(L25))),0,IF(VALUE(F25)<VALUE(LEFT(TEXT(L25,"00000000"),6)),1,0)) | AE25: =IF(OR(M25="",NOT(ISNUMBER(M25))),0,IF(VALUE(F25)<VALUE(LEFT(TEXT(M25,"00000000"),6)),1,0)) | AF25: =IF(AND(AD25=0,AE25=0),1,0) | AG25: =IF(ISNUMBER(X25),X25,IFERROR(VALUE(LEFT(TEXT(J25,"00000000"),4)),"")) | AH25: =IFERROR(XLOOKUP(AG25,Vintage_Rates!$A$2:$A$1000,Vintage_Rates!$B$2:$B$1000,""),"") | AI25: =IF(ISNUMBER(Y25),Y25,IFERROR((G25-AH25)*100,"")) | AJ25: =IF(ISNUMBER(V25),V25,IFERROR(XLOOKUP(VALUE(F25),PLC_Rates!$A$2:$A$1000,PLC_Rates!$B$2:$B$1000,""),"")) | AK25: =IF(ISNUMBER(Z25),Z25,IF(AE25=0,0,MAX(0,MIN(10,((VALUE(LEFT(TEXT(M25,"00000000"),4))-VALUE(LEFT(F25,4)))*12+(VALUE(MID(TEXT(M25,"00000000"),5,2))-VALUE(MID(F25,5,2))))/12)))) | AL25: =IFERROR(G25*100-AJ25,"") | AM25: =IFERROR(G25*100-(AJ25+(1+AK25)*12.5),"") | AN25: =IFERROR(MIN(H25/1000000,100),"") | AO25: =IFERROR(INDEX(FHA_Lookup!$B$2:$B$11,MATCH(TRUE,ISNUMBER(SEARCH(FHA_Lookup!$A$2:$A$11,UPPER(SUBSTITUTE(O25," ","")))),0)),"OTHER") | AP25: =IFERROR(INDEX(FHA_Lookup!$C$2:$C$11,MATCH(TRUE,ISNUMBER(SEARCH(FHA_Lookup!$A$2:$A$11,UPPER(SUBSTITUTE(O25," ","")))),0)),"OTHER") | AQ25: =IF(AP25="NC",1,0) | AR25: =IF(UPPER(TRIM(P25))="AFF",1,0) | AS25: =IF(UPPER(TRIM(P25))="BAF",1,0) | AT25: =IF(UPPER(TRIM(P25))="MKT",1,0) | AU25: =IF(AO25="221d4",1,0) | AV25: =IF(AO25="223a7",1,0) | AW25: =IF(AO25="232",1,0) | AX25: =IF(AO25="538",1,0) | AY25: =IF(AO25="241",1,0) | AZ25: =IF(AO25="220",1,0) | BA25: =IF(AO25="OTHER",1,0) | BB25: =IF(UPPER(TRIM(C25))="LM",1,0) | BC25: =IF(UPPER(TRIM(C25))="PN",1,0) | BD25: =IF(UPPER(TRIM(C25))="LS",1,0) | BE25: =IF(UPPER(TRIM(C25))="RX",1,0) | BF25: =IFERROR((Parameters!$C$6*AM25+Parameters!$C$7*MAX(AM25-(-150),0)+Parameters!$C$8*MAX(AM25-(-50),0)+Parameters!$C$9*MAX(AM25-(0),0)+Parameters!$C$10*MAX(AM25-(50),0)+Parameters!$C$11*MAX(AM25-(100),0)+Parameters!$C$12*MAX(AM25-(150),0)+Parameters!$C$13*MAX(AM25-(250),0)),0) | BG25: =IFERROR((Parameters!$C$14*AA25+Parameters!$C$15*MAX(AA25-(12),0)+Parameters!$C$16*MAX(AA25-(36),0)+Parameters!$C$17*MAX(AA25-(60),0)+Parameters!$C$18*MAX(AA25-(84),0)+Parameters!$C$19*MAX(AA25-(120),0)+Parameters!$C$20*MAX(AA25-(180),0)),0) | BH25: =IFERROR((Parameters!$C$21*AK25+Parameters!$C$22*MAX(AK25-(0),0)+Parameters!$C$23*MAX(AK25-(2),0)+Parameters!$C$24*MAX(AK25-(5),0)+Parameters!$C$25*MAX(AK25-(8),0)),0) | BI25: =IFERROR((Parameters!$C$26*AI25+Parameters!$C$27*MAX(AI25-(-100),0)+Parameters!$C$28*MAX(AI25-(-25),0)+Parameters!$C$29*MAX(AI25-(25),0)+Parameters!$C$30*MAX(AI25-(100),0)),0) | BJ25: =IFERROR((Parameters!$C$31*AN25+Parameters!$C$32*MAX(AN25-(2),0)+Parameters!$C$33*MAX(AN25-(10),0)+Parameters!$C$34*MAX(AN25-(25),0)),0) | BK25: =IFERROR((Parameters!$C$35*AB25+Parameters!$C$36*MAX(AB25-(12),0)+Parameters!$C$37*MAX(AB25-(24),0)+Parameters!$C$38*MAX(AB25-(60),0)),0) | BL25: =IFERROR((Parameters!$C$39*AC25+Parameters!$C$40*MAX(AC25-(6),0)+Parameters!$C$41*MAX(AC25-(12),0)+Parameters!$C$42*MAX(AC25-(24),0)),0) | BM25: =IFERROR(Parameters!$C$43*(MAX(AM25,0)*MIN(MAX(AK25,0),10))/100,0) | BN25: =Parameters!$C$44*AE25 | BO25: =Parameters!$C$45*AU25 + Parameters!$C$46*AV25 + Parameters!$C$47*AW25 + Parameters!$C$48*AX25 + Parameters!$C$49*AY25 + Parameters!$C$50*AZ25 + Parameters!$C$51*BA25 | BP25: =Parameters!$C$52*AQ25 | BQ25: =Parameters!$C$53*AR25+Parameters!$C$54*AS25+Parameters!$C$55*AT25 | BR25: =Parameters!$C$56*BB25+Parameters!$C$57*BC25+Parameters!$C$58*BD25+Parameters!$C$59*BE25 | BS25: =Parameters!$B$2 | BT25: =BS25+BF25 + BG25 + BH25 + BI25 + BJ25 + BK25 + BL25 + BM25 + BN25 + BO25 + BP25 + BQ25 + BR25 | BU25: =IF(AD25=1,0,1/(1+EXP(-BT25))*Parameters!$B$3) | BV25: =(1-(1-BU25)^12)*100 | BW25: =IF(AD25=1,0,(1-(1-1/(1+EXP(-Parameters!$B$2)))^12)*100) | BX25: =IF(AD25=1,0,BV25-(1-(1-(1/(1+EXP(-(BT25-BF25)))*Parameters!$B$3))^12)*100) | BY25: =IF(AD25=1,0,BV25-(1-(1-(1/(1+EXP(-(BT25-BG25)))*Parameters!$B$3))^12)*100) | BZ25: =IF(AD25=1,0,BV25-(1-(1-(1/(1+EXP(-(BT25-BH25)))*Parameters!$B$3))^12)*100) | CA25: =IF(AD25=1,0,BV25-(1-(1-(1/(1+EXP(-(BT25-BI25)))*Parameters!$B$3))^12)*100) | CB25: =IF(AD25=1,0,BV25-(1-(1-(1/(1+EXP(-(BT25-BJ25)))*Parameters!$B$3))^12)*100) | CC25: =IF(AD25=1,0,BV25-(1-(1-(1/(1+EXP(-(BT25-BK25)))*Parameters!$B$3))^12)*100) | CD25: =IF(AD25=1,0,BV25-(1-(1-(1/(1+EXP(-(BT25-BL25)))*Parameters!$B$3))^12)*100) | CE25: =IF(AD25=1,0,BV25-(1-(1-(1/(1+EXP(-(BT25-BM25)))*Parameters!$B$3))^12)*100) | CF25: =IF(AD25=1,0,BV25-(1-(1-(1/(1+EXP(-(BT25-BN25)))*Parameters!$B$3))^12)*100) | CG25: =IF(AD25=1,0,BV25-(1-(1-(1/(1+EXP(-(BT25-BO25)))*Parameters!$B$3))^12)*100) | CH25: =IF(AD25=1,0,BV25-(1-(1-(1/(1+EXP(-(BT25-BP25)))*Parameters!$B$3))^12)*100) | CI25: =IF(AD25=1,0,BV25-(1-(1-(1/(1+EXP(-(BT25-BQ25)))*Parameters!$B$3))^12)*100) | CJ25: =IF(AD25=1,0,BV25-(1-(1-(1/(1+EXP(-(BT25-BR25)))*Parameters!$B$3))^12)*100)
A26: GNR_2024_NEW | B26: 3618KU4F1 | C26: PN | D26: DWIGHT CAPITAL LLC | E26: 3618KU4F1_000000008322130 | F26: 202603 | G26: 6.28 | H26: 13040678 | I26: 420 | J26: 20250501 | K26: 20600601 | M26: 20350701 | N26: 10 | O26: 232/223(F) | T26: KY | U26: 117 | V26: 490.5 | W26: 10 | X26: 2025 | Y26: 46 | Z26: 0 | AA26: =IF(ISNUMBER(W26),W26,IFERROR(MAX(0,(VALUE(LEFT(F26,4))-VALUE(LEFT(TEXT(J26,"00000000"),4)))*12+(VALUE(MID(F26,5,2))-VALUE(MID(TEXT(J26,"00000000"),5,2)))),"")) | AB26: =IFERROR((VALUE(LEFT(TEXT(K26,"00000000"),4))-VALUE(LEFT(F26,4)))*12+(VALUE(MID(TEXT(K26,"00000000"),5,2))-VALUE(MID(F26,5,2))),"") | AC26: =IF(OR(L26="",NOT(ISNUMBER(L26))),0,MAX(0,MIN(60,(VALUE(LEFT(F26,4))-VALUE(LEFT(TEXT(L26,"00000000"),4)))*12+(VALUE(MID(F26,5,2))-VALUE(MID(TEXT(L26,"00000000"),5,2)))))) | AD26: =IF(OR(L26="",NOT(ISNUMBER(L26))),0,IF(VALUE(F26)<VALUE(LEFT(TEXT(L26,"00000000"),6)),1,0)) | AE26: =IF(OR(M26="",NOT(ISNUMBER(M26))),0,IF(VALUE(F26)<VALUE(LEFT(TEXT(M26,"00000000"),6)),1,0)) | AF26: =IF(AND(AD26=0,AE26=0),1,0) | AG26: =IF(ISNUMBER(X26),X26,IFERROR(VALUE(LEFT(TEXT(J26,"00000000"),4)),"")) | AH26: =IFERROR(XLOOKUP(AG26,Vintage_Rates!$A$2:$A$1000,Vintage_Rates!$B$2:$B$1000,""),"") | AI26: =IF(ISNUMBER(Y26),Y26,IFERROR((G26-AH26)*100,"")) | AJ26: =IF(ISNUMBER(V26),V26,IFERROR(XLOOKUP(VALUE(F26),PLC_Rates!$A$2:$A$1000,PLC_Rates!$B$2:$B$1000,""),"")) | AK26: =IF(ISNUMBER(Z26),Z26,IF(AE26=0,0,MAX(0,MIN(10,((VALUE(LEFT(TEXT(M26,"00000000"),4))-VALUE(LEFT(F26,4)))*12+(VALUE(MID(TEXT(M26,"00000000"),5,2))-VALUE(MID(F26,5,2))))/12)))) | AL26: =IFERROR(G26*100-AJ26,"") | AM26: =IFERROR(G26*100-(AJ26+(1+AK26)*12.5),"") | AN26: =IFERROR(MIN(H26/1000000,100),"") | AO26: =IFERROR(INDEX(FHA_Lookup!$B$2:$B$11,MATCH(TRUE,ISNUMBER(SEARCH(FHA_Lookup!$A$2:$A$11,UPPER(SUBSTITUTE(O26," ","")))),0)),"OTHER") | AP26: =IFERROR(INDEX(FHA_Lookup!$C$2:$C$11,MATCH(TRUE,ISNUMBER(SEARCH(FHA_Lookup!$A$2:$A$11,UPPER(SUBSTITUTE(O26," ","")))),0)),"OTHER") | AQ26: =IF(AP26="NC",1,0) | AR26: =IF(UPPER(TRIM(P26))="AFF",1,0) | AS26: =IF(UPPER(TRIM(P26))="BAF",1,0) | AT26: =IF(UPPER(TRIM(P26))="MKT",1,0) | AU26: =IF(AO26="221d4",1,0) | AV26: =IF(AO26="223a7",1,0) | AW26: =IF(AO26="232",1,0) | AX26: =IF(AO26="538",1,0) | AY26: =IF(AO26="241",1,0) | AZ26: =IF(AO26="220",1,0) | BA26: =IF(AO26="OTHER",1,0) | BB26: =IF(UPPER(TRIM(C26))="LM",1,0) | BC26: =IF(UPPER(TRIM(C26))="PN",1,0) | BD26: =IF(UPPER(TRIM(C26))="LS",1,0) | BE26: =IF(UPPER(TRIM(C26))="RX",1,0) | BF26: =IFERROR((Parameters!$C$6*AM26+Parameters!$C$7*MAX(AM26-(-150),0)+Parameters!$C$8*MAX(AM26-(-50),0)+Parameters!$C$9*MAX(AM26-(0),0)+Parameters!$C$10*MAX(AM26-(50),0)+Parameters!$C$11*MAX(AM26-(100),0)+Parameters!$C$12*MAX(AM26-(150),0)+Parameters!$C$13*MAX(AM26-(250),0)),0) | BG26: =IFERROR((Parameters!$C$14*AA26+Parameters!$C$15*MAX(AA26-(12),0)+Parameters!$C$16*MAX(AA26-(36),0)+Parameters!$C$17*MAX(AA26-(60),0)+Parameters!$C$18*MAX(AA26-(84),0)+Parameters!$C$19*MAX(AA26-(120),0)+Parameters!$C$20*MAX(AA26-(180),0)),0) | BH26: =IFERROR((Parameters!$C$21*AK26+Parameters!$C$22*MAX(AK26-(0),0)+Parameters!$C$23*MAX(AK26-(2),0)+Parameters!$C$24*MAX(AK26-(5),0)+Parameters!$C$25*MAX(AK26-(8),0)),0) | BI26: =IFERROR((Parameters!$C$26*AI26+Parameters!$C$27*MAX(AI26-(-100),0)+Parameters!$C$28*MAX(AI26-(-25),0)+Parameters!$C$29*MAX(AI26-(25),0)+Parameters!$C$30*MAX(AI26-(100),0)),0) | BJ26: =IFERROR((Parameters!$C$31*AN26+Parameters!$C$32*MAX(AN26-(2),0)+Parameters!$C$33*MAX(AN26-(10),0)+Parameters!$C$34*MAX(AN26-(25),0)),0) | BK26: =IFERROR((Parameters!$C$35*AB26+Parameters!$C$36*MAX(AB26-(12),0)+Parameters!$C$37*MAX(AB26-(24),0)+Parameters!$C$38*MAX(AB26-(60),0)),0) | BL26: =IFERROR((Parameters!$C$39*AC26+Parameters!$C$40*MAX(AC26-(6),0)+Parameters!$C$41*MAX(AC26-(12),0)+Parameters!$C$42*MAX(AC26-(24),0)),0) | BM26: =IFERROR(Parameters!$C$43*(MAX(AM26,0)*MIN(MAX(AK26,0),10))/100,0) | BN26: =Parameters!$C$44*AE26 | BO26: =Parameters!$C$45*AU26 + Parameters!$C$46*AV26 + Parameters!$C$47*AW26 + Parameters!$C$48*AX26 + Parameters!$C$49*AY26 + Parameters!$C$50*AZ26 + Parameters!$C$51*BA26 | BP26: =Parameters!$C$52*AQ26 | BQ26: =Parameters!$C$53*AR26+Parameters!$C$54*AS26+Parameters!$C$55*AT26 | BR26: =Parameters!$C$56*BB26+Parameters!$C$57*BC26+Parameters!$C$58*BD26+Parameters!$C$59*BE26 | BS26: =Parameters!$B$2 | BT26: =BS26+BF26 + BG26 + BH26 + BI26 + BJ26 + BK26 + BL26 + BM26 + BN26 + BO26 + BP26 + BQ26 + BR26 | BU26: =IF(AD26=1,0,1/(1+EXP(-BT26))*Parameters!$B$3) | BV26: =(1-(1-BU26)^12)*100 | BW26: =IF(AD26=1,0,(1-(1-1/(1+EXP(-Parameters!$B$2)))^12)*100) | BX26: =IF(AD26=1,0,BV26-(1-(1-(1/(1+EXP(-(BT26-BF26)))*Parameters!$B$3))^12)*100) | BY26: =IF(AD26=1,0,BV26-(1-(1-(1/(1+EXP(-(BT26-BG26)))*Parameters!$B$3))^12)*100) | BZ26: =IF(AD26=1,0,BV26-(1-(1-(1/(1+EXP(-(BT26-BH26)))*Parameters!$B$3))^12)*100) | CA26: =IF(AD26=1,0,BV26-(1-(1-(1/(1+EXP(-(BT26-BI26)))*Parameters!$B$3))^12)*100) | CB26: =IF(AD26=1,0,BV26-(1-(1-(1/(1+EXP(-(BT26-BJ26)))*Parameters!$B$3))^12)*100) | CC26: =IF(AD26=1,0,BV26-(1-(1-(1/(1+EXP(-(BT26-BK26)))*Parameters!$B$3))^12)*100) | CD26: =IF(AD26=1,0,BV26-(1-(1-(1/(1+EXP(-(BT26-BL26)))*Parameters!$B$3))^12)*100) | CE26: =IF(AD26=1,0,BV26-(1-(1-(1/(1+EXP(-(BT26-BM26)))*Parameters!$B$3))^12)*100) | CF26: =IF(AD26=1,0,BV26-(1-(1-(1/(1+EXP(-(BT26-BN26)))*Parameters!$B$3))^12)*100) | CG26: =IF(AD26=1,0,BV26-(1-(1-(1/(1+EXP(-(BT26-BO26)))*Parameters!$B$3))^12)*100) | CH26: =IF(AD26=1,0,BV26-(1-(1-(1/(1+EXP(-(BT26-BP26)))*Parameters!$B$3))^12)*100) | CI26: =IF(AD26=1,0,BV26-(1-(1-(1/(1+EXP(-(BT26-BQ26)))*Parameters!$B$3))^12)*100) | CJ26: =IF(AD26=1,0,BV26-(1-(1-(1/(1+EXP(-(BT26-BR26)))*Parameters!$B$3))^12)*100)
A27: GNR_2024_NEW | B27: 3617FTDU9 | C27: PN | D27: LUMENT REAL ESTATE CAPITAL,LLC | E27: 3617FTDU9_000000012911131 | F27: 202603 | G27: 4.8 | H27: 18335699 | I27: 420 | J27: 20230401 | K27: 20580501 | M27: 20330601 | N27: 10 | O27: 207/223(F) | P27: MKT | T27: CA | U27: 172 | V27: 490.5 | W27: 35 | X27: 2023 | Y27: -78.5 | Z27: 8 | AA27: =IF(ISNUMBER(W27),W27,IFERROR(MAX(0,(VALUE(LEFT(F27,4))-VALUE(LEFT(TEXT(J27,"00000000"),4)))*12+(VALUE(MID(F27,5,2))-VALUE(MID(TEXT(J27,"00000000"),5,2)))),"")) | AB27: =IFERROR((VALUE(LEFT(TEXT(K27,"00000000"),4))-VALUE(LEFT(F27,4)))*12+(VALUE(MID(TEXT(K27,"00000000"),5,2))-VALUE(MID(F27,5,2))),"") | AC27: =IF(OR(L27="",NOT(ISNUMBER(L27))),0,MAX(0,MIN(60,(VALUE(LEFT(F27,4))-VALUE(LEFT(TEXT(L27,"00000000"),4)))*12+(VALUE(MID(F27,5,2))-VALUE(MID(TEXT(L27,"00000000"),5,2)))))) | AD27: =IF(OR(L27="",NOT(ISNUMBER(L27))),0,IF(VALUE(F27)<VALUE(LEFT(TEXT(L27,"00000000"),6)),1,0)) | AE27: =IF(OR(M27="",NOT(ISNUMBER(M27))),0,IF(VALUE(F27)<VALUE(LEFT(TEXT(M27,"00000000"),6)),1,0)) | AF27: =IF(AND(AD27=0,AE27=0),1,0) | AG27: =IF(ISNUMBER(X27),X27,IFERROR(VALUE(LEFT(TEXT(J27,"00000000"),4)),"")) | AH27: =IFERROR(XLOOKUP(AG27,Vintage_Rates!$A$2:$A$1000,Vintage_Rates!$B$2:$B$1000,""),"") | AI27: =IF(ISNUMBER(Y27),Y27,IFERROR((G27-AH27)*100,"")) | AJ27: =IF(ISNUMBER(V27),V27,IFERROR(XLOOKUP(VALUE(F27),PLC_Rates!$A$2:$A$1000,PLC_Rates!$B$2:$B$1000,""),"")) | AK27: =IF(ISNUMBER(Z27),Z27,IF(AE27=0,0,MAX(0,MIN(10,((VALUE(LEFT(TEXT(M27,"00000000"),4))-VALUE(LEFT(F27,4)))*12+(VALUE(MID(TEXT(M27,"00000000"),5,2))-VALUE(MID(F27,5,2))))/12)))) | AL27: =IFERROR(G27*100-AJ27,"") | AM27: =IFERROR(G27*100-(AJ27+(1+AK27)*12.5),"") | AN27: =IFERROR(MIN(H27/1000000,100),"") | AO27: =IFERROR(INDEX(FHA_Lookup!$B$2:$B$11,MATCH(TRUE,ISNUMBER(SEARCH(FHA_Lookup!$A$2:$A$11,UPPER(SUBSTITUTE(O27," ","")))),0)),"OTHER") | AP27: =IFERROR(INDEX(FHA_Lookup!$C$2:$C$11,MATCH(TRUE,ISNUMBER(SEARCH(FHA_Lookup!$A$2:$A$11,UPPER(SUBSTITUTE(O27," ","")))),0)),"OTHER") | AQ27: =IF(AP27="NC",1,0) | AR27: =IF(UPPER(TRIM(P27))="AFF",1,0) | AS27: =IF(UPPER(TRIM(P27))="BAF",1,0) | AT27: =IF(UPPER(TRIM(P27))="MKT",1,0) | AU27: =IF(AO27="221d4",1,0) | AV27: =IF(AO27="223a7",1,0) | AW27: =IF(AO27="232",1,0) | AX27: =IF(AO27="538",1,0) | AY27: =IF(AO27="241",1,0) | AZ27: =IF(AO27="220",1,0) | BA27: =IF(AO27="OTHER",1,0) | BB27: =IF(UPPER(TRIM(C27))="LM",1,0) | BC27: =IF(UPPER(TRIM(C27))="PN",1,0) | BD27: =IF(UPPER(TRIM(C27))="LS",1,0) | BE27: =IF(UPPER(TRIM(C27))="RX",1,0) | BF27: =IFERROR((Parameters!$C$6*AM27+Parameters!$C$7*MAX(AM27-(-150),0)+Parameters!$C$8*MAX(AM27-(-50),0)+Parameters!$C$9*MAX(AM27-(0),0)+Parameters!$C$10*MAX(AM27-(50),0)+Parameters!$C$11*MAX(AM27-(100),0)+Parameters!$C$12*MAX(AM27-(150),0)+Parameters!$C$13*MAX(AM27-(250),0)),0) | BG27: =IFERROR((Parameters!$C$14*AA27+Parameters!$C$15*MAX(AA27-(12),0)+Parameters!$C$16*MAX(AA27-(36),0)+Parameters!$C$17*MAX(AA27-(60),0)+Parameters!$C$18*MAX(AA27-(84),0)+Parameters!$C$19*MAX(AA27-(120),0)+Parameters!$C$20*MAX(AA27-(180),0)),0) | BH27: =IFERROR((Parameters!$C$21*AK27+Parameters!$C$22*MAX(AK27-(0),0)+Parameters!$C$23*MAX(AK27-(2),0)+Parameters!$C$24*MAX(AK27-(5),0)+Parameters!$C$25*MAX(AK27-(8),0)),0) | BI27: =IFERROR((Parameters!$C$26*AI27+Parameters!$C$27*MAX(AI27-(-100),0)+Parameters!$C$28*MAX(AI27-(-25),0)+Parameters!$C$29*MAX(AI27-(25),0)+Parameters!$C$30*MAX(AI27-(100),0)),0) | BJ27: =IFERROR((Parameters!$C$31*AN27+Parameters!$C$32*MAX(AN27-(2),0)+Parameters!$C$33*MAX(AN27-(10),0)+Parameters!$C$34*MAX(AN27-(25),0)),0) | BK27: =IFERROR((Parameters!$C$35*AB27+Parameters!$C$36*MAX(AB27-(12),0)+Parameters!$C$37*MAX(AB27-(24),0)+Parameters!$C$38*MAX(AB27-(60),0)),0) | BL27: =IFERROR((Parameters!$C$39*AC27+Parameters!$C$40*MAX(AC27-(6),0)+Parameters!$C$41*MAX(AC27-(12),0)+Parameters!$C$42*MAX(AC27-(24),0)),0) | BM27: =IFERROR(Parameters!$C$43*(MAX(AM27,0)*MIN(MAX(AK27,0),10))/100,0) | BN27: =Parameters!$C$44*AE27 | BO27: =Parameters!$C$45*AU27 + Parameters!$C$46*AV27 + Parameters!$C$47*AW27 + Parameters!$C$48*AX27 + Parameters!$C$49*AY27 + Parameters!$C$50*AZ27 + Parameters!$C$51*BA27 | BP27: =Parameters!$C$52*AQ27 | BQ27: =Parameters!$C$53*AR27+Parameters!$C$54*AS27+Parameters!$C$55*AT27 | BR27: =Parameters!$C$56*BB27+Parameters!$C$57*BC27+Parameters!$C$58*BD27+Parameters!$C$59*BE27 | BS27: =Parameters!$B$2 | BT27: =BS27+BF27 + BG27 + BH27 + BI27 + BJ27 + BK27 + BL27 + BM27 + BN27 + BO27 + BP27 + BQ27 + BR27 | BU27: =IF(AD27=1,0,1/(1+EXP(-BT27))*Parameters!$B$3) | BV27: =(1-(1-BU27)^12)*100 | BW27: =IF(AD27=1,0,(1-(1-1/(1+EXP(-Parameters!$B$2)))^12)*100) | BX27: =IF(AD27=1,0,BV27-(1-(1-(1/(1+EXP(-(BT27-BF27)))*Parameters!$B$3))^12)*100) | BY27: =IF(AD27=1,0,BV27-(1-(1-(1/(1+EXP(-(BT27-BG27)))*Parameters!$B$3))^12)*100) | BZ27: =IF(AD27=1,0,BV27-(1-(1-(1/(1+EXP(-(BT27-BH27)))*Parameters!$B$3))^12)*100) | CA27: =IF(AD27=1,0,BV27-(1-(1-(1/(1+EXP(-(BT27-BI27)))*Parameters!$B$3))^12)*100) | CB27: =IF(AD27=1,0,BV27-(1-(1-(1/(1+EXP(-(BT27-BJ27)))*Parameters!$B$3))^12)*100) | CC27: =IF(AD27=1,0,BV27-(1-(1-(1/(1+EXP(-(BT27-BK27)))*Parameters!$B$3))^12)*100) | CD27: =IF(AD27=1,0,BV27-(1-(1-(1/(1+EXP(-(BT27-BL27)))*Parameters!$B$3))^12)*100) | CE27: =IF(AD27=1,0,BV27-(1-(1-(1/(1+EXP(-(BT27-BM27)))*Parameters!$B$3))^12)*100) | CF27: =IF(AD27=1,0,BV27-(1-(1-(1/(1+EXP(-(BT27-BN27)))*Parameters!$B$3))^12)*100) | CG27: =IF(AD27=1,0,BV27-(1-(1-(1/(1+EXP(-(BT27-BO27)))*Parameters!$B$3))^12)*100) | CH27: =IF(AD27=1,0,BV27-(1-(1-(1/(1+EXP(-(BT27-BP27)))*Parameters!$B$3))^12)*100) | CI27: =IF(AD27=1,0,BV27-(1-(1-(1/(1+EXP(-(BT27-BQ27)))*Parameters!$B$3))^12)*100) | CJ27: =IF(AD27=1,0,BV27-(1-(1-(1/(1+EXP(-(BT27-BR27)))*Parameters!$B$3))^12)*100)
A28: GNR_2024_NEW | B28: 3618JUCH0 | C28: PN | D28: MERCHANTS CAPITAL CORP. | E28: 3618JUCH0_000000005422114 | F28: 202603 | G28: 5.23 | H28: 20808291 | I28: 420 | J28: 20241001 | K28: 20591101 | M28: 20341201 | N28: 10 | O28: 232/223(F) | P28: MKT | T28: SC | U28: 68 | V28: 490.5 | W28: 17 | X28: 2024 | Y28: -55 | Z28: 9 | AA28: =IF(ISNUMBER(W28),W28,IFERROR(MAX(0,(VALUE(LEFT(F28,4))-VALUE(LEFT(TEXT(J28,"00000000"),4)))*12+(VALUE(MID(F28,5,2))-VALUE(MID(TEXT(J28,"00000000"),5,2)))),"")) | AB28: =IFERROR((VALUE(LEFT(TEXT(K28,"00000000"),4))-VALUE(LEFT(F28,4)))*12+(VALUE(MID(TEXT(K28,"00000000"),5,2))-VALUE(MID(F28,5,2))),"") | AC28: =IF(OR(L28="",NOT(ISNUMBER(L28))),0,MAX(0,MIN(60,(VALUE(LEFT(F28,4))-VALUE(LEFT(TEXT(L28,"00000000"),4)))*12+(VALUE(MID(F28,5,2))-VALUE(MID(TEXT(L28,"00000000"),5,2)))))) | AD28: =IF(OR(L28="",NOT(ISNUMBER(L28))),0,IF(VALUE(F28)<VALUE(LEFT(TEXT(L28,"00000000"),6)),1,0)) | AE28: =IF(OR(M28="",NOT(ISNUMBER(M28))),0,IF(VALUE(F28)<VALUE(LEFT(TEXT(M28,"00000000"),6)),1,0)) | AF28: =IF(AND(AD28=0,AE28=0),1,0) | AG28: =IF(ISNUMBER(X28),X28,IFERROR(VALUE(LEFT(TEXT(J28,"00000000"),4)),"")) | AH28: =IFERROR(XLOOKUP(AG28,Vintage_Rates!$A$2:$A$1000,Vintage_Rates!$B$2:$B$1000,""),"") | AI28: =IF(ISNUMBER(Y28),Y28,IFERROR((G28-AH28)*100,"")) | AJ28: =IF(ISNUMBER(V28),V28,IFERROR(XLOOKUP(VALUE(F28),PLC_Rates!$A$2:$A$1000,PLC_Rates!$B$2:$B$1000,""),"")) | AK28: =IF(ISNUMBER(Z28),Z28,IF(AE28=0,0,MAX(0,MIN(10,((VALUE(LEFT(TEXT(M28,"00000000"),4))-VALUE(LEFT(F28,4)))*12+(VALUE(MID(TEXT(M28,"00000000"),5,2))-VALUE(MID(F28,5,2))))/12)))) | AL28: =IFERROR(G28*100-AJ28,"") | AM28: =IFERROR(G28*100-(AJ28+(1+AK28)*12.5),"") | AN28: =IFERROR(MIN(H28/1000000,100),"") | AO28: =IFERROR(INDEX(FHA_Lookup!$B$2:$B$11,MATCH(TRUE,ISNUMBER(SEARCH(FHA_Lookup!$A$2:$A$11,UPPER(SUBSTITUTE(O28," ","")))),0)),"OTHER") | AP28: =IFERROR(INDEX(FHA_Lookup!$C$2:$C$11,MATCH(TRUE,ISNUMBER(SEARCH(FHA_Lookup!$A$2:$A$11,UPPER(SUBSTITUTE(O28," ","")))),0)),"OTHER") | AQ28: =IF(AP28="NC",1,0) | AR28: =IF(UPPER(TRIM(P28))="AFF",1,0) | AS28: =IF(UPPER(TRIM(P28))="BAF",1,0) | AT28: =IF(UPPER(TRIM(P28))="MKT",1,0) | AU28: =IF(AO28="221d4",1,0) | AV28: =IF(AO28="223a7",1,0) | AW28: =IF(AO28="232",1,0) | AX28: =IF(AO28="538",1,0) | AY28: =IF(AO28="241",1,0) | AZ28: =IF(AO28="220",1,0) | BA28: =IF(AO28="OTHER",1,0) | BB28: =IF(UPPER(TRIM(C28))="LM",1,0) | BC28: =IF(UPPER(TRIM(C28))="PN",1,0) | BD28: =IF(UPPER(TRIM(C28))="LS",1,0) | BE28: =IF(UPPER(TRIM(C28))="RX",1,0) | BF28: =IFERROR((Parameters!$C$6*AM28+Parameters!$C$7*MAX(AM28-(-150),0)+Parameters!$C$8*MAX(AM28-(-50),0)+Parameters!$C$9*MAX(AM28-(0),0)+Parameters!$C$10*MAX(AM28-(50),0)+Parameters!$C$11*MAX(AM28-(100),0)+Parameters!$C$12*MAX(AM28-(150),0)+Parameters!$C$13*MAX(AM28-(250),0)),0) | BG28: =IFERROR((Parameters!$C$14*AA28+Parameters!$C$15*MAX(AA28-(12),0)+Parameters!$C$16*MAX(AA28-(36),0)+Parameters!$C$17*MAX(AA28-(60),0)+Parameters!$C$18*MAX(AA28-(84),0)+Parameters!$C$19*MAX(AA28-(120),0)+Parameters!$C$20*MAX(AA28-(180),0)),0) | BH28: =IFERROR((Parameters!$C$21*AK28+Parameters!$C$22*MAX(AK28-(0),0)+Parameters!$C$23*MAX(AK28-(2),0)+Parameters!$C$24*MAX(AK28-(5),0)+Parameters!$C$25*MAX(AK28-(8),0)),0) | BI28: =IFERROR((Parameters!$C$26*AI28+Parameters!$C$27*MAX(AI28-(-100),0)+Parameters!$C$28*MAX(AI28-(-25),0)+Parameters!$C$29*MAX(AI28-(25),0)+Parameters!$C$30*MAX(AI28-(100),0)),0) | BJ28: =IFERROR((Parameters!$C$31*AN28+Parameters!$C$32*MAX(AN28-(2),0)+Parameters!$C$33*MAX(AN28-(10),0)+Parameters!$C$34*MAX(AN28-(25),0)),0) | BK28: =IFERROR((Parameters!$C$35*AB28+Parameters!$C$36*MAX(AB28-(12),0)+Parameters!$C$37*MAX(AB28-(24),0)+Parameters!$C$38*MAX(AB28-(60),0)),0) | BL28: =IFERROR((Parameters!$C$39*AC28+Parameters!$C$40*MAX(AC28-(6),0)+Parameters!$C$41*MAX(AC28-(12),0)+Parameters!$C$42*MAX(AC28-(24),0)),0) | BM28: =IFERROR(Parameters!$C$43*(MAX(AM28,0)*MIN(MAX(AK28,0),10))/100,0) | BN28: =Parameters!$C$44*AE28 | BO28: =Parameters!$C$45*AU28 + Parameters!$C$46*AV28 + Parameters!$C$47*AW28 + Parameters!$C$48*AX28 + Parameters!$C$49*AY28 + Parameters!$C$50*AZ28 + Parameters!$C$51*BA28 | BP28: =Parameters!$C$52*AQ28 | BQ28: =Parameters!$C$53*AR28+Parameters!$C$54*AS28+Parameters!$C$55*AT28 | BR28: =Parameters!$C$56*BB28+Parameters!$C$57*BC28+Parameters!$C$58*BD28+Parameters!$C$59*BE28 | BS28: =Parameters!$B$2 | BT28: =BS28+BF28 + BG28 + BH28 + BI28 + BJ28 + BK28 + BL28 + BM28 + BN28 + BO28 + BP28 + BQ28 + BR28 | BU28: =IF(AD28=1,0,1/(1+EXP(-BT28))*Parameters!$B$3) | BV28: =(1-(1-BU28)^12)*100 | BW28: =IF(AD28=1,0,(1-(1-1/(1+EXP(-Parameters!$B$2)))^12)*100) | BX28: =IF(AD28=1,0,BV28-(1-(1-(1/(1+EXP(-(BT28-BF28)))*Parameters!$B$3))^12)*100) | BY28: =IF(AD28=1,0,BV28-(1-(1-(1/(1+EXP(-(BT28-BG28)))*Parameters!$B$3))^12)*100) | BZ28: =IF(AD28=1,0,BV28-(1-(1-(1/(1+EXP(-(BT28-BH28)))*Parameters!$B$3))^12)*100) | CA28: =IF(AD28=1,0,BV28-(1-(1-(1/(1+EXP(-(BT28-BI28)))*Parameters!$B$3))^12)*100) | CB28: =IF(AD28=1,0,BV28-(1-(1-(1/(1+EXP(-(BT28-BJ28)))*Parameters!$B$3))^12)*100) | CC28: =IF(AD28=1,0,BV28-(1-(1-(1/(1+EXP(-(BT28-BK28)))*Parameters!$B$3))^12)*100) | CD28: =IF(AD28=1,0,BV28-(1-(1-(1/(1+EXP(-(BT28-BL28)))*Parameters!$B$3))^12)*100) | CE28: =IF(AD28=1,0,BV28-(1-(1-(1/(1+EXP(-(BT28-BM28)))*Parameters!$B$3))^12)*100) | CF28: =IF(AD28=1,0,BV28-(1-(1-(1/(1+EXP(-(BT28-BN28)))*Parameters!$B$3))^12)*100) | CG28: =IF(AD28=1,0,BV28-(1-(1-(1/(1+EXP(-(BT28-BO28)))*Parameters!$B$3))^12)*100) | CH28: =IF(AD28=1,0,BV28-(1-(1-(1/(1+EXP(-(BT28-BP28)))*Parameters!$B$3))^12)*100) | CI28: =IF(AD28=1,0,BV28-(1-(1-(1/(1+EXP(-(BT28-BQ28)))*Parameters!$B$3))^12)*100) | CJ28: =IF(AD28=1,0,BV28-(1-(1-(1/(1+EXP(-(BT28-BR28)))*Parameters!$B$3))^12)*100)
A29: GNR_2024_NEW | B29: 3618BP4H8 | C29: PN | D29: VIUM CAPITAL MORTGAGE, LLC. | E29: 3618BP4H8_000000007322354 | F29: 202603 | G29: 5.62 | H29: 9949068.1 | I29: 420 | J29: 20230801 | K29: 20580901 | M29: 20331001 | N29: 10 | O29: 232/223(F) | P29: MKT | T29: IN | U29: 76 | V29: 490.5 | W29: 31 | X29: 2023 | Y29: 3.5 | Z29: 8 | AA29: =IF(ISNUMBER(W29),W29,IFERROR(MAX(0,(VALUE(LEFT(F29,4))-VALUE(LEFT(TEXT(J29,"00000000"),4)))*12+(VALUE(MID(F29,5,2))-VALUE(MID(TEXT(J29,"00000000"),5,2)))),"")) | AB29: =IFERROR((VALUE(LEFT(TEXT(K29,"00000000"),4))-VALUE(LEFT(F29,4)))*12+(VALUE(MID(TEXT(K29,"00000000"),5,2))-VALUE(MID(F29,5,2))),"") | AC29: =IF(OR(L29="",NOT(ISNUMBER(L29))),0,MAX(0,MIN(60,(VALUE(LEFT(F29,4))-VALUE(LEFT(TEXT(L29,"00000000"),4)))*12+(VALUE(MID(F29,5,2))-VALUE(MID(TEXT(L29,"00000000"),5,2)))))) | AD29: =IF(OR(L29="",NOT(ISNUMBER(L29))),0,IF(VALUE(F29)<VALUE(LEFT(TEXT(L29,"00000000"),6)),1,0)) | AE29: =IF(OR(M29="",NOT(ISNUMBER(M29))),0,IF(VALUE(F29)<VALUE(LEFT(TEXT(M29,"00000000"),6)),1,0)) | AF29: =IF(AND(AD29=0,AE29=0),1,0) | AG29: =IF(ISNUMBER(X29),X29,IFERROR(VALUE(LEFT(TEXT(J29,"00000000"),4)),"")) | AH29: =IFERROR(XLOOKUP(AG29,Vintage_Rates!$A$2:$A$1000,Vintage_Rates!$B$2:$B$1000,""),"") | AI29: =IF(ISNUMBER(Y29),Y29,IFERROR((G29-AH29)*100,"")) | AJ29: =IF(ISNUMBER(V29),V29,IFERROR(XLOOKUP(VALUE(F29),PLC_Rates!$A$2:$A$1000,PLC_Rates!$B$2:$B$1000,""),"")) | AK29: =IF(ISNUMBER(Z29),Z29,IF(AE29=0,0,MAX(0,MIN(10,((VALUE(LEFT(TEXT(M29,"00000000"),4))-VALUE(LEFT(F29,4)))*12+(VALUE(MID(TEXT(M29,"00000000"),5,2))-VALUE(MID(F29,5,2))))/12)))) | AL29: =IFERROR(G29*100-AJ29,"") | AM29: =IFERROR(G29*100-(AJ29+(1+AK29)*12.5),"") | AN29: =IFERROR(MIN(H29/1000000,100),"") | AO29: =IFERROR(INDEX(FHA_Lookup!$B$2:$B$11,MATCH(TRUE,ISNUMBER(SEARCH(FHA_Lookup!$A$2:$A$11,UPPER(SUBSTITUTE(O29," ","")))),0)),"OTHER") | AP29: =IFERROR(INDEX(FHA_Lookup!$C$2:$C$11,MATCH(TRUE,ISNUMBER(SEARCH(FHA_Lookup!$A$2:$A$11,UPPER(SUBSTITUTE(O29," ","")))),0)),"OTHER") | AQ29: =IF(AP29="NC",1,0) | AR29: =IF(UPPER(TRIM(P29))="AFF",1,0) | AS29: =IF(UPPER(TRIM(P29))="BAF",1,0) | AT29: =IF(UPPER(TRIM(P29))="MKT",1,0) | AU29: =IF(AO29="221d4",1,0) | AV29: =IF(AO29="223a7",1,0) | AW29: =IF(AO29="232",1,0) | AX29: =IF(AO29="538",1,0) | AY29: =IF(AO29="241",1,0) | AZ29: =IF(AO29="220",1,0) | BA29: =IF(AO29="OTHER",1,0) | BB29: =IF(UPPER(TRIM(C29))="LM",1,0) | BC29: =IF(UPPER(TRIM(C29))="PN",1,0) | BD29: =IF(UPPER(TRIM(C29))="LS",1,0) | BE29: =IF(UPPER(TRIM(C29))="RX",1,0) | BF29: =IFERROR((Parameters!$C$6*AM29+Parameters!$C$7*MAX(AM29-(-150),0)+Parameters!$C$8*MAX(AM29-(-50),0)+Parameters!$C$9*MAX(AM29-(0),0)+Parameters!$C$10*MAX(AM29-(50),0)+Parameters!$C$11*MAX(AM29-(100),0)+Parameters!$C$12*MAX(AM29-(150),0)+Parameters!$C$13*MAX(AM29-(250),0)),0) | BG29: =IFERROR((Parameters!$C$14*AA29+Parameters!$C$15*MAX(AA29-(12),0)+Parameters!$C$16*MAX(AA29-(36),0)+Parameters!$C$17*MAX(AA29-(60),0)+Parameters!$C$18*MAX(AA29-(84),0)+Parameters!$C$19*MAX(AA29-(120),0)+Parameters!$C$20*MAX(AA29-(180),0)),0) | BH29: =IFERROR((Parameters!$C$21*AK29+Parameters!$C$22*MAX(AK29-(0),0)+Parameters!$C$23*MAX(AK29-(2),0)+Parameters!$C$24*MAX(AK29-(5),0)+Parameters!$C$25*MAX(AK29-(8),0)),0) | BI29: =IFERROR((Parameters!$C$26*AI29+Parameters!$C$27*MAX(AI29-(-100),0)+Parameters!$C$28*MAX(AI29-(-25),0)+Parameters!$C$29*MAX(AI29-(25),0)+Parameters!$C$30*MAX(AI29-(100),0)),0) | BJ29: =IFERROR((Parameters!$C$31*AN29+Parameters!$C$32*MAX(AN29-(2),0)+Parameters!$C$33*MAX(AN29-(10),0)+Parameters!$C$34*MAX(AN29-(25),0)),0) | BK29: =IFERROR((Parameters!$C$35*AB29+Parameters!$C$36*MAX(AB29-(12),0)+Parameters!$C$37*MAX(AB29-(24),0)+Parameters!$C$38*MAX(AB29-(60),0)),0) | BL29: =IFERROR((Parameters!$C$39*AC29+Parameters!$C$40*MAX(AC29-(6),0)+Parameters!$C$41*MAX(AC29-(12),0)+Parameters!$C$42*MAX(AC29-(24),0)),0) | BM29: =IFERROR(Parameters!$C$43*(MAX(AM29,0)*MIN(MAX(AK29,0),10))/100,0) | BN29: =Parameters!$C$44*AE29 | BO29: =Parameters!$C$45*AU29 + Parameters!$C$46*AV29 + Parameters!$C$47*AW29 + Parameters!$C$48*AX29 + Parameters!$C$49*AY29 + Parameters!$C$50*AZ29 + Parameters!$C$51*BA29 | BP29: =Parameters!$C$52*AQ29 | BQ29: =Parameters!$C$53*AR29+Parameters!$C$54*AS29+Parameters!$C$55*AT29 | BR29: =Parameters!$C$56*BB29+Parameters!$C$57*BC29+Parameters!$C$58*BD29+Parameters!$C$59*BE29 | BS29: =Parameters!$B$2 | BT29: =BS29+BF29 + BG29 + BH29 + BI29 + BJ29 + BK29 + BL29 + BM29 + BN29 + BO29 + BP29 + BQ29 + BR29 | BU29: =IF(AD29=1,0,1/(1+EXP(-BT29))*Parameters!$B$3) | BV29: =(1-(1-BU29)^12)*100 | BW29: =IF(AD29=1,0,(1-(1-1/(1+EXP(-Parameters!$B$2)))^12)*100) | BX29: =IF(AD29=1,0,BV29-(1-(1-(1/(1+EXP(-(BT29-BF29)))*Parameters!$B$3))^12)*100) | BY29: =IF(AD29=1,0,BV29-(1-(1-(1/(1+EXP(-(BT29-BG29)))*Parameters!$B$3))^12)*100) | BZ29: =IF(AD29=1,0,BV29-(1-(1-(1/(1+EXP(-(BT29-BH29)))*Parameters!$B$3))^12)*100) | CA29: =IF(AD29=1,0,BV29-(1-(1-(1/(1+EXP(-(BT29-BI29)))*Parameters!$B$3))^12)*100) | CB29: =IF(AD29=1,0,BV29-(1-(1-(1/(1+EXP(-(BT29-BJ29)))*Parameters!$B$3))^12)*100) | CC29: =IF(AD29=1,0,BV29-(1-(1-(1/(1+EXP(-(BT29-BK29)))*Parameters!$B$3))^12)*100) | CD29: =IF(AD29=1,0,BV29-(1-(1-(1/(1+EXP(-(BT29-BL29)))*Parameters!$B$3))^12)*100) | CE29: =IF(AD29=1,0,BV29-(1-(1-(1/(1+EXP(-(BT29-BM29)))*Parameters!$B$3))^12)*100) | CF29: =IF(AD29=1,0,BV29-(1-(1-(1/(1+EXP(-(BT29-BN29)))*Parameters!$B$3))^12)*100) | CG29: =IF(AD29=1,0,BV29-(1-(1-(1/(1+EXP(-(BT29-BO29)))*Parameters!$B$3))^12)*100) | CH29: =IF(AD29=1,0,BV29-(1-(1-(1/(1+EXP(-(BT29-BP29)))*Parameters!$B$3))^12)*100) | CI29: =IF(AD29=1,0,BV29-(1-(1-(1/(1+EXP(-(BT29-BQ29)))*Parameters!$B$3))^12)*100) | CJ29: =IF(AD29=1,0,BV29-(1-(1-(1/(1+EXP(-(BT29-BR29)))*Parameters!$B$3))^12)*100)
A30: GNR_2024_NEW | B30: 3618ACYR3 | C30: PN | D30: ARBOR AGENCY LENDING, LLC | E30: 3618ACYR3_000000005411276 | F30: 202603 | G30: 5.5 | H30: 22135629 | I30: 421 | J30: 20251001 | K30: 20601101 | M30: 20351201 | N30: 10 | O30: 207/223(F) | T30: SC | U30: 160 | V30: 490.5 | W30: 5 | X30: 2025 | Y30: -32 | Z30: 10 | AA30: =IF(ISNUMBER(W30),W30,IFERROR(MAX(0,(VALUE(LEFT(F30,4))-VALUE(LEFT(TEXT(J30,"00000000"),4)))*12+(VALUE(MID(F30,5,2))-VALUE(MID(TEXT(J30,"00000000"),5,2)))),"")) | AB30: =IFERROR((VALUE(LEFT(TEXT(K30,"00000000"),4))-VALUE(LEFT(F30,4)))*12+(VALUE(MID(TEXT(K30,"00000000"),5,2))-VALUE(MID(F30,5,2))),"") | AC30: =IF(OR(L30="",NOT(ISNUMBER(L30))),0,MAX(0,MIN(60,(VALUE(LEFT(F30,4))-VALUE(LEFT(TEXT(L30,"00000000"),4)))*12+(VALUE(MID(F30,5,2))-VALUE(MID(TEXT(L30,"00000000"),5,2)))))) | AD30: =IF(OR(L30="",NOT(ISNUMBER(L30))),0,IF(VALUE(F30)<VALUE(LEFT(TEXT(L30,"00000000"),6)),1,0)) | AE30: =IF(OR(M30="",NOT(ISNUMBER(M30))),0,IF(VALUE(F30)<VALUE(LEFT(TEXT(M30,"00000000"),6)),1,0)) | AF30: =IF(AND(AD30=0,AE30=0),1,0) | AG30: =IF(ISNUMBER(X30),X30,IFERROR(VALUE(LEFT(TEXT(J30,"00000000"),4)),"")) | AH30: =IFERROR(XLOOKUP(AG30,Vintage_Rates!$A$2:$A$1000,Vintage_Rates!$B$2:$B$1000,""),"") | AI30: =IF(ISNUMBER(Y30),Y30,IFERROR((G30-AH30)*100,"")) | AJ30: =IF(ISNUMBER(V30),V30,IFERROR(XLOOKUP(VALUE(F30),PLC_Rates!$A$2:$A$1000,PLC_Rates!$B$2:$B$1000,""),"")) | AK30: =IF(ISNUMBER(Z30),Z30,IF(AE30=0,0,MAX(0,MIN(10,((VALUE(LEFT(TEXT(M30,"00000000"),4))-VALUE(LEFT(F30,4)))*12+(VALUE(MID(TEXT(M30,"00000000"),5,2))-VALUE(MID(F30,5,2))))/12)))) | AL30: =IFERROR(G30*100-AJ30,"") | AM30: =IFERROR(G30*100-(AJ30+(1+AK30)*12.5),"") | AN30: =IFERROR(MIN(H30/1000000,100),"") | AO30: =IFERROR(INDEX(FHA_Lookup!$B$2:$B$11,MATCH(TRUE,ISNUMBER(SEARCH(FHA_Lookup!$A$2:$A$11,UPPER(SUBSTITUTE(O30," ","")))),0)),"OTHER") | AP30: =IFERROR(INDEX(FHA_Lookup!$C$2:$C$11,MATCH(TRUE,ISNUMBER(SEARCH(FHA_Lookup!$A$2:$A$11,UPPER(SUBSTITUTE(O30," ","")))),0)),"OTHER") | AQ30: =IF(AP30="NC",1,0) | AR30: =IF(UPPER(TRIM(P30))="AFF",1,0) | AS30: =IF(UPPER(TRIM(P30))="BAF",1,0) | AT30: =IF(UPPER(TRIM(P30))="MKT",1,0) | AU30: =IF(AO30="221d4",1,0) | AV30: =IF(AO30="223a7",1,0) | AW30: =IF(AO30="232",1,0) | AX30: =IF(AO30="538",1,0) | AY30: =IF(AO30="241",1,0) | AZ30: =IF(AO30="220",1,0) | BA30: =IF(AO30="OTHER",1,0) | BB30: =IF(UPPER(TRIM(C30))="LM",1,0) | BC30: =IF(UPPER(TRIM(C30))="PN",1,0) | BD30: =IF(UPPER(TRIM(C30))="LS",1,0) | BE30: =IF(UPPER(TRIM(C30))="RX",1,0) | BF30: =IFERROR((Parameters!$C$6*AM30+Parameters!$C$7*MAX(AM30-(-150),0)+Parameters!$C$8*MAX(AM30-(-50),0)+Parameters!$C$9*MAX(AM30-(0),0)+Parameters!$C$10*MAX(AM30-(50),0)+Parameters!$C$11*MAX(AM30-(100),0)+Parameters!$C$12*MAX(AM30-(150),0)+Parameters!$C$13*MAX(AM30-(250),0)),0) | BG30: =IFERROR((Parameters!$C$14*AA30+Parameters!$C$15*MAX(AA30-(12),0)+Parameters!$C$16*MAX(AA30-(36),0)+Parameters!$C$17*MAX(AA30-(60),0)+Parameters!$C$18*MAX(AA30-(84),0)+Parameters!$C$19*MAX(AA30-(120),0)+Parameters!$C$20*MAX(AA30-(180),0)),0) | BH30: =IFERROR((Parameters!$C$21*AK30+Parameters!$C$22*MAX(AK30-(0),0)+Parameters!$C$23*MAX(AK30-(2),0)+Parameters!$C$24*MAX(AK30-(5),0)+Parameters!$C$25*MAX(AK30-(8),0)),0) | BI30: =IFERROR((Parameters!$C$26*AI30+Parameters!$C$27*MAX(AI30-(-100),0)+Parameters!$C$28*MAX(AI30-(-25),0)+Parameters!$C$29*MAX(AI30-(25),0)+Parameters!$C$30*MAX(AI30-(100),0)),0) | BJ30: =IFERROR((Parameters!$C$31*AN30+Parameters!$C$32*MAX(AN30-(2),0)+Parameters!$C$33*MAX(AN30-(10),0)+Parameters!$C$34*MAX(AN30-(25),0)),0) | BK30: =IFERROR((Parameters!$C$35*AB30+Parameters!$C$36*MAX(AB30-(12),0)+Parameters!$C$37*MAX(AB30-(24),0)+Parameters!$C$38*MAX(AB30-(60),0)),0) | BL30: =IFERROR((Parameters!$C$39*AC30+Parameters!$C$40*MAX(AC30-(6),0)+Parameters!$C$41*MAX(AC30-(12),0)+Parameters!$C$42*MAX(AC30-(24),0)),0) | BM30: =IFERROR(Parameters!$C$43*(MAX(AM30,0)*MIN(MAX(AK30,0),10))/100,0) | BN30: =Parameters!$C$44*AE30 | BO30: =Parameters!$C$45*AU30 + Parameters!$C$46*AV30 + Parameters!$C$47*AW30 + Parameters!$C$48*AX30 + Parameters!$C$49*AY30 + Parameters!$C$50*AZ30 + Parameters!$C$51*BA30 | BP30: =Parameters!$C$52*AQ30 | BQ30: =Parameters!$C$53*AR30+Parameters!$C$54*AS30+Parameters!$C$55*AT30 | BR30: =Parameters!$C$56*BB30+Parameters!$C$57*BC30+Parameters!$C$58*BD30+Parameters!$C$59*BE30 | BS30: =Parameters!$B$2 | BT30: =BS30+BF30 + BG30 + BH30 + BI30 + BJ30 + BK30 + BL30 + BM30 + BN30 + BO30 + BP30 + BQ30 + BR30 | BU30: =IF(AD30=1,0,1/(1+EXP(-BT30))*Parameters!$B$3) | BV30: =(1-(1-BU30)^12)*100 | BW30: =IF(AD30=1,0,(1-(1-1/(1+EXP(-Parameters!$B$2)))^12)*100) | BX30: =IF(AD30=1,0,BV30-(1-(1-(1/(1+EXP(-(BT30-BF30)))*Parameters!$B$3))^12)*100) | BY30: =IF(AD30=1,0,BV30-(1-(1-(1/(1+EXP(-(BT30-BG30)))*Parameters!$B$3))^12)*100) | BZ30: =IF(AD30=1,0,BV30-(1-(1-(1/(1+EXP(-(BT30-BH30)))*Parameters!$B$3))^12)*100) | CA30: =IF(AD30=1,0,BV30-(1-(1-(1/(1+EXP(-(BT30-BI30)))*Parameters!$B$3))^12)*100) | CB30: =IF(AD30=1,0,BV30-(1-(1-(1/(1+EXP(-(BT30-BJ30)))*Parameters!$B$3))^12)*100) | CC30: =IF(AD30=1,0,BV30-(1-(1-(1/(1+EXP(-(BT30-BK30)))*Parameters!$B$3))^12)*100) | CD30: =IF(AD30=1,0,BV30-(1-(1-(1/(1+EXP(-(BT30-BL30)))*Parameters!$B$3))^12)*100) | CE30: =IF(AD30=1,0,BV30-(1-(1-(1/(1+EXP(-(BT30-BM30)))*Parameters!$B$3))^12)*100) | CF30: =IF(AD30=1,0,BV30-(1-(1-(1/(1+EXP(-(BT30-BN30)))*Parameters!$B$3))^12)*100) | CG30: =IF(AD30=1,0,BV30-(1-(1-(1/(1+EXP(-(BT30-BO30)))*Parameters!$B$3))^12)*100) | CH30: =IF(AD30=1,0,BV30-(1-(1-(1/(1+EXP(-(BT30-BP30)))*Parameters!$B$3))^12)*100) | CI30: =IF(AD30=1,0,BV30-(1-(1-(1/(1+EXP(-(BT30-BQ30)))*Parameters!$B$3))^12)*100) | CJ30: =IF(AD30=1,0,BV30-(1-(1-(1/(1+EXP(-(BT30-BR30)))*Parameters!$B$3))^12)*100)
A31: GNR_2024_NEW | B31: 3618ASNZ2 | C31: PN | D31: ROSE COMMUNITY CAPITAL, LLC | E31: 3618ASNZ2_000000012235767 | F31: 202603 | G31: 5.89 | H31: 6768706.7 | I31: 494 | J31: 20240401 | K31: 20650601 | L31: 20250701 | M31: 20350701 | N31: 10 | O31: 221(d)(4) | P31: BAF | T31: CA | U31: 40 | V31: 490.5 | W31: 23 | X31: 2024 | Y31: 11 | Z31: 10 | AA31: =IF(ISNUMBER(W31),W31,IFERROR(MAX(0,(VALUE(LEFT(F31,4))-VALUE(LEFT(TEXT(J31,"00000000"),4)))*12+(VALUE(MID(F31,5,2))-VALUE(MID(TEXT(J31,"00000000"),5,2)))),"")) | AB31: =IFERROR((VALUE(LEFT(TEXT(K31,"00000000"),4))-VALUE(LEFT(F31,4)))*12+(VALUE(MID(TEXT(K31,"00000000"),5,2))-VALUE(MID(F31,5,2))),"") | AC31: =IF(OR(L31="",NOT(ISNUMBER(L31))),0,MAX(0,MIN(60,(VALUE(LEFT(F31,4))-VALUE(LEFT(TEXT(L31,"00000000"),4)))*12+(VALUE(MID(F31,5,2))-VALUE(MID(TEXT(L31,"00000000"),5,2)))))) | AD31: =IF(OR(L31="",NOT(ISNUMBER(L31))),0,IF(VALUE(F31)<VALUE(LEFT(TEXT(L31,"00000000"),6)),1,0)) | AE31: =IF(OR(M31="",NOT(ISNUMBER(M31))),0,IF(VALUE(F31)<VALUE(LEFT(TEXT(M31,"00000000"),6)),1,0)) | AF31: =IF(AND(AD31=0,AE31=0),1,0) | AG31: =IF(ISNUMBER(X31),X31,IFERROR(VALUE(LEFT(TEXT(J31,"00000000"),4)),"")) | AH31: =IFERROR(XLOOKUP(AG31,Vintage_Rates!$A$2:$A$1000,Vintage_Rates!$B$2:$B$1000,""),"") | AI31: =IF(ISNUMBER(Y31),Y31,IFERROR((G31-AH31)*100,"")) | AJ31: =IF(ISNUMBER(V31),V31,IFERROR(XLOOKUP(VALUE(F31),PLC_Rates!$A$2:$A$1000,PLC_Rates!$B$2:$B$1000,""),"")) | AK31: =IF(ISNUMBER(Z31),Z31,IF(AE31=0,0,MAX(0,MIN(10,((VALUE(LEFT(TEXT(M31,"00000000"),4))-VALUE(LEFT(F31,4)))*12+(VALUE(MID(TEXT(M31,"00000000"),5,2))-VALUE(MID(F31,5,2))))/12)))) | AL31: =IFERROR(G31*100-AJ31,"") | AM31: =IFERROR(G31*100-(AJ31+(1+AK31)*12.5),"") | AN31: =IFERROR(MIN(H31/1000000,100),"") | AO31: =IFERROR(INDEX(FHA_Lookup!$B$2:$B$11,MATCH(TRUE,ISNUMBER(SEARCH(FHA_Lookup!$A$2:$A$11,UPPER(SUBSTITUTE(O31," ","")))),0)),"OTHER") | AP31: =IFERROR(INDEX(FHA_Lookup!$C$2:$C$11,MATCH(TRUE,ISNUMBER(SEARCH(FHA_Lookup!$A$2:$A$11,UPPER(SUBSTITUTE(O31," ","")))),0)),"OTHER") | AQ31: =IF(AP31="NC",1,0) | AR31: =IF(UPPER(TRIM(P31))="AFF",1,0) | AS31: =IF(UPPER(TRIM(P31))="BAF",1,0) | AT31: =IF(UPPER(TRIM(P31))="MKT",1,0) | AU31: =IF(AO31="221d4",1,0) | AV31: =IF(AO31="223a7",1,0) | AW31: =IF(AO31="232",1,0) | AX31: =IF(AO31="538",1,0) | AY31: =IF(AO31="241",1,0) | AZ31: =IF(AO31="220",1,0) | BA31: =IF(AO31="OTHER",1,0) | BB31: =IF(UPPER(TRIM(C31))="LM",1,0) | BC31: =IF(UPPER(TRIM(C31))="PN",1,0) | BD31: =IF(UPPER(TRIM(C31))="LS",1,0) | BE31: =IF(UPPER(TRIM(C31))="RX",1,0) | BF31: =IFERROR((Parameters!$C$6*AM31+Parameters!$C$7*MAX(AM31-(-150),0)+Parameters!$C$8*MAX(AM31-(-50),0)+Parameters!$C$9*MAX(AM31-(0),0)+Parameters!$C$10*MAX(AM31-(50),0)+Parameters!$C$11*MAX(AM31-(100),0)+Parameters!$C$12*MAX(AM31-(150),0)+Parameters!$C$13*MAX(AM31-(250),0)),0) | BG31: =IFERROR((Parameters!$C$14*AA31+Parameters!$C$15*MAX(AA31-(12),0)+Parameters!$C$16*MAX(AA31-(36),0)+Parameters!$C$17*MAX(AA31-(60),0)+Parameters!$C$18*MAX(AA31-(84),0)+Parameters!$C$19*MAX(AA31-(120),0)+Parameters!$C$20*MAX(AA31-(180),0)),0) | BH31: =IFERROR((Parameters!$C$21*AK31+Parameters!$C$22*MAX(AK31-(0),0)+Parameters!$C$23*MAX(AK31-(2),0)+Parameters!$C$24*MAX(AK31-(5),0)+Parameters!$C$25*MAX(AK31-(8),0)),0) | BI31: =IFERROR((Parameters!$C$26*AI31+Parameters!$C$27*MAX(AI31-(-100),0)+Parameters!$C$28*MAX(AI31-(-25),0)+Parameters!$C$29*MAX(AI31-(25),0)+Parameters!$C$30*MAX(AI31-(100),0)),0) | BJ31: =IFERROR((Parameters!$C$31*AN31+Parameters!$C$32*MAX(AN31-(2),0)+Parameters!$C$33*MAX(AN31-(10),0)+Parameters!$C$34*MAX(AN31-(25),0)),0) | BK31: =IFERROR((Parameters!$C$35*AB31+Parameters!$C$36*MAX(AB31-(12),0)+Parameters!$C$37*MAX(AB31-(24),0)+Parameters!$C$38*MAX(AB31-(60),0)),0) | BL31: =IFERROR((Parameters!$C$39*AC31+Parameters!$C$40*MAX(AC31-(6),0)+Parameters!$C$41*MAX(AC31-(12),0)+Parameters!$C$42*MAX(AC31-(24),0)),0) | BM31: =IFERROR(Parameters!$C$43*(MAX(AM31,0)*MIN(MAX(AK31,0),10))/100,0) | BN31: =Parameters!$C$44*AE31 | BO31: =Parameters!$C$45*AU31 + Parameters!$C$46*AV31 + Parameters!$C$47*AW31 + Parameters!$C$48*AX31 + Parameters!$C$49*AY31 + Parameters!$C$50*AZ31 + Parameters!$C$51*BA31 | BP31: =Parameters!$C$52*AQ31 | BQ31: =Parameters!$C$53*AR31+Parameters!$C$54*AS31+Parameters!$C$55*AT31 | BR31: =Parameters!$C$56*BB31+Parameters!$C$57*BC31+Parameters!$C$58*BD31+Parameters!$C$59*BE31 | BS31: =Parameters!$B$2 | BT31: =BS31+BF31 + BG31 + BH31 + BI31 + BJ31 + BK31 + BL31 + BM31 + BN31 + BO31 + BP31 + BQ31 + BR31 | BU31: =IF(AD31=1,0,1/(1+EXP(-BT31))*Parameters!$B$3) | BV31: =(1-(1-BU31)^12)*100 | BW31: =IF(AD31=1,0,(1-(1-1/(1+EXP(-Parameters!$B$2)))^12)*100) | BX31: =IF(AD31=1,0,BV31-(1-(1-(1/(1+EXP(-(BT31-BF31)))*Parameters!$B$3))^12)*100) | BY31: =IF(AD31=1,0,BV31-(1-(1-(1/(1+EXP(-(BT31-BG31)))*Parameters!$B$3))^12)*100) | BZ31: =IF(AD31=1,0,BV31-(1-(1-(1/(1+EXP(-(BT31-BH31)))*Parameters!$B$3))^12)*100) | CA31: =IF(AD31=1,0,BV31-(1-(1-(1/(1+EXP(-(BT31-BI31)))*Parameters!$B$3))^12)*100) | CB31: =IF(AD31=1,0,BV31-(1-(1-(1/(1+EXP(-(BT31-BJ31)))*Parameters!$B$3))^12)*100) | CC31: =IF(AD31=1,0,BV31-(1-(1-(1/(1+EXP(-(BT31-BK31)))*Parameters!$B$3))^12)*100) | CD31: =IF(AD31=1,0,BV31-(1-(1-(1/(1+EXP(-(BT31-BL31)))*Parameters!$B$3))^12)*100) | CE31: =IF(AD31=1,0,BV31-(1-(1-(1/(1+EXP(-(BT31-BM31)))*Parameters!$B$3))^12)*100) | CF31: =IF(AD31=1,0,BV31-(1-(1-(1/(1+EXP(-(BT31-BN31)))*Parameters!$B$3))^12)*100) | CG31: =IF(AD31=1,0,BV31-(1-(1-(1/(1+EXP(-(BT31-BO31)))*Parameters!$B$3))^12)*100) | CH31: =IF(AD31=1,0,BV31-(1-(1-(1/(1+EXP(-(BT31-BP31)))*Parameters!$B$3))^12)*100) | CI31: =IF(AD31=1,0,BV31-(1-(1-(1/(1+EXP(-(BT31-BQ31)))*Parameters!$B$3))^12)*100) | CJ31: =IF(AD31=1,0,BV31-(1-(1-(1/(1+EXP(-(BT31-BR31)))*Parameters!$B$3))^12)*100)
A32: GNR_2024_NEW | B32: 3618A2B41 | C32: PN | D32: FIRST AMERICAN CAPITAL GROUP CORPORATION | E32: 3618A2B41_000000008122066 | F32: 202603 | G32: 6.09 | H32: 16753678 | I32: 419 | J32: 20250114 | K32: 20600701 | M32: 20350801 | N32: 10 | O32: 232/223(f) | T32: TN | U32: 128 | V32: 490.5 | W32: 14 | X32: 2025 | Y32: 27 | Z32: 10 | AA32: =IF(ISNUMBER(W32),W32,IFERROR(MAX(0,(VALUE(LEFT(F32,4))-VALUE(LEFT(TEXT(J32,"00000000"),4)))*12+(VALUE(MID(F32,5,2))-VALUE(MID(TEXT(J32,"00000000"),5,2)))),"")) | AB32: =IFERROR((VALUE(LEFT(TEXT(K32,"00000000"),4))-VALUE(LEFT(F32,4)))*12+(VALUE(MID(TEXT(K32,"00000000"),5,2))-VALUE(MID(F32,5,2))),"") | AC32: =IF(OR(L32="",NOT(ISNUMBER(L32))),0,MAX(0,MIN(60,(VALUE(LEFT(F32,4))-VALUE(LEFT(TEXT(L32,"00000000"),4)))*12+(VALUE(MID(F32,5,2))-VALUE(MID(TEXT(L32,"00000000"),5,2)))))) | AD32: =IF(OR(L32="",NOT(ISNUMBER(L32))),0,IF(VALUE(F32)<VALUE(LEFT(TEXT(L32,"00000000"),6)),1,0)) | AE32: =IF(OR(M32="",NOT(ISNUMBER(M32))),0,IF(VALUE(F32)<VALUE(LEFT(TEXT(M32,"00000000"),6)),1,0)) | AF32: =IF(AND(AD32=0,AE32=0),1,0) | AG32: =IF(ISNUMBER(X32),X32,IFERROR(VALUE(LEFT(TEXT(J32,"00000000"),4)),"")) | AH32: =IFERROR(XLOOKUP(AG32,Vintage_Rates!$A$2:$A$1000,Vintage_Rates!$B$2:$B$1000,""),"") | AI32: =IF(ISNUMBER(Y32),Y32,IFERROR((G32-AH32)*100,"")) | AJ32: =IF(ISNUMBER(V32),V32,IFERROR(XLOOKUP(VALUE(F32),PLC_Rates!$A$2:$A$1000,PLC_Rates!$B$2:$B$1000,""),"")) | AK32: =IF(ISNUMBER(Z32),Z32,IF(AE32=0,0,MAX(0,MIN(10,((VALUE(LEFT(TEXT(M32,"00000000"),4))-VALUE(LEFT(F32,4)))*12+(VALUE(MID(TEXT(M32,"00000000"),5,2))-VALUE(MID(F32,5,2))))/12)))) | AL32: =IFERROR(G32*100-AJ32,"") | AM32: =IFERROR(G32*100-(AJ32+(1+AK32)*12.5),"") | AN32: =IFERROR(MIN(H32/1000000,100),"") | AO32: =IFERROR(INDEX(FHA_Lookup!$B$2:$B$11,MATCH(TRUE,ISNUMBER(SEARCH(FHA_Lookup!$A$2:$A$11,UPPER(SUBSTITUTE(O32," ","")))),0)),"OTHER") | AP32: =IFERROR(INDEX(FHA_Lookup!$C$2:$C$11,MATCH(TRUE,ISNUMBER(SEARCH(FHA_Lookup!$A$2:$A$11,UPPER(SUBSTITUTE(O32," ","")))),0)),"OTHER") | AQ32: =IF(AP32="NC",1,0) | AR32: =IF(UPPER(TRIM(P32))="AFF",1,0) | AS32: =IF(UPPER(TRIM(P32))="BAF",1,0) | AT32: =IF(UPPER(TRIM(P32))="MKT",1,0) | AU32: =IF(AO32="221d4",1,0) | AV32: =IF(AO32="223a7",1,0) | AW32: =IF(AO32="232",1,0) | AX32: =IF(AO32="538",1,0) | AY32: =IF(AO32="241",1,0) | AZ32: =IF(AO32="220",1,0) | BA32: =IF(AO32="OTHER",1,0) | BB32: =IF(UPPER(TRIM(C32))="LM",1,0) | BC32: =IF(UPPER(TRIM(C32))="PN",1,0) | BD32: =IF(UPPER(TRIM(C32))="LS",1,0) | BE32: =IF(UPPER(TRIM(C32))="RX",1,0) | BF32: =IFERROR((Parameters!$C$6*AM32+Parameters!$C$7*MAX(AM32-(-150),0)+Parameters!$C$8*MAX(AM32-(-50),0)+Parameters!$C$9*MAX(AM32-(0),0)+Parameters!$C$10*MAX(AM32-(50),0)+Parameters!$C$11*MAX(AM32-(100),0)+Parameters!$C$12*MAX(AM32-(150),0)+Parameters!$C$13*MAX(AM32-(250),0)),0) | BG32: =IFERROR((Parameters!$C$14*AA32+Parameters!$C$15*MAX(AA32-(12),0)+Parameters!$C$16*MAX(AA32-(36),0)+Parameters!$C$17*MAX(AA32-(60),0)+Parameters!$C$18*MAX(AA32-(84),0)+Parameters!$C$19*MAX(AA32-(120),0)+Parameters!$C$20*MAX(AA32-(180),0)),0) | BH32: =IFERROR((Parameters!$C$21*AK32+Parameters!$C$22*MAX(AK32-(0),0)+Parameters!$C$23*MAX(AK32-(2),0)+Parameters!$C$24*MAX(AK32-(5),0)+Parameters!$C$25*MAX(AK32-(8),0)),0) | BI32: =IFERROR((Parameters!$C$26*AI32+Parameters!$C$27*MAX(AI32-(-100),0)+Parameters!$C$28*MAX(AI32-(-25),0)+Parameters!$C$29*MAX(AI32-(25),0)+Parameters!$C$30*MAX(AI32-(100),0)),0) | BJ32: =IFERROR((Parameters!$C$31*AN32+Parameters!$C$32*MAX(AN32-(2),0)+Parameters!$C$33*MAX(AN32-(10),0)+Parameters!$C$34*MAX(AN32-(25),0)),0) | BK32: =IFERROR((Parameters!$C$35*AB32+Parameters!$C$36*MAX(AB32-(12),0)+Parameters!$C$37*MAX(AB32-(24),0)+Parameters!$C$38*MAX(AB32-(60),0)),0) | BL32: =IFERROR((Parameters!$C$39*AC32+Parameters!$C$40*MAX(AC32-(6),0)+Parameters!$C$41*MAX(AC32-(12),0)+Parameters!$C$42*MAX(AC32-(24),0)),0) | BM32: =IFERROR(Parameters!$C$43*(MAX(AM32,0)*MIN(MAX(AK32,0),10))/100,0) | BN32: =Parameters!$C$44*AE32 | BO32: =Parameters!$C$45*AU32 + Parameters!$C$46*AV32 + Parameters!$C$47*AW32 + Parameters!$C$48*AX32 + Parameters!$C$49*AY32 + Parameters!$C$50*AZ32 + Parameters!$C$51*BA32 | BP32: =Parameters!$C$52*AQ32 | BQ32: =Parameters!$C$53*AR32+Parameters!$C$54*AS32+Parameters!$C$55*AT32 | BR32: =Parameters!$C$56*BB32+Parameters!$C$57*BC32+Parameters!$C$58*BD32+Parameters!$C$59*BE32 | BS32: =Parameters!$B$2 | BT32: =BS32+BF32 + BG32 + BH32 + BI32 + BJ32 + BK32 + BL32 + BM32 + BN32 + BO32 + BP32 + BQ32 + BR32 | BU32: =IF(AD32=1,0,1/(1+EXP(-BT32))*Parameters!$B$3) | BV32: =(1-(1-BU32)^12)*100 | BW32: =IF(AD32=1,0,(1-(1-1/(1+EXP(-Parameters!$B$2)))^12)*100) | BX32: =IF(AD32=1,0,BV32-(1-(1-(1/(1+EXP(-(BT32-BF32)))*Parameters!$B$3))^12)*100) | BY32: =IF(AD32=1,0,BV32-(1-(1-(1/(1+EXP(-(BT32-BG32)))*Parameters!$B$3))^12)*100) | BZ32: =IF(AD32=1,0,BV32-(1-(1-(1/(1+EXP(-(BT32-BH32)))*Parameters!$B$3))^12)*100) | CA32: =IF(AD32=1,0,BV32-(1-(1-(1/(1+EXP(-(BT32-BI32)))*Parameters!$B$3))^12)*100) | CB32: =IF(AD32=1,0,BV32-(1-(1-(1/(1+EXP(-(BT32-BJ32)))*Parameters!$B$3))^12)*100) | CC32: =IF(AD32=1,0,BV32-(1-(1-(1/(1+EXP(-(BT32-BK32)))*Parameters!$B$3))^12)*100) | CD32: =IF(AD32=1,0,BV32-(1-(1-(1/(1+EXP(-(BT32-BL32)))*Parameters!$B$3))^12)*100) | CE32: =IF(AD32=1,0,BV32-(1-(1-(1/(1+EXP(-(BT32-BM32)))*Parameters!$B$3))^12)*100) | CF32: =IF(AD32=1,0,BV32-(1-(1-(1/(1+EXP(-(BT32-BN32)))*Parameters!$B$3))^12)*100) | CG32: =IF(AD32=1,0,BV32-(1-(1-(1/(1+EXP(-(BT32-BO32)))*Parameters!$B$3))^12)*100) | CH32: =IF(AD32=1,0,BV32-(1-(1-(1/(1+EXP(-(BT32-BP32)))*Parameters!$B$3))^12)*100) | CI32: =IF(AD32=1,0,BV32-(1-(1-(1/(1+EXP(-(BT32-BQ32)))*Parameters!$B$3))^12)*100) | CJ32: =IF(AD32=1,0,BV32-(1-(1-(1/(1+EXP(-(BT32-BR32)))*Parameters!$B$3))^12)*100)
A33: GNR_2024_NEW | B33: 3618JCGR4 | C33: PN | D33: CENTENNIAL MORTGAGE, INC | E33: 3618JCGR4_000000004211452 | F33: 202603 | G33: 5.64 | H33: 5768690.9 | I33: 420 | J33: 20250403 | K33: 20600601 | M33: 20350701 | N33: 10 | O33: 207/223(F) | T33: OH | U33: 79 | V33: 490.5 | W33: 11 | X33: 2025 | Y33: -18 | Z33: 10 | AA33: =IF(ISNUMBER(W33),W33,IFERROR(MAX(0,(VALUE(LEFT(F33,4))-VALUE(LEFT(TEXT(J33,"00000000"),4)))*12+(VALUE(MID(F33,5,2))-VALUE(MID(TEXT(J33,"00000000"),5,2)))),"")) | AB33: =IFERROR((VALUE(LEFT(TEXT(K33,"00000000"),4))-VALUE(LEFT(F33,4)))*12+(VALUE(MID(TEXT(K33,"00000000"),5,2))-VALUE(MID(F33,5,2))),"") | AC33: =IF(OR(L33="",NOT(ISNUMBER(L33))),0,MAX(0,MIN(60,(VALUE(LEFT(F33,4))-VALUE(LEFT(TEXT(L33,"00000000"),4)))*12+(VALUE(MID(F33,5,2))-VALUE(MID(TEXT(L33,"00000000"),5,2)))))) | AD33: =IF(OR(L33="",NOT(ISNUMBER(L33))),0,IF(VALUE(F33)<VALUE(LEFT(TEXT(L33,"00000000"),6)),1,0)) | AE33: =IF(OR(M33="",NOT(ISNUMBER(M33))),0,IF(VALUE(F33)<VALUE(LEFT(TEXT(M33,"00000000"),6)),1,0)) | AF33: =IF(AND(AD33=0,AE33=0),1,0) | AG33: =IF(ISNUMBER(X33),X33,IFERROR(VALUE(LEFT(TEXT(J33,"00000000"),4)),"")) | AH33: =IFERROR(XLOOKUP(AG33,Vintage_Rates!$A$2:$A$1000,Vintage_Rates!$B$2:$B$1000,""),"") | AI33: =IF(ISNUMBER(Y33),Y33,IFERROR((G33-AH33)*100,"")) | AJ33: =IF(ISNUMBER(V33),V33,IFERROR(XLOOKUP(VALUE(F33),PLC_Rates!$A$2:$A$1000,PLC_Rates!$B$2:$B$1000,""),"")) | AK33: =IF(ISNUMBER(Z33),Z33,IF(AE33=0,0,MAX(0,MIN(10,((VALUE(LEFT(TEXT(M33,"00000000"),4))-VALUE(LEFT(F33,4)))*12+(VALUE(MID(TEXT(M33,"00000000"),5,2))-VALUE(MID(F33,5,2))))/12)))) | AL33: =IFERROR(G33*100-AJ33,"") | AM33: =IFERROR(G33*100-(AJ33+(1+AK33)*12.5),"") | AN33: =IFERROR(MIN(H33/1000000,100),"") | AO33: =IFERROR(INDEX(FHA_Lookup!$B$2:$B$11,MATCH(TRUE,ISNUMBER(SEARCH(FHA_Lookup!$A$2:$A$11,UPPER(SUBSTITUTE(O33," ","")))),0)),"OTHER") | AP33: =IFERROR(INDEX(FHA_Lookup!$C$2:$C$11,MATCH(TRUE,ISNUMBER(SEARCH(FHA_Lookup!$A$2:$A$11,UPPER(SUBSTITUTE(O33," ","")))),0)),"OTHER") | AQ33: =IF(AP33="NC",1,0) | AR33: =IF(UPPER(TRIM(P33))="AFF",1,0) | AS33: =IF(UPPER(TRIM(P33))="BAF",1,0) | AT33: =IF(UPPER(TRIM(P33))="MKT",1,0) | AU33: =IF(AO33="221d4",1,0) | AV33: =IF(AO33="223a7",1,0) | AW33: =IF(AO33="232",1,0) | AX33: =IF(AO33="538",1,0) | AY33: =IF(AO33="241",1,0) | AZ33: =IF(AO33="220",1,0) | BA33: =IF(AO33="OTHER",1,0) | BB33: =IF(UPPER(TRIM(C33))="LM",1,0) | BC33: =IF(UPPER(TRIM(C33))="PN",1,0) | BD33: =IF(UPPER(TRIM(C33))="LS",1,0) | BE33: =IF(UPPER(TRIM(C33))="RX",1,0) | BF33: =IFERROR((Parameters!$C$6*AM33+Parameters!$C$7*MAX(AM33-(-150),0)+Parameters!$C$8*MAX(AM33-(-50),0)+Parameters!$C$9*MAX(AM33-(0),0)+Parameters!$C$10*MAX(AM33-(50),0)+Parameters!$C$11*MAX(AM33-(100),0)+Parameters!$C$12*MAX(AM33-(150),0)+Parameters!$C$13*MAX(AM33-(250),0)),0) | BG33: =IFERROR((Parameters!$C$14*AA33+Parameters!$C$15*MAX(AA33-(12),0)+Parameters!$C$16*MAX(AA33-(36),0)+Parameters!$C$17*MAX(AA33-(60),0)+Parameters!$C$18*MAX(AA33-(84),0)+Parameters!$C$19*MAX(AA33-(120),0)+Parameters!$C$20*MAX(AA33-(180),0)),0) | BH33: =IFERROR((Parameters!$C$21*AK33+Parameters!$C$22*MAX(AK33-(0),0)+Parameters!$C$23*MAX(AK33-(2),0)+Parameters!$C$24*MAX(AK33-(5),0)+Parameters!$C$25*MAX(AK33-(8),0)),0) | BI33: =IFERROR((Parameters!$C$26*AI33+Parameters!$C$27*MAX(AI33-(-100),0)+Parameters!$C$28*MAX(AI33-(-25),0)+Parameters!$C$29*MAX(AI33-(25),0)+Parameters!$C$30*MAX(AI33-(100),0)),0) | BJ33: =IFERROR((Parameters!$C$31*AN33+Parameters!$C$32*MAX(AN33-(2),0)+Parameters!$C$33*MAX(AN33-(10),0)+Parameters!$C$34*MAX(AN33-(25),0)),0) | BK33: =IFERROR((Parameters!$C$35*AB33+Parameters!$C$36*MAX(AB33-(12),0)+Parameters!$C$37*MAX(AB33-(24),0)+Parameters!$C$38*MAX(AB33-(60),0)),0) | BL33: =IFERROR((Parameters!$C$39*AC33+Parameters!$C$40*MAX(AC33-(6),0)+Parameters!$C$41*MAX(AC33-(12),0)+Parameters!$C$42*MAX(AC33-(24),0)),0) | BM33: =IFERROR(Parameters!$C$43*(MAX(AM33,0)*MIN(MAX(AK33,0),10))/100,0) | BN33: =Parameters!$C$44*AE33 | BO33: =Parameters!$C$45*AU33 + Parameters!$C$46*AV33 + Parameters!$C$47*AW33 + Parameters!$C$48*AX33 + Parameters!$C$49*AY33 + Parameters!$C$50*AZ33 + Parameters!$C$51*BA33 | BP33: =Parameters!$C$52*AQ33 | BQ33: =Parameters!$C$53*AR33+Parameters!$C$54*AS33+Parameters!$C$55*AT33 | BR33: =Parameters!$C$56*BB33+Parameters!$C$57*BC33+Parameters!$C$58*BD33+Parameters!$C$59*BE33 | BS33: =Parameters!$B$2 | BT33: =BS33+BF33 + BG33 + BH33 + BI33 + BJ33 + BK33 + BL33 + BM33 + BN33 + BO33 + BP33 + BQ33 + BR33 | BU33: =IF(AD33=1,0,1/(1+EXP(-BT33))*Parameters!$B$3) | BV33: =(1-(1-BU33)^12)*100 | BW33: =IF(AD33=1,0,(1-(1-1/(1+EXP(-Parameters!$B$2)))^12)*100) | BX33: =IF(AD33=1,0,BV33-(1-(1-(1/(1+EXP(-(BT33-BF33)))*Parameters!$B$3))^12)*100) | BY33: =IF(AD33=1,0,BV33-(1-(1-(1/(1+EXP(-(BT33-BG33)))*Parameters!$B$3))^12)*100) | BZ33: =IF(AD33=1,0,BV33-(1-(1-(1/(1+EXP(-(BT33-BH33)))*Parameters!$B$3))^12)*100) | CA33: =IF(AD33=1,0,BV33-(1-(1-(1/(1+EXP(-(BT33-BI33)))*Parameters!$B$3))^12)*100) | CB33: =IF(AD33=1,0,BV33-(1-(1-(1/(1+EXP(-(BT33-BJ33)))*Parameters!$B$3))^12)*100) | CC33: =IF(AD33=1,0,BV33-(1-(1-(1/(1+EXP(-(BT33-BK33)))*Parameters!$B$3))^12)*100) | CD33: =IF(AD33=1,0,BV33-(1-(1-(1/(1+EXP(-(BT33-BL33)))*Parameters!$B$3))^12)*100) | CE33: =IF(AD33=1,0,BV33-(1-(1-(1/(1+EXP(-(BT33-BM33)))*Parameters!$B$3))^12)*100) | CF33: =IF(AD33=1,0,BV33-(1-(1-(1/(1+EXP(-(BT33-BN33)))*Parameters!$B$3))^12)*100) | CG33: =IF(AD33=1,0,BV33-(1-(1-(1/(1+EXP(-(BT33-BO33)))*Parameters!$B$3))^12)*100) | CH33: =IF(AD33=1,0,BV33-(1-(1-(1/(1+EXP(-(BT33-BP33)))*Parameters!$B$3))^12)*100) | CI33: =IF(AD33=1,0,BV33-(1-(1-(1/(1+EXP(-(BT33-BQ33)))*Parameters!$B$3))^12)*100) | CJ33: =IF(AD33=1,0,BV33-(1-(1-(1/(1+EXP(-(BT33-BR33)))*Parameters!$B$3))^12)*100)
A34: GNR_2024_NEW | B34: 3618B24K2 | C34: PN | D34: REGIONS BANK | E34: 3618B24K2_000000006322127 | F34: 202603 | G34: 6.34 | H34: 7344488.9 | I34: 396 | J34: 20240515 | K34: 20570601 | M34: 20340701 | N34: 10 | O34: 232/223(F) | P34: MKT | T34: FL | U34: 53 | V34: 490.5 | W34: 22 | X34: 2024 | Y34: 56 | Z34: 10 | AA34: =IF(ISNUMBER(W34),W34,IFERROR(MAX(0,(VALUE(LEFT(F34,4))-VALUE(LEFT(TEXT(J34,"00000000"),4)))*12+(VALUE(MID(F34,5,2))-VALUE(MID(TEXT(J34,"00000000"),5,2)))),"")) | AB34: =IFERROR((VALUE(LEFT(TEXT(K34,"00000000"),4))-VALUE(LEFT(F34,4)))*12+(VALUE(MID(TEXT(K34,"00000000"),5,2))-VALUE(MID(F34,5,2))),"") | AC34: =IF(OR(L34="",NOT(ISNUMBER(L34))),0,MAX(0,MIN(60,(VALUE(LEFT(F34,4))-VALUE(LEFT(TEXT(L34,"00000000"),4)))*12+(VALUE(MID(F34,5,2))-VALUE(MID(TEXT(L34,"00000000"),5,2)))))) | AD34: =IF(OR(L34="",NOT(ISNUMBER(L34))),0,IF(VALUE(F34)<VALUE(LEFT(TEXT(L34,"00000000"),6)),1,0)) | AE34: =IF(OR(M34="",NOT(ISNUMBER(M34))),0,IF(VALUE(F34)<VALUE(LEFT(TEXT(M34,"00000000"),6)),1,0)) | AF34: =IF(AND(AD34=0,AE34=0),1,0) | AG34: =IF(ISNUMBER(X34),X34,IFERROR(VALUE(LEFT(TEXT(J34,"00000000"),4)),"")) | AH34: =IFERROR(XLOOKUP(AG34,Vintage_Rates!$A$2:$A$1000,Vintage_Rates!$B$2:$B$1000,""),"") | AI34: =IF(ISNUMBER(Y34),Y34,IFERROR((G34-AH34)*100,"")) | AJ34: =IF(ISNUMBER(V34),V34,IFERROR(XLOOKUP(VALUE(F34),PLC_Rates!$A$2:$A$1000,PLC_Rates!$B$2:$B$1000,""),"")) | AK34: =IF(ISNUMBER(Z34),Z34,IF(AE34=0,0,MAX(0,MIN(10,((VALUE(LEFT(TEXT(M34,"00000000"),4))-VALUE(LEFT(F34,4)))*12+(VALUE(MID(TEXT(M34,"00000000"),5,2))-VALUE(MID(F34,5,2))))/12)))) | AL34: =IFERROR(G34*100-AJ34,"") | AM34: =IFERROR(G34*100-(AJ34+(1+AK34)*12.5),"") | AN34: =IFERROR(MIN(H34/1000000,100),"") | AO34: =IFERROR(INDEX(FHA_Lookup!$B$2:$B$11,MATCH(TRUE,ISNUMBER(SEARCH(FHA_Lookup!$A$2:$A$11,UPPER(SUBSTITUTE(O34," ","")))),0)),"OTHER") | AP34: =IFERROR(INDEX(FHA_Lookup!$C$2:$C$11,MATCH(TRUE,ISNUMBER(SEARCH(FHA_Lookup!$A$2:$A$11,UPPER(SUBSTITUTE(O34," ","")))),0)),"OTHER") | AQ34: =IF(AP34="NC",1,0) | AR34: =IF(UPPER(TRIM(P34))="AFF",1,0) | AS34: =IF(UPPER(TRIM(P34))="BAF",1,0) | AT34: =IF(UPPER(TRIM(P34))="MKT",1,0) | AU34: =IF(AO34="221d4",1,0) | AV34: =IF(AO34="223a7",1,0) | AW34: =IF(AO34="232",1,0) | AX34: =IF(AO34="538",1,0) | AY34: =IF(AO34="241",1,0) | AZ34: =IF(AO34="220",1,0) | BA34: =IF(AO34="OTHER",1,0) | BB34: =IF(UPPER(TRIM(C34))="LM",1,0) | BC34: =IF(UPPER(TRIM(C34))="PN",1,0) | BD34: =IF(UPPER(TRIM(C34))="LS",1,0) | BE34: =IF(UPPER(TRIM(C34))="RX",1,0) | BF34: =IFERROR((Parameters!$C$6*AM34+Parameters!$C$7*MAX(AM34-(-150),0)+Parameters!$C$8*MAX(AM34-(-50),0)+Parameters!$C$9*MAX(AM34-(0),0)+Parameters!$C$10*MAX(AM34-(50),0)+Parameters!$C$11*MAX(AM34-(100),0)+Parameters!$C$12*MAX(AM34-(150),0)+Parameters!$C$13*MAX(AM34-(250),0)),0) | BG34: =IFERROR((Parameters!$C$14*AA34+Parameters!$C$15*MAX(AA34-(12),0)+Parameters!$C$16*MAX(AA34-(36),0)+Parameters!$C$17*MAX(AA34-(60),0)+Parameters!$C$18*MAX(AA34-(84),0)+Parameters!$C$19*MAX(AA34-(120),0)+Parameters!$C$20*MAX(AA34-(180),0)),0) | BH34: =IFERROR((Parameters!$C$21*AK34+Parameters!$C$22*MAX(AK34-(0),0)+Parameters!$C$23*MAX(AK34-(2),0)+Parameters!$C$24*MAX(AK34-(5),0)+Parameters!$C$25*MAX(AK34-(8),0)),0) | BI34: =IFERROR((Parameters!$C$26*AI34+Parameters!$C$27*MAX(AI34-(-100),0)+Parameters!$C$28*MAX(AI34-(-25),0)+Parameters!$C$29*MAX(AI34-(25),0)+Parameters!$C$30*MAX(AI34-(100),0)),0) | BJ34: =IFERROR((Parameters!$C$31*AN34+Parameters!$C$32*MAX(AN34-(2),0)+Parameters!$C$33*MAX(AN34-(10),0)+Parameters!$C$34*MAX(AN34-(25),0)),0) | BK34: =IFERROR((Parameters!$C$35*AB34+Parameters!$C$36*MAX(AB34-(12),0)+Parameters!$C$37*MAX(AB34-(24),0)+Parameters!$C$38*MAX(AB34-(60),0)),0) | BL34: =IFERROR((Parameters!$C$39*AC34+Parameters!$C$40*MAX(AC34-(6),0)+Parameters!$C$41*MAX(AC34-(12),0)+Parameters!$C$42*MAX(AC34-(24),0)),0) | BM34: =IFERROR(Parameters!$C$43*(MAX(AM34,0)*MIN(MAX(AK34,0),10))/100,0) | BN34: =Parameters!$C$44*AE34 | BO34: =Parameters!$C$45*AU34 + Parameters!$C$46*AV34 + Parameters!$C$47*AW34 + Parameters!$C$48*AX34 + Parameters!$C$49*AY34 + Parameters!$C$50*AZ34 + Parameters!$C$51*BA34 | BP34: =Parameters!$C$52*AQ34 | BQ34: =Parameters!$C$53*AR34+Parameters!$C$54*AS34+Parameters!$C$55*AT34 | BR34: =Parameters!$C$56*BB34+Parameters!$C$57*BC34+Parameters!$C$58*BD34+Parameters!$C$59*BE34 | BS34: =Parameters!$B$2 | BT34: =BS34+BF34 + BG34 + BH34 + BI34 + BJ34 + BK34 + BL34 + BM34 + BN34 + BO34 + BP34 + BQ34 + BR34 | BU34: =IF(AD34=1,0,1/(1+EXP(-BT34))*Parameters!$B$3) | BV34: =(1-(1-BU34)^12)*100 | BW34: =IF(AD34=1,0,(1-(1-1/(1+EXP(-Parameters!$B$2)))^12)*100) | BX34: =IF(AD34=1,0,BV34-(1-(1-(1/(1+EXP(-(BT34-BF34)))*Parameters!$B$3))^12)*100) | BY34: =IF(AD34=1,0,BV34-(1-(1-(1/(1+EXP(-(BT34-BG34)))*Parameters!$B$3))^12)*100) | BZ34: =IF(AD34=1,0,BV34-(1-(1-(1/(1+EXP(-(BT34-BH34)))*Parameters!$B$3))^12)*100) | CA34: =IF(AD34=1,0,BV34-(1-(1-(1/(1+EXP(-(BT34-BI34)))*Parameters!$B$3))^12)*100) | CB34: =IF(AD34=1,0,BV34-(1-(1-(1/(1+EXP(-(BT34-BJ34)))*Parameters!$B$3))^12)*100) | CC34: =IF(AD34=1,0,BV34-(1-(1-(1/(1+EXP(-(BT34-BK34)))*Parameters!$B$3))^12)*100) | CD34: =IF(AD34=1,0,BV34-(1-(1-(1/(1+EXP(-(BT34-BL34)))*Parameters!$B$3))^12)*100) | CE34: =IF(AD34=1,0,BV34-(1-(1-(1/(1+EXP(-(BT34-BM34)))*Parameters!$B$3))^12)*100) | CF34: =IF(AD34=1,0,BV34-(1-(1-(1/(1+EXP(-(BT34-BN34)))*Parameters!$B$3))^12)*100) | CG34: =IF(AD34=1,0,BV34-(1-(1-(1/(1+EXP(-(BT34-BO34)))*Parameters!$B$3))^12)*100) | CH34: =IF(AD34=1,0,BV34-(1-(1-(1/(1+EXP(-(BT34-BP34)))*Parameters!$B$3))^12)*100) | CI34: =IF(AD34=1,0,BV34-(1-(1-(1/(1+EXP(-(BT34-BQ34)))*Parameters!$B$3))^12)*100) | CJ34: =IF(AD34=1,0,BV34-(1-(1-(1/(1+EXP(-(BT34-BR34)))*Parameters!$B$3))^12)*100)
A35: GNR_2024_NEW | B35: 3618H6UY8 | C35: PN | D35: VIUM CAPITAL MORTGAGE, LLC. | E35: 3618H6UY8_000000004222444 | F35: 202603 | G35: 5.95 | H35: 10578550 | I35: 420 | J35: 20250201 | K35: 20600301 | M35: 20350401 | N35: 10 | O35: 232/223(F) | T35: OH | U35: 116 | V35: 490.5 | W35: 13 | X35: 2025 | Y35: 13 | Z35: 10 | AA35: =IF(ISNUMBER(W35),W35,IFERROR(MAX(0,(VALUE(LEFT(F35,4))-VALUE(LEFT(TEXT(J35,"00000000"),4)))*12+(VALUE(MID(F35,5,2))-VALUE(MID(TEXT(J35,"00000000"),5,2)))),"")) | AB35: =IFERROR((VALUE(LEFT(TEXT(K35,"00000000"),4))-VALUE(LEFT(F35,4)))*12+(VALUE(MID(TEXT(K35,"00000000"),5,2))-VALUE(MID(F35,5,2))),"") | AC35: =IF(OR(L35="",NOT(ISNUMBER(L35))),0,MAX(0,MIN(60,(VALUE(LEFT(F35,4))-VALUE(LEFT(TEXT(L35,"00000000"),4)))*12+(VALUE(MID(F35,5,2))-VALUE(MID(TEXT(L35,"00000000"),5,2)))))) | AD35: =IF(OR(L35="",NOT(ISNUMBER(L35))),0,IF(VALUE(F35)<VALUE(LEFT(TEXT(L35,"00000000"),6)),1,0)) | AE35: =IF(OR(M35="",NOT(ISNUMBER(M35))),0,IF(VALUE(F35)<VALUE(LEFT(TEXT(M35,"00000000"),6)),1,0)) | AF35: =IF(AND(AD35=0,AE35=0),1,0) | AG35: =IF(ISNUMBER(X35),X35,IFERROR(VALUE(LEFT(TEXT(J35,"00000000"),4)),"")) | AH35: =IFERROR(XLOOKUP(AG35,Vintage_Rates!$A$2:$A$1000,Vintage_Rates!$B$2:$B$1000,""),"") | AI35: =IF(ISNUMBER(Y35),Y35,IFERROR((G35-AH35)*100,"")) | AJ35: =IF(ISNUMBER(V35),V35,IFERROR(XLOOKUP(VALUE(F35),PLC_Rates!$A$2:$A$1000,PLC_Rates!$B$2:$B$1000,""),"")) | AK35: =IF(ISNUMBER(Z35),Z35,IF(AE35=0,0,MAX(0,MIN(10,((VALUE(LEFT(TEXT(M35,"00000000"),4))-VALUE(LEFT(F35,4)))*12+(VALUE(MID(TEXT(M35,"00000000"),5,2))-VALUE(MID(F35,5,2))))/12)))) | AL35: =IFERROR(G35*100-AJ35,"") | AM35: =IFERROR(G35*100-(AJ35+(1+AK35)*12.5),"") | AN35: =IFERROR(MIN(H35/1000000,100),"") | AO35: =IFERROR(INDEX(FHA_Lookup!$B$2:$B$11,MATCH(TRUE,ISNUMBER(SEARCH(FHA_Lookup!$A$2:$A$11,UPPER(SUBSTITUTE(O35," ","")))),0)),"OTHER") | AP35: =IFERROR(INDEX(FHA_Lookup!$C$2:$C$11,MATCH(TRUE,ISNUMBER(SEARCH(FHA_Lookup!$A$2:$A$11,UPPER(SUBSTITUTE(O35," ","")))),0)),"OTHER") | AQ35: =IF(AP35="NC",1,0) | AR35: =IF(UPPER(TRIM(P35))="AFF",1,0) | AS35: =IF(UPPER(TRIM(P35))="BAF",1,0) | AT35: =IF(UPPER(TRIM(P35))="MKT",1,0) | AU35: =IF(AO35="221d4",1,0) | AV35: =IF(AO35="223a7",1,0) | AW35: =IF(AO35="232",1,0) | AX35: =IF(AO35="538",1,0) | AY35: =IF(AO35="241",1,0) | AZ35: =IF(AO35="220",1,0) | BA35: =IF(AO35="OTHER",1,0) | BB35: =IF(UPPER(TRIM(C35))="LM",1,0) | BC35: =IF(UPPER(TRIM(C35))="PN",1,0) | BD35: =IF(UPPER(TRIM(C35))="LS",1,0) | BE35: =IF(UPPER(TRIM(C35))="RX",1,0) | BF35: =IFERROR((Parameters!$C$6*AM35+Parameters!$C$7*MAX(AM35-(-150),0)+Parameters!$C$8*MAX(AM35-(-50),0)+Parameters!$C$9*MAX(AM35-(0),0)+Parameters!$C$10*MAX(AM35-(50),0)+Parameters!$C$11*MAX(AM35-(100),0)+Parameters!$C$12*MAX(AM35-(150),0)+Parameters!$C$13*MAX(AM35-(250),0)),0) | BG35: =IFERROR((Parameters!$C$14*AA35+Parameters!$C$15*MAX(AA35-(12),0)+Parameters!$C$16*MAX(AA35-(36),0)+Parameters!$C$17*MAX(AA35-(60),0)+Parameters!$C$18*MAX(AA35-(84),0)+Parameters!$C$19*MAX(AA35-(120),0)+Parameters!$C$20*MAX(AA35-(180),0)),0) | BH35: =IFERROR((Parameters!$C$21*AK35+Parameters!$C$22*MAX(AK35-(0),0)+Parameters!$C$23*MAX(AK35-(2),0)+Parameters!$C$24*MAX(AK35-(5),0)+Parameters!$C$25*MAX(AK35-(8),0)),0) | BI35: =IFERROR((Parameters!$C$26*AI35+Parameters!$C$27*MAX(AI35-(-100),0)+Parameters!$C$28*MAX(AI35-(-25),0)+Parameters!$C$29*MAX(AI35-(25),0)+Parameters!$C$30*MAX(AI35-(100),0)),0) | BJ35: =IFERROR((Parameters!$C$31*AN35+Parameters!$C$32*MAX(AN35-(2),0)+Parameters!$C$33*MAX(AN35-(10),0)+Parameters!$C$34*MAX(AN35-(25),0)),0) | BK35: =IFERROR((Parameters!$C$35*AB35+Parameters!$C$36*MAX(AB35-(12),0)+Parameters!$C$37*MAX(AB35-(24),0)+Parameters!$C$38*MAX(AB35-(60),0)),0) | BL35: =IFERROR((Parameters!$C$39*AC35+Parameters!$C$40*MAX(AC35-(6),0)+Parameters!$C$41*MAX(AC35-(12),0)+Parameters!$C$42*MAX(AC35-(24),0)),0) | BM35: =IFERROR(Parameters!$C$43*(MAX(AM35,0)*MIN(MAX(AK35,0),10))/100,0) | BN35: =Parameters!$C$44*AE35 | BO35: =Parameters!$C$45*AU35 + Parameters!$C$46*AV35 + Parameters!$C$47*AW35 + Parameters!$C$48*AX35 + Parameters!$C$49*AY35 + Parameters!$C$50*AZ35 + Parameters!$C$51*BA35 | BP35: =Parameters!$C$52*AQ35 | BQ35: =Parameters!$C$53*AR35+Parameters!$C$54*AS35+Parameters!$C$55*AT35 | BR35: =Parameters!$C$56*BB35+Parameters!$C$57*BC35+Parameters!$C$58*BD35+Parameters!$C$59*BE35 | BS35: =Parameters!$B$2 | BT35: =BS35+BF35 + BG35 + BH35 + BI35 + BJ35 + BK35 + BL35 + BM35 + BN35 + BO35 + BP35 + BQ35 + BR35 | BU35: =IF(AD35=1,0,1/(1+EXP(-BT35))*Parameters!$B$3) | BV35: =(1-(1-BU35)^12)*100 | BW35: =IF(AD35=1,0,(1-(1-1/(1+EXP(-Parameters!$B$2)))^12)*100) | BX35: =IF(AD35=1,0,BV35-(1-(1-(1/(1+EXP(-(BT35-BF35)))*Parameters!$B$3))^12)*100) | BY35: =IF(AD35=1,0,BV35-(1-(1-(1/(1+EXP(-(BT35-BG35)))*Parameters!$B$3))^12)*100) | BZ35: =IF(AD35=1,0,BV35-(1-(1-(1/(1+EXP(-(BT35-BH35)))*Parameters!$B$3))^12)*100) | CA35: =IF(AD35=1,0,BV35-(1-(1-(1/(1+EXP(-(BT35-BI35)))*Parameters!$B$3))^12)*100) | CB35: =IF(AD35=1,0,BV35-(1-(1-(1/(1+EXP(-(BT35-BJ35)))*Parameters!$B$3))^12)*100) | CC35: =IF(AD35=1,0,BV35-(1-(1-(1/(1+EXP(-(BT35-BK35)))*Parameters!$B$3))^12)*100) | CD35: =IF(AD35=1,0,BV35-(1-(1-(1/(1+EXP(-(BT35-BL35)))*Parameters!$B$3))^12)*100) | CE35: =IF(AD35=1,0,BV35-(1-(1-(1/(1+EXP(-(BT35-BM35)))*Parameters!$B$3))^12)*100) | CF35: =IF(AD35=1,0,BV35-(1-(1-(1/(1+EXP(-(BT35-BN35)))*Parameters!$B$3))^12)*100) | CG35: =IF(AD35=1,0,BV35-(1-(1-(1/(1+EXP(-(BT35-BO35)))*Parameters!$B$3))^12)*100) | CH35: =IF(AD35=1,0,BV35-(1-(1-(1/(1+EXP(-(BT35-BP35)))*Parameters!$B$3))^12)*100) | CI35: =IF(AD35=1,0,BV35-(1-(1-(1/(1+EXP(-(BT35-BQ35)))*Parameters!$B$3))^12)*100) | CJ35: =IF(AD35=1,0,BV35-(1-(1-(1/(1+EXP(-(BT35-BR35)))*Parameters!$B$3))^12)*100)
A36: GNR_2024_NEW | B36: 3618V5GR5 | C36: PN | D36: MERCHANTS CAPITAL CORP. | E36: 3618V5GR5_000000008611148 | F36: 202603 | G36: 5.48 | H36: 1420076.7 | I36: 420 | J36: 20260101 | K36: 20610201 | M36: 20360301 | N36: 10 | O36: 207/223(F) | T36: TN | U36: 50 | V36: 490.5 | W36: 2 | X36: 2026 | Y36: 7 | Z36: 10 | AA36: =IF(ISNUMBER(W36),W36,IFERROR(MAX(0,(VALUE(LEFT(F36,4))-VALUE(LEFT(TEXT(J36,"00000000"),4)))*12+(VALUE(MID(F36,5,2))-VALUE(MID(TEXT(J36,"00000000"),5,2)))),"")) | AB36: =IFERROR((VALUE(LEFT(TEXT(K36,"00000000"),4))-VALUE(LEFT(F36,4)))*12+(VALUE(MID(TEXT(K36,"00000000"),5,2))-VALUE(MID(F36,5,2))),"") | AC36: =IF(OR(L36="",NOT(ISNUMBER(L36))),0,MAX(0,MIN(60,(VALUE(LEFT(F36,4))-VALUE(LEFT(TEXT(L36,"00000000"),4)))*12+(VALUE(MID(F36,5,2))-VALUE(MID(TEXT(L36,"00000000"),5,2)))))) | AD36: =IF(OR(L36="",NOT(ISNUMBER(L36))),0,IF(VALUE(F36)<VALUE(LEFT(TEXT(L36,"00000000"),6)),1,0)) | AE36: =IF(OR(M36="",NOT(ISNUMBER(M36))),0,IF(VALUE(F36)<VALUE(LEFT(TEXT(M36,"00000000"),6)),1,0)) | AF36: =IF(AND(AD36=0,AE36=0),1,0) | AG36: =IF(ISNUMBER(X36),X36,IFERROR(VALUE(LEFT(TEXT(J36,"00000000"),4)),"")) | AH36: =IFERROR(XLOOKUP(AG36,Vintage_Rates!$A$2:$A$1000,Vintage_Rates!$B$2:$B$1000,""),"") | AI36: =IF(ISNUMBER(Y36),Y36,IFERROR((G36-AH36)*100,"")) | AJ36: =IF(ISNUMBER(V36),V36,IFERROR(XLOOKUP(VALUE(F36),PLC_Rates!$A$2:$A$1000,PLC_Rates!$B$2:$B$1000,""),"")) | AK36: =IF(ISNUMBER(Z36),Z36,IF(AE36=0,0,MAX(0,MIN(10,((VALUE(LEFT(TEXT(M36,"00000000"),4))-VALUE(LEFT(F36,4)))*12+(VALUE(MID(TEXT(M36,"00000000"),5,2))-VALUE(MID(F36,5,2))))/12)))) | AL36: =IFERROR(G36*100-AJ36,"") | AM36: =IFERROR(G36*100-(AJ36+(1+AK36)*12.5),"") | AN36: =IFERROR(MIN(H36/1000000,100),"") | AO36: =IFERROR(INDEX(FHA_Lookup!$B$2:$B$11,MATCH(TRUE,ISNUMBER(SEARCH(FHA_Lookup!$A$2:$A$11,UPPER(SUBSTITUTE(O36," ","")))),0)),"OTHER") | AP36: =IFERROR(INDEX(FHA_Lookup!$C$2:$C$11,MATCH(TRUE,ISNUMBER(SEARCH(FHA_Lookup!$A$2:$A$11,UPPER(SUBSTITUTE(O36," ","")))),0)),"OTHER") | AQ36: =IF(AP36="NC",1,0) | AR36: =IF(UPPER(TRIM(P36))="AFF",1,0) | AS36: =IF(UPPER(TRIM(P36))="BAF",1,0) | AT36: =IF(UPPER(TRIM(P36))="MKT",1,0) | AU36: =IF(AO36="221d4",1,0) | AV36: =IF(AO36="223a7",1,0) | AW36: =IF(AO36="232",1,0) | AX36: =IF(AO36="538",1,0) | AY36: =IF(AO36="241",1,0) | AZ36: =IF(AO36="220",1,0) | BA36: =IF(AO36="OTHER",1,0) | BB36: =IF(UPPER(TRIM(C36))="LM",1,0) | BC36: =IF(UPPER(TRIM(C36))="PN",1,0) | BD36: =IF(UPPER(TRIM(C36))="LS",1,0) | BE36: =IF(UPPER(TRIM(C36))="RX",1,0) | BF36: =IFERROR((Parameters!$C$6*AM36+Parameters!$C$7*MAX(AM36-(-150),0)+Parameters!$C$8*MAX(AM36-(-50),0)+Parameters!$C$9*MAX(AM36-(0),0)+Parameters!$C$10*MAX(AM36-(50),0)+Parameters!$C$11*MAX(AM36-(100),0)+Parameters!$C$12*MAX(AM36-(150),0)+Parameters!$C$13*MAX(AM36-(250),0)),0) | BG36: =IFERROR((Parameters!$C$14*AA36+Parameters!$C$15*MAX(AA36-(12),0)+Parameters!$C$16*MAX(AA36-(36),0)+Parameters!$C$17*MAX(AA36-(60),0)+Parameters!$C$18*MAX(AA36-(84),0)+Parameters!$C$19*MAX(AA36-(120),0)+Parameters!$C$20*MAX(AA36-(180),0)),0) | BH36: =IFERROR((Parameters!$C$21*AK36+Parameters!$C$22*MAX(AK36-(0),0)+Parameters!$C$23*MAX(AK36-(2),0)+Parameters!$C$24*MAX(AK36-(5),0)+Parameters!$C$25*MAX(AK36-(8),0)),0) | BI36: =IFERROR((Parameters!$C$26*AI36+Parameters!$C$27*MAX(AI36-(-100),0)+Parameters!$C$28*MAX(AI36-(-25),0)+Parameters!$C$29*MAX(AI36-(25),0)+Parameters!$C$30*MAX(AI36-(100),0)),0) | BJ36: =IFERROR((Parameters!$C$31*AN36+Parameters!$C$32*MAX(AN36-(2),0)+Parameters!$C$33*MAX(AN36-(10),0)+Parameters!$C$34*MAX(AN36-(25),0)),0) | BK36: =IFERROR((Parameters!$C$35*AB36+Parameters!$C$36*MAX(AB36-(12),0)+Parameters!$C$37*MAX(AB36-(24),0)+Parameters!$C$38*MAX(AB36-(60),0)),0) | BL36: =IFERROR((Parameters!$C$39*AC36+Parameters!$C$40*MAX(AC36-(6),0)+Parameters!$C$41*MAX(AC36-(12),0)+Parameters!$C$42*MAX(AC36-(24),0)),0) | BM36: =IFERROR(Parameters!$C$43*(MAX(AM36,0)*MIN(MAX(AK36,0),10))/100,0) | BN36: =Parameters!$C$44*AE36 | BO36: =Parameters!$C$45*AU36 + Parameters!$C$46*AV36 + Parameters!$C$47*AW36 + Parameters!$C$48*AX36 + Parameters!$C$49*AY36 + Parameters!$C$50*AZ36 + Parameters!$C$51*BA36 | BP36: =Parameters!$C$52*AQ36 | BQ36: =Parameters!$C$53*AR36+Parameters!$C$54*AS36+Parameters!$C$55*AT36 | BR36: =Parameters!$C$56*BB36+Parameters!$C$57*BC36+Parameters!$C$58*BD36+Parameters!$C$59*BE36 | BS36: =Parameters!$B$2 | BT36: =BS36+BF36 + BG36 + BH36 + BI36 + BJ36 + BK36 + BL36 + BM36 + BN36 + BO36 + BP36 + BQ36 + BR36 | BU36: =IF(AD36=1,0,1/(1+EXP(-BT36))*Parameters!$B$3) | BV36: =(1-(1-BU36)^12)*100 | BW36: =IF(AD36=1,0,(1-(1-1/(1+EXP(-Parameters!$B$2)))^12)*100) | BX36: =IF(AD36=1,0,BV36-(1-(1-(1/(1+EXP(-(BT36-BF36)))*Parameters!$B$3))^12)*100) | BY36: =IF(AD36=1,0,BV36-(1-(1-(1/(1+EXP(-(BT36-BG36)))*Parameters!$B$3))^12)*100) | BZ36: =IF(AD36=1,0,BV36-(1-(1-(1/(1+EXP(-(BT36-BH36)))*Parameters!$B$3))^12)*100) | CA36: =IF(AD36=1,0,BV36-(1-(1-(1/(1+EXP(-(BT36-BI36)))*Parameters!$B$3))^12)*100) | CB36: =IF(AD36=1,0,BV36-(1-(1-(1/(1+EXP(-(BT36-BJ36)))*Parameters!$B$3))^12)*100) | CC36: =IF(AD36=1,0,BV36-(1-(1-(1/(1+EXP(-(BT36-BK36)))*Parameters!$B$3))^12)*100) | CD36: =IF(AD36=1,0,BV36-(1-(1-(1/(1+EXP(-(BT36-BL36)))*Parameters!$B$3))^12)*100) | CE36: =IF(AD36=1,0,BV36-(1-(1-(1/(1+EXP(-(BT36-BM36)))*Parameters!$B$3))^12)*100) | CF36: =IF(AD36=1,0,BV36-(1-(1-(1/(1+EXP(-(BT36-BN36)))*Parameters!$B$3))^12)*100) | CG36: =IF(AD36=1,0,BV36-(1-(1-(1/(1+EXP(-(BT36-BO36)))*Parameters!$B$3))^12)*100) | CH36: =IF(AD36=1,0,BV36-(1-(1-(1/(1+EXP(-(BT36-BP36)))*Parameters!$B$3))^12)*100) | CI36: =IF(AD36=1,0,BV36-(1-(1-(1/(1+EXP(-(BT36-BQ36)))*Parameters!$B$3))^12)*100) | CJ36: =IF(AD36=1,0,BV36-(1-(1-(1/(1+EXP(-(BT36-BR36)))*Parameters!$B$3))^12)*100)
